Workbook

Sheet Start_Here
B1: Northfield Nutrition (fictional): operations workbook
B2: Portfolio demonstration with invented sample data, not client work.
B4: What this workbook does
C5: One file for the product catalog, suppliers, purchase orders, the inventory ledger, lots and expiry dates, reservations, marketing campaigns, milestones, tasks and documents. The Dashboard calculates stock, alerts and record checks from those sheets with formulas, using the as-of date on Config.
C6: Every number on the Dashboard is a formula over the other sheets. Nothing is typed into the Dashboard.
B8: Sheet guide
B9: Sheet | C9: Purpose | D9: Who types here
B10: Start_Here | C10: How the workbook works: adding records, colour key, rules, import steps, backup and recovery. | D10: Read only
B11: Dashboard | C11: Stock by SKU, reorder alerts, outstanding and overdue purchase orders, lots near expiry, open tasks, record checks, import status and a marketing summary. Formulas only. | D11: Read only
B12: Config | C12: As-of date, expiry windows, reorder and reservation rules, dropdown lists and the import check catalog. | D12: Operations lead
B13: Products | C13: Product catalog with opening balances and reorder rules. Stock columns calculate from the ledger, lots and reservations. Room for 100 rows. | D13: Operations
B14: Suppliers | C14: Supplier and manufacturing partner directory. Room for 50 rows. | D14: Operations
B15: Purchase_Orders | C15: Purchase orders and expected deliveries. Received quantities come from ledger receipts. Room for 300 rows. | D15: Purchasing
B16: Inventory_Ledger | C16: Every receipt, shipment and adjustment with lot, reference and source link. Room for 2,000 rows. | D16: Operations, import
B17: Batches | C17: Lots with company-supplied expiry dates. Lot balances, days left and expiry windows calculate. Room for 300 rows. | D17: Quality
B18: Reservations | C18: Stock set aside for orders or campaigns. Config decides which statuses count. Room for 200 rows. | D18: Sales, marketing
B19: Marketing | C19: Campaign tracker: products, channel, owner, deadlines, approval, assets, planned vs actual spend, platform-attributed revenue and company sales kept apart. Room for 100 rows. | D19: Marketing
B20: Metric_Definitions | C20: What every number means and what a blank means. | D20: Operations lead
... B26: Ready_To_Post | C26: The Ready rows of Import_Staging laid out in the column order of Inventory_Ledger, and new lots from receipts in the column order of Batches, ready to paste as values. | D26: Read only
B28: How to add a record
B29: Step 1 | C29: Go to the first empty row of the sheet. Records start on row 2.
B30: Step 2 | C30: Type only in columns with a dark blue header. A * in the header means the field is required; the header note says what goes in it.
B31: Step 3 | C31: Use the dropdowns for statuses and for SKU, supplier and lot IDs. IDs must be unique: a repeated ID is refused or flagged.
B32: Step 4 | C32: Grey-header columns calculate by themselves and are locked. Do not insert rows or columns: each sheet already has formulas in its spare rows (room listed in the sheet guide).
B33: Step 5 | C33: Read the Record check column at the right of the row. It says OK, or names the first problem in the row. The Dashboard counts every row that is not OK.
B35: Colour key
B36: Dark blue header | C36: You type in this column.
B37: Grey header | C37: Calculated column, locked.
B38: Light grey header | C38: Helper column used by the Dashboard or Exceptions lists, locked.
B39: Amber | C39: Attention: below reorder point, lot in the second expiry window, or overdue document review.
B40: Orange | C40: Lot in the first expiry window.
B41: Light yellow | C41: Lot in the third expiry window.
B42: Red | C42: Problem: overdue PO or task, expired lot with stock, negative stock, record check not OK, rejected import row.
B43: Green | C43: Import row ready to post.
B45: Rules (change them on Config)
B46: Recorded stock | C46: Opening balance + receipts - shipments + adjustments, per SKU, from Inventory_Ledger.
B47: Lot balances | C47: Lot opening qty + ledger movements for that lot. The lot balances of a SKU must add up to its recorded stock; Products flags any gap.
B48: Available stock | C48: Recorded stock - reserved - held in lots. Reservations count when their status holds stock on Config, the start date is on or before the as-of date, and the release date is empty or on or after it. Lots count as held when their status holds stock on Config, or when they are expired and Config says expired lots are held.
B49: Reorder alert | C49: The stock chosen on Config (Available or Recorded) is below the SKU's reorder point.
B50: Purchase orders | C50: Open = status counts as open on Config and the ordered qty is not fully received in the ledger. Overdue = open and the expected date is before the as-of date.
B51: Expiry | C51: Days left = company-supplied expiry date - as-of date. Windows come from Config. The workbook tracks the dates it is given; it does not judge product safety.
B52: Marketing | C52: Platform-attributed revenue and company sales sit in separate columns and are never added together. A blank metric means not supplied; nothing is estimated.
B54: Importing a warehouse CSV (agreed layout: the 12 columns of Import_Staging)
B55: Step 1 | C55: Make a backup first (see Backup and recovery).
B56: Step 2 | C56: In Import_Staging, clear columns A to L (dark blue headers) from row 2 down, then paste the CSV rows below the header as values.
B57: Step 3 | C57: Type the file name on Config (File in Import_Staging).
B58: Step 4 | C58: Read the Result column and the Exceptions sheet. Ready rows passed all 23 checks. Each problem in a rejected row is listed in plain words with what to do.
B59: Step 5 | C59: Open Ready_To_Post. Copy the filled rows of the left block and paste them as values into the next empty rows of Inventory_Ledger; copy the filled rows of the right block (new lots from receipts) into the next empty rows of Batches. Both blocks are already in the column order of those sheets.
B60: Step 6 | C60: Clear Import_Staging. Nothing is posted by itself, and a movement ID that is already in Inventory_Ledger is always rejected, so importing the same file twice cannot post a row twice or overwrite a ledger row.
B62: Backup and recovery
C63: Before each import and at each month end, make a dated copy (Google Sheets: File > Make a copy; Excel: Save As), named like Ops-Workbook-2026-10-15.
C64: Google Sheets also keeps version history: File > Version history > See version history, choose a version from before the problem, then Restore this version.
C65: To recover a few rows only, open the dated copy, copy the rows and paste them as values into the live workbook.
C66: Once a month, download a copy (File > Download > Microsoft Excel) and keep it in a shared folder.
B68: Sheet protection in Google Sheets
C69: In this .xlsx file, formula cells are locked with sheet protection (no password) for Excel and LibreOffice. After importing it into Google Sheets, open Data > Protect sheets and ranges to see whether the protection came across. If Google Sheets dropped it, switch it back on there: Add a sheet or range > Sheet, pick the sheet, tick Except certain cells, add the dark blue input columns, then choose who can edit.
B71: Limits of this demo
C72: The data is invented for a portfolio demonstration. Posting Ready import rows is a copy-and-paste step in this file; a real build could add a one-click script for it. There are no charts in this workbook. The HTML milestone report is a separate file built from the Milestones sheet.

Sheet Dashboard
B1: Northfield Nutrition (fictional): operations dashboard | S1: =Config!$B$6 -> 30
B2: Portfolio demonstration with invented sample data, not client work. | S2: =Config!$B$7 -> 60
B3: ="As of "&TEXT(Config!$B$4,"yyyy-mm-dd")&" · every figure is a formula over the record sheets · change the date or the rules on Config" -> As of 2026-10-15 · every figure is a formula over the record sheets · change the date or the rules on Config | S3: =Config!$B$8 -> 90
B5: Stock and purchasing | D5: SKUs tracked | F5: Recorded units | H5: Available units | J5: SKUs below reorder | L5: Open POs | N5: Overdue POs | P5: Open tasks
B6: Each tile is a formula; see Metric_Definitions. | D6: =SUMPRODUCT(--(Products!$A$2:$A$101<>"")) -> 12 | F6: =SUM(Products!$R$2:$R$101) -> 9234 | H6: =SUM(Products!$U$2:$U$101) -> 8048 | J6: =SUM(Products!$Y$2:$Y$101) -> 4 | L6: =SUM(Purchase_Orders!$O$2:$O$301) -> 5 | N6: =SUM(Purchase_Orders!$P$2:$P$301) -> 2 | P6: =SUM(Tasks!$I$2:$I$301) -> 9
D7: ="rows in Products" -> rows in Products | F7: ="opening + receipts - shipments + adjustments" -> opening + receipts - shipments + adjustments | H7: ="recorded - reserved - held in lots" -> recorded - reserved - held in lots | J7: ="test uses "&LOWER(Config!$B$9)&" stock" -> test uses available stock | L7: =TEXT(SUMIFS(Purchase_Orders!$N$2:$N$301,Purchase_Orders!$O$2:$O$301,1),"#,##0")&" units on order" -> 3,560 units on order | N7: ="expected date has passed" -> expected date has passed | P7: =SUM(Tasks!$J$2:$J$301)&" overdue" -> 2 overdue
B9: Expiry, imports and checks | D9: Expired lots with stock | F9: ="Lots expiring in "&0&"-"&Config!$B$6&" days" -> Lots expiring in 0-30 days | H9: ="Lots expiring in "&(Config!$B$6+1)&"-"&Config!$B$7&" days" -> Lots expiring in 31-60 days | J9: ="Lots expiring in "&(Config!$B$7+1)&"-"&Config!$B$8&" days" -> Lots expiring in 61-90 days | L9: Import rows ready | N9: Import exceptions | P9: Record issues
B10: Each tile is a formula; see Metric_Definitions. | D10: =COUNTIFS(Batches!$L$2:$L$301,">0",Batches!$M$2:$M$301,"<0") -> 1 | F10: =COUNTIFS(Batches!$L$2:$L$301,">0",Batches!$M$2:$M$301,">=0",Batches!$M$2:$M$301,"<="&Config!$B$6) -> 3 | H10: =COUNTIFS(Batches!$L$2:$L$301,">0",Batches!$M$2:$M$301,">"&Config!$B$6,Batches!$M$2:$M$301,"<="&Config!$B$7) -> 2 | J10: =COUNTIFS(Batches!$L$2:$L$301,">0",Batches!$M$2:$M$301,">"&Config!$B$7,Batches!$M$2:$M$301,"<="&Config!$B$8) -> 3 | L10: =COUNTIF(Import_Staging!$U$2:$U$301,"Ready") -> 8 | N10: =SUM(Import_Staging!$T$2:$T$301) -> 11 | P10: =$E$107 -> 0
D11: ="expiry date has passed" -> expiry date has passed | F11: ="lots with stock on hand" -> lots with stock on hand | H11: ="lots with stock on hand" -> lots with stock on hand | J11: ="lots with stock on hand" -> lots with stock on hand | L11: ="of "&(COUNTIF(Import_Staging!$U$2:$U$301,"Ready")+COUNTIF(Import_Staging!$U$2:$U$301,"Rejected"))&" rows staged" -> of 18 rows staged | N11: =COUNTIF(Import_Staging!$U$2:$U$301,"Rejected")&" rows rejected" -> 10 rows rejected | P11: ="missing or inconsistent rows" -> missing or inconsistent rows
B13: Reorder alerts
B14: ="SKUs whose "&LOWER(Config!$B$9)&" stock is below the reorder point. Up to 15 shown; the tile counts all." -> SKUs whose available stock is below the reorder point. Up to 15 shown; the tile counts all.
B15: SKU | C15: Product | D15: Recorded | E15: Reserved | F15: Held in lots | G15: Available | H15: Reorder point | I15: Reorder qty | J15: On order | K15: Status | L15: Supplier
A16: =IFERROR(MATCH(1,Products!$AC$2:$AC$101,0),"") -> 1 | B16: =IF($A16="","",INDEX(Products!$A$2:$A$101,$A16)&"") -> WPI-CHO-2LB | C16: =IF($A16="","",INDEX(Products!$B$2:$B$101,$A16)&"") -> Whey Protein Isolate, Chocolate, 2 lb | D16: =IF($A16="","",INDEX(Products!$R$2:$R$101,$A16)) -> 429 | E16: =IF($A16="","",INDEX(Products!$S$2:$S$101,$A16)) -> 120 | F16: =IF($A16="","",INDEX(Products!$T$2:$T$101,$A16)) -> 0 | G16: =IF($A16="","",INDEX(Products!$U$2:$U$101,$A16)) -> 309 | H16: =IF($A16="","",INDEX(Products!$I$2:$I$101,$A16)) -> 600 | I16: =IF($A16="","",INDEX(Products!$J$2:$J$101,$A16)) -> 1500 | J16: =IF($A16="","",INDEX(Products!$V$2:$V$101,$A16)) -> 1500 | K16: =IF($A16="","",INDEX(Products!$Z$2:$Z$101,$A16)&"") -> Below reorder | L16: =IF($A16="","",INDEX(Products!$N$2:$N$101,$A16)&"") -> Alder Creek Dairy Proteins
A17: =IFERROR(MATCH(2,Products!$AC$2:$AC$101,0),"") -> 2 | B17: =IF($A17="","",INDEX(Products!$A$2:$A$101,$A17)&"") -> WPI-VAN-2LB | C17: =IF($A17="","",INDEX(Products!$B$2:$B$101,$A17)&"") -> Whey Protein Isolate, Vanilla, 2 lb | D17: =IF($A17="","",INDEX(Products!$R$2:$R$101,$A17)) -> 808 | E17: =IF($A17="","",INDEX(Products!$S$2:$S$101,$A17)) -> 0 | F17: =IF($A17="","",INDEX(Products!$T$2:$T$101,$A17)) -> 600 | G17: =IF($A17="","",INDEX(Products!$U$2:$U$101,$A17)) -> 208 | H17: =IF($A17="","",INDEX(Products!$I$2:$I$101,$A17)) -> 450 | I17: =IF($A17="","",INDEX(Products!$J$2:$J$101,$A17)) -> 1200 | J17: =IF($A17="","",INDEX(Products!$V$2:$V$101,$A17)) -> 600 | K17: =IF($A17="","",INDEX(Products!$Z$2:$Z$101,$A17)&"") -> Below reorder | L17: =IF($A17="","",INDEX(Products!$N$2:$N$101,$A17)&"") -> Alder Creek Dairy Proteins
A18: =IFERROR(MATCH(3,Products!$AC$2:$AC$101,0),"") -> 5 | B18: =IF($A18="","",INDEX(Products!$A$2:$A$101,$A18)&"") -> PLT-VAN-2LB | C18: =IF($A18="","",INDEX(Products!$B$2:$B$101,$A18)&"") -> Plant Protein, Vanilla, 2 lb | D18: =IF($A18="","",INDEX(Products!$R$2:$R$101,$A18)) -> 133 | E18: =IF($A18="","",INDEX(Products!$S$2:$S$101,$A18)) -> 0 | F18: =IF($A18="","",INDEX(Products!$T$2:$T$101,$A18)) -> 0 | G18: =IF($A18="","",INDEX(Products!$U$2:$U$101,$A18)) -> 133 | H18: =IF($A18="","",INDEX(Products!$I$2:$I$101,$A18)) -> 200 | I18: =IF($A18="","",INDEX(Products!$J$2:$J$101,$A18)) -> 500 | J18: =IF($A18="","",INDEX(Products!$V$2:$V$101,$A18)) -> 500 | K18: =IF($A18="","",INDEX(Products!$Z$2:$Z$101,$A18)&"") -> Below reorder | L18: =IF($A18="","",INDEX(Products!$N$2:$N$101,$A18)&"") -> Corliss Plant Proteins
A19: =IFERROR(MATCH(4,Products!$AC$2:$AC$101,0),"") -> 9 | B19: =IF($A19="","",INDEX(Products!$A$2:$A$101,$A19)&"") -> CRE-UNF-500G | C19: =IF($A19="","",INDEX(Products!$B$2:$B$101,$A19)&"") -> Creatine Monohydrate, Unflavoured, 500 g | D19: =IF($A19="","",INDEX(Products!$R$2:$R$101,$A19)) -> 290 | E19: =IF($A19="","",INDEX(Products!$S$2:$S$101,$A19)) -> 80 | F19: =IF($A19="","",INDEX(Products!$T$2:$T$101,$A19)) -> 0 | G19: =IF($A19="","",INDEX(Products!$U$2:$U$101,$A19)) -> 210 | H19: =IF($A19="","",INDEX(Products!$I$2:$I$101,$A19)) -> 250 | I19: =IF($A19="","",INDEX(Products!$J$2:$J$101,$A19)) -> 700 | J19: =IF($A19="","",INDEX(Products!$V$2:$V$101,$A19)) -> 0 | K19: =IF($A19="","",INDEX(Products!$Z$2:$Z$101,$A19)&"") -> Below reorder | L19: =IF($A19="","",INDEX(Products!$N$2:$N$101,$A19)&"") -> Dunmore Powder Labs
A20: =IFERROR(MATCH(5,Products!$AC$2:$AC$101,0),"") | B20: =IF($A20="","",INDEX(Products!$A$2:$A$101,$A20)&"") | C20: =IF($A20="","",INDEX(Products!$B$2:$B$101,$A20)&"") | D20: =IF($A20="","",INDEX(Products!$R$2:$R$101,$A20)) | E20: =IF($A20="","",INDEX(Products!$S$2:$S$101,$A20)) | F20: =IF($A20="","",INDEX(Products!$T$2:$T$101,$A20)) | G20: =IF($A20="","",INDEX(Products!$U$2:$U$101,$A20)) | H20: =IF($A20="","",INDEX(Products!$I$2:$I$101,$A20)) | I20: =IF($A20="","",INDEX(Products!$J$2:$J$101,$A20)) | J20: =IF($A20="","",INDEX(Products!$V$2:$V$101,$A20)) | K20: =IF($A20="","",INDEX(Products!$Z$2:$Z$101,$A20)&"") | L20: =IF($A20="","",INDEX(Products!$N$2:$N$101,$A20)&"")
A21: =IFERROR(MATCH(6,Products!$AC$2:$AC$101,0),"") | B21: =IF($A21="","",INDEX(Products!$A$2:$A$101,$A21)&"") | C21: =IF($A21="","",INDEX(Products!$B$2:$B$101,$A21)&"") | D21: =IF($A21="","",INDEX(Products!$R$2:$R$101,$A21)) | E21: =IF($A21="","",INDEX(Products!$S$2:$S$101,$A21)) | F21: =IF($A21="","",INDEX(Products!$T$2:$T$101,$A21)) | G21: =IF($A21="","",INDEX(Products!$U$2:$U$101,$A21)) | H21: =IF($A21="","",INDEX(Products!$I$2:$I$101,$A21)) | I21: =IF($A21="","",INDEX(Products!$J$2:$J$101,$A21)) | J21: =IF($A21="","",INDEX(Products!$V$2:$V$101,$A21)) | K21: =IF($A21="","",INDEX(Products!$Z$2:$Z$101,$A21)&"") | L21: =IF($A21="","",INDEX(Products!$N$2:$N$101,$A21)&"")
A22: =IFERROR(MATCH(7,Products!$AC$2:$AC$101,0),"") | B22: =IF($A22="","",INDEX(Products!$A$2:$A$101,$A22)&"") | C22: =IF($A22="","",INDEX(Products!$B$2:$B$101,$A22)&"") | D22: =IF($A22="","",INDEX(Products!$R$2:$R$101,$A22)) | E22: =IF($A22="","",INDEX(Products!$S$2:$S$101,$A22)) | F22: =IF($A22="","",INDEX(Products!$T$2:$T$101,$A22)) | G22: =IF($A22="","",INDEX(Products!$U$2:$U$101,$A22)) | H22: =IF($A22="","",INDEX(Products!$I$2:$I$101,$A22)) | I22: =IF($A22="","",INDEX(Products!$J$2:$J$101,$A22)) | J22: =IF($A22="","",INDEX(Products!$V$2:$V$101,$A22)) | K22: =IF($A22="","",INDEX(Products!$Z$2:$Z$101,$A22)&"") | L22: =IF($A22="","",INDEX(Products!$N$2:$N$101,$A22)&"")
A23: =IFERROR(MATCH(8,Products!$AC$2:$AC$101,0),"") | B23: =IF($A23="","",INDEX(Products!$A$2:$A$101,$A23)&"") | C23: =IF($A23="","",INDEX(Products!$B$2:$B$101,$A23)&"") | D23: =IF($A23="","",INDEX(Products!$R$2:$R$101,$A23)) | E23: =IF($A23="","",INDEX(Products!$S$2:$S$101,$A23)) | F23: =IF($A23="","",INDEX(Products!$T$2:$T$101,$A23)) | G23: =IF($A23="","",INDEX(Products!$U$2:$U$101,$A23)) | H23: =IF($A23="","",INDEX(Products!$I$2:$I$101,$A23)) | I23: =IF($A23="","",INDEX(Products!$J$2:$J$101,$A23)) | J23: =IF($A23="","",INDEX(Products!$V$2:$V$101,$A23)) | K23: =IF($A23="","",INDEX(Products!$Z$2:$Z$101,$A23)&"") | L23: =IF($A23="","",INDEX(Products!$N$2:$N$101,$A23)&"")
A24: =IFERROR(MATCH(9,Products!$AC$2:$AC$101,0),"") | B24: =IF($A24="","",INDEX(Products!$A$2:$A$101,$A24)&"") | C24: =IF($A24="","",INDEX(Products!$B$2:$B$101,$A24)&"") | D24: =IF($A24="","",INDEX(Products!$R$2:$R$101,$A24)) | E24: =IF($A24="","",INDEX(Products!$S$2:$S$101,$A24)) | F24: =IF($A24="","",INDEX(Products!$T$2:$T$101,$A24)) | G24: =IF($A24="","",INDEX(Products!$U$2:$U$101,$A24)) | H24: =IF($A24="","",INDEX(Products!$I$2:$I$101,$A24)) | I24: =IF($A24="","",INDEX(Products!$J$2:$J$101,$A24)) | J24: =IF($A24="","",INDEX(Products!$V$2:$V$101,$A24)) | K24: =IF($A24="","",INDEX(Products!$Z$2:$Z$101,$A24)&"") | L24: =IF($A24="","",INDEX(Products!$N$2:$N$101,$A24)&"")
A25: =IFERROR(MATCH(10,Products!$AC$2:$AC$101,0),"") | B25: =IF($A25="","",INDEX(Products!$A$2:$A$101,$A25)&"") | C25: =IF($A25="","",INDEX(Products!$B$2:$B$101,$A25)&"") | D25: =IF($A25="","",INDEX(Products!$R$2:$R$101,$A25)) | E25: =IF($A25="","",INDEX(Products!$S$2:$S$101,$A25)) | F25: =IF($A25="","",INDEX(Products!$T$2:$T$101,$A25)) | G25: =IF($A25="","",INDEX(Products!$U$2:$U$101,$A25)) | H25: =IF($A25="","",INDEX(Products!$I$2:$I$101,$A25)) | I25: =IF($A25="","",INDEX(Products!$J$2:$J$101,$A25)) | J25: =IF($A25="","",INDEX(Products!$V$2:$V$101,$A25)) | K25: =IF($A25="","",INDEX(Products!$Z$2:$Z$101,$A25)&"") | L25: =IF($A25="","",INDEX(Products!$N$2:$N$101,$A25)&"")
A26: =IFERROR(MATCH(11,Products!$AC$2:$AC$101,0),"") | B26: =IF($A26="","",INDEX(Products!$A$2:$A$101,$A26)&"") | C26: =IF($A26="","",INDEX(Products!$B$2:$B$101,$A26)&"") | D26: =IF($A26="","",INDEX(Products!$R$2:$R$101,$A26)) | E26: =IF($A26="","",INDEX(Products!$S$2:$S$101,$A26)) | F26: =IF($A26="","",INDEX(Products!$T$2:$T$101,$A26)) | G26: =IF($A26="","",INDEX(Products!$U$2:$U$101,$A26)) | H26: =IF($A26="","",INDEX(Products!$I$2:$I$101,$A26)) | I26: =IF($A26="","",INDEX(Products!$J$2:$J$101,$A26)) | J26: =IF($A26="","",INDEX(Products!$V$2:$V$101,$A26)) | K26: =IF($A26="","",INDEX(Products!$Z$2:$Z$101,$A26)&"") | L26: =IF($A26="","",INDEX(Products!$N$2:$N$101,$A26)&"")
A27: =IFERROR(MATCH(12,Products!$AC$2:$AC$101,0),"") | B27: =IF($A27="","",INDEX(Products!$A$2:$A$101,$A27)&"") | C27: =IF($A27="","",INDEX(Products!$B$2:$B$101,$A27)&"") | D27: =IF($A27="","",INDEX(Products!$R$2:$R$101,$A27)) | E27: =IF($A27="","",INDEX(Products!$S$2:$S$101,$A27)) | F27: =IF($A27="","",INDEX(Products!$T$2:$T$101,$A27)) | G27: =IF($A27="","",INDEX(Products!$U$2:$U$101,$A27)) | H27: =IF($A27="","",INDEX(Products!$I$2:$I$101,$A27)) | I27: =IF($A27="","",INDEX(Products!$J$2:$J$101,$A27)) | J27: =IF($A27="","",INDEX(Products!$V$2:$V$101,$A27)) | K27: =IF($A27="","",INDEX(Products!$Z$2:$Z$101,$A27)&"") | L27: =IF($A27="","",INDEX(Products!$N$2:$N$101,$A27)&"")
A28: =IFERROR(MATCH(13,Products!$AC$2:$AC$101,0),"") | B28: =IF($A28="","",INDEX(Products!$A$2:$A$101,$A28)&"") | C28: =IF($A28="","",INDEX(Products!$B$2:$B$101,$A28)&"") | D28: =IF($A28="","",INDEX(Products!$R$2:$R$101,$A28)) | E28: =IF($A28="","",INDEX(Products!$S$2:$S$101,$A28)) | F28: =IF($A28="","",INDEX(Products!$T$2:$T$101,$A28)) | G28: =IF($A28="","",INDEX(Products!$U$2:$U$101,$A28)) | H28: =IF($A28="","",INDEX(Products!$I$2:$I$101,$A28)) | I28: =IF($A28="","",INDEX(Products!$J$2:$J$101,$A28)) | J28: =IF($A28="","",INDEX(Products!$V$2:$V$101,$A28)) | K28: =IF($A28="","",INDEX(Products!$Z$2:$Z$101,$A28)&"") | L28: =IF($A28="","",INDEX(Products!$N$2:$N$101,$A28)&"")
A29: =IFERROR(MATCH(14,Products!$AC$2:$AC$101,0),"") | B29: =IF($A29="","",INDEX(Products!$A$2:$A$101,$A29)&"") | C29: =IF($A29="","",INDEX(Products!$B$2:$B$101,$A29)&"") | D29: =IF($A29="","",INDEX(Products!$R$2:$R$101,$A29)) | E29: =IF($A29="","",INDEX(Products!$S$2:$S$101,$A29)) | F29: =IF($A29="","",INDEX(Products!$T$2:$T$101,$A29)) | G29: =IF($A29="","",INDEX(Products!$U$2:$U$101,$A29)) | H29: =IF($A29="","",INDEX(Products!$I$2:$I$101,$A29)) | I29: =IF($A29="","",INDEX(Products!$J$2:$J$101,$A29)) | J29: =IF($A29="","",INDEX(Products!$V$2:$V$101,$A29)) | K29: =IF($A29="","",INDEX(Products!$Z$2:$Z$101,$A29)&"") | L29: =IF($A29="","",INDEX(Products!$N$2:$N$101,$A29)&"")
A30: =IFERROR(MATCH(15,Products!$AC$2:$AC$101,0),"") | B30: =IF($A30="","",INDEX(Products!$A$2:$A$101,$A30)&"") | C30: =IF($A30="","",INDEX(Products!$B$2:$B$101,$A30)&"") | D30: =IF($A30="","",INDEX(Products!$R$2:$R$101,$A30)) | E30: =IF($A30="","",INDEX(Products!$S$2:$S$101,$A30)) | F30: =IF($A30="","",INDEX(Products!$T$2:$T$101,$A30)) | G30: =IF($A30="","",INDEX(Products!$U$2:$U$101,$A30)) | H30: =IF($A30="","",INDEX(Products!$I$2:$I$101,$A30)) | I30: =IF($A30="","",INDEX(Products!$J$2:$J$101,$A30)) | J30: =IF($A30="","",INDEX(Products!$V$2:$V$101,$A30)) | K30: =IF($A30="","",INDEX(Products!$Z$2:$Z$101,$A30)&"") | L30: =IF($A30="","",INDEX(Products!$N$2:$N$101,$A30)&"")
B32: Outstanding purchase orders
B33: Open POs, earliest expected date first. Up to 15 shown.
B34: PO | C34: Supplier | D34: SKU | E34: Ordered | F34: Received | G34: Outstanding | H34: Order date | I34: Expected | J34: Status | K34: Overdue | L34: Days late
A35: =IFERROR(MATCH(1,Purchase_Orders!$T$2:$T$301,0),"") -> 8 | B35: =IF($A35="","",INDEX(Purchase_Orders!$A$2:$A$301,$A35)&"") -> PO-2026-029 | C35: =IF($A35="","",INDEX(Purchase_Orders!$K$2:$K$301,$A35)&"") -> Corliss Plant Proteins | D35: =IF($A35="","",INDEX(Purchase_Orders!$C$2:$C$301,$A35)&"") -> PLT-VAN-2LB | E35: =IF($A35="","",INDEX(Purchase_Orders!$D$2:$D$301,$A35)) -> 500 | F35: =IF($A35="","",INDEX(Purchase_Orders!$M$2:$M$301,$A35)) -> 0 | G35: =IF($A35="","",INDEX(Purchase_Orders!$N$2:$N$301,$A35)) -> 500 | H35: =IF($A35="","",INDEX(Purchase_Orders!$F$2:$F$301,$A35)) -> 46266 | I35: =IF($A35="","",INDEX(Purchase_Orders!$G$2:$G$301,$A35)) -> 46301 | J35: =IF($A35="","",INDEX(Purchase_Orders!$H$2:$H$301,$A35)&"") -> Confirmed | K35: =IF($A35="","",IF(INDEX(Purchase_Orders!$P$2:$P$301,$A35)=1,"Yes","")) -> Yes | L35: =IF($A35="","",INDEX(Purchase_Orders!$Q$2:$Q$301,$A35)) -> 9
A36: =IFERROR(MATCH(2,Purchase_Orders!$T$2:$T$301,0),"") -> 10 | B36: =IF($A36="","",INDEX(Purchase_Orders!$A$2:$A$301,$A36)&"") -> PO-2026-031 | C36: =IF($A36="","",INDEX(Purchase_Orders!$K$2:$K$301,$A36)&"") -> Dunmore Powder Labs | D36: =IF($A36="","",INDEX(Purchase_Orders!$C$2:$C$301,$A36)&"") -> PRE-WTM-30 | E36: =IF($A36="","",INDEX(Purchase_Orders!$D$2:$D$301,$A36)) -> 600 | F36: =IF($A36="","",INDEX(Purchase_Orders!$M$2:$M$301,$A36)) -> 0 | G36: =IF($A36="","",INDEX(Purchase_Orders!$N$2:$N$301,$A36)) -> 600 | H36: =IF($A36="","",INDEX(Purchase_Orders!$F$2:$F$301,$A36)) -> 46269 | I36: =IF($A36="","",INDEX(Purchase_Orders!$G$2:$G$301,$A36)) -> 46305 | J36: =IF($A36="","",INDEX(Purchase_Orders!$H$2:$H$301,$A36)&"") -> In transit | K36: =IF($A36="","",IF(INDEX(Purchase_Orders!$P$2:$P$301,$A36)=1,"Yes","")) -> Yes | L36: =IF($A36="","",INDEX(Purchase_Orders!$Q$2:$Q$301,$A36)) -> 5
A37: =IFERROR(MATCH(3,Purchase_Orders!$T$2:$T$301,0),"") -> 9 | B37: =IF($A37="","",INDEX(Purchase_Orders!$A$2:$A$301,$A37)&"") -> PO-2026-030 | C37: =IF($A37="","",INDEX(Purchase_Orders!$K$2:$K$301,$A37)&"") -> Alder Creek Dairy Proteins | D37: =IF($A37="","",INDEX(Purchase_Orders!$C$2:$C$301,$A37)&"") -> WPI-CHO-2LB | E37: =IF($A37="","",INDEX(Purchase_Orders!$D$2:$D$301,$A37)) -> 1500 | F37: =IF($A37="","",INDEX(Purchase_Orders!$M$2:$M$301,$A37)) -> 0 | G37: =IF($A37="","",INDEX(Purchase_Orders!$N$2:$N$301,$A37)) -> 1500 | H37: =IF($A37="","",INDEX(Purchase_Orders!$F$2:$F$301,$A37)) -> 46280 | I37: =IF($A37="","",INDEX(Purchase_Orders!$G$2:$G$301,$A37)) -> 46315 | J37: =IF($A37="","",INDEX(Purchase_Orders!$H$2:$H$301,$A37)&"") -> In transit | K37: =IF($A37="","",IF(INDEX(Purchase_Orders!$P$2:$P$301,$A37)=1,"Yes","")) | L37: =IF($A37="","",INDEX(Purchase_Orders!$Q$2:$Q$301,$A37)) -> 0
A38: =IFERROR(MATCH(4,Purchase_Orders!$T$2:$T$301,0),"") -> 6 | B38: =IF($A38="","",INDEX(Purchase_Orders!$A$2:$A$301,$A38)&"") -> PO-2026-027 | C38: =IF($A38="","",INDEX(Purchase_Orders!$K$2:$K$301,$A38)&"") -> Alder Creek Dairy Proteins | D38: =IF($A38="","",INDEX(Purchase_Orders!$C$2:$C$301,$A38)&"") -> WPI-VAN-2LB | E38: =IF($A38="","",INDEX(Purchase_Orders!$D$2:$D$301,$A38)) -> 1200 | F38: =IF($A38="","",INDEX(Purchase_Orders!$M$2:$M$301,$A38)) -> 600 | G38: =IF($A38="","",INDEX(Purchase_Orders!$N$2:$N$301,$A38)) -> 600 | H38: =IF($A38="","",INDEX(Purchase_Orders!$F$2:$F$301,$A38)) -> 46267 | I38: =IF($A38="","",INDEX(Purchase_Orders!$G$2:$G$301,$A38)) -> 46324 | J38: =IF($A38="","",INDEX(Purchase_Orders!$H$2:$H$301,$A38)&"") -> Partially received | K38: =IF($A38="","",IF(INDEX(Purchase_Orders!$P$2:$P$301,$A38)=1,"Yes","")) | L38: =IF($A38="","",INDEX(Purchase_Orders!$Q$2:$Q$301,$A38)) -> 0
A39: =IFERROR(MATCH(5,Purchase_Orders!$T$2:$T$301,0),"") -> 11 | B39: =IF($A39="","",INDEX(Purchase_Orders!$A$2:$A$301,$A39)&"") -> PO-2026-032 | C39: =IF($A39="","",INDEX(Purchase_Orders!$K$2:$K$301,$A39)&"") -> Elmstead Co-Packing | D39: =IF($A39="","",INDEX(Purchase_Orders!$C$2:$C$301,$A39)&"") -> CAS-CHO-2LB | E39: =IF($A39="","",INDEX(Purchase_Orders!$D$2:$D$301,$A39)) -> 360 | F39: =IF($A39="","",INDEX(Purchase_Orders!$M$2:$M$301,$A39)) -> 0 | G39: =IF($A39="","",INDEX(Purchase_Orders!$N$2:$N$301,$A39)) -> 360 | H39: =IF($A39="","",INDEX(Purchase_Orders!$F$2:$F$301,$A39)) -> 46300 | I39: =IF($A39="","",INDEX(Purchase_Orders!$G$2:$G$301,$A39)) -> 46345 | J39: =IF($A39="","",INDEX(Purchase_Orders!$H$2:$H$301,$A39)&"") -> Ordered | K39: =IF($A39="","",IF(INDEX(Purchase_Orders!$P$2:$P$301,$A39)=1,"Yes","")) | L39: =IF($A39="","",INDEX(Purchase_Orders!$Q$2:$Q$301,$A39)) -> 0
A40: =IFERROR(MATCH(6,Purchase_Orders!$T$2:$T$301,0),"") | B40: =IF($A40="","",INDEX(Purchase_Orders!$A$2:$A$301,$A40)&"") | C40: =IF($A40="","",INDEX(Purchase_Orders!$K$2:$K$301,$A40)&"") | D40: =IF($A40="","",INDEX(Purchase_Orders!$C$2:$C$301,$A40)&"") | E40: =IF($A40="","",INDEX(Purchase_Orders!$D$2:$D$301,$A40)) | F40: =IF($A40="","",INDEX(Purchase_Orders!$M$2:$M$301,$A40)) | G40: =IF($A40="","",INDEX(Purchase_Orders!$N$2:$N$301,$A40)) | H40: =IF($A40="","",INDEX(Purchase_Orders!$F$2:$F$301,$A40)) | I40: =IF($A40="","",INDEX(Purchase_Orders!$G$2:$G$301,$A40)) | J40: =IF($A40="","",INDEX(Purchase_Orders!$H$2:$H$301,$A40)&"") | K40: =IF($A40="","",IF(INDEX(Purchase_Orders!$P$2:$P$301,$A40)=1,"Yes","")) | L40: =IF($A40="","",INDEX(Purchase_Orders!$Q$2:$Q$301,$A40))
A41: =IFERROR(MATCH(7,Purchase_Orders!$T$2:$T$301,0),"") | B41: =IF($A41="","",INDEX(Purchase_Orders!$A$2:$A$301,$A41)&"") | C41: =IF($A41="","",INDEX(Purchase_Orders!$K$2:$K$301,$A41)&"") | D41: =IF($A41="","",INDEX(Purchase_Orders!$C$2:$C$301,$A41)&"") | E41: =IF($A41="","",INDEX(Purchase_Orders!$D$2:$D$301,$A41)) | F41: =IF($A41="","",INDEX(Purchase_Orders!$M$2:$M$301,$A41)) | G41: =IF($A41="","",INDEX(Purchase_Orders!$N$2:$N$301,$A41)) | H41: =IF($A41="","",INDEX(Purchase_Orders!$F$2:$F$301,$A41)) | I41: =IF($A41="","",INDEX(Purchase_Orders!$G$2:$G$301,$A41)) | J41: =IF($A41="","",INDEX(Purchase_Orders!$H$2:$H$301,$A41)&"") | K41: =IF($A41="","",IF(INDEX(Purchase_Orders!$P$2:$P$301,$A41)=1,"Yes","")) | L41: =IF($A41="","",INDEX(Purchase_Orders!$Q$2:$Q$301,$A41))
A42: =IFERROR(MATCH(8,Purchase_Orders!$T$2:$T$301,0),"") | B42: =IF($A42="","",INDEX(Purchase_Orders!$A$2:$A$301,$A42)&"") | C42: =IF($A42="","",INDEX(Purchase_Orders!$K$2:$K$301,$A42)&"") | D42: =IF($A42="","",INDEX(Purchase_Orders!$C$2:$C$301,$A42)&"") | E42: =IF($A42="","",INDEX(Purchase_Orders!$D$2:$D$301,$A42)) | F42: =IF($A42="","",INDEX(Purchase_Orders!$M$2:$M$301,$A42)) | G42: =IF($A42="","",INDEX(Purchase_Orders!$N$2:$N$301,$A42)) | H42: =IF($A42="","",INDEX(Purchase_Orders!$F$2:$F$301,$A42)) | I42: =IF($A42="","",INDEX(Purchase_Orders!$G$2:$G$301,$A42)) | J42: =IF($A42="","",INDEX(Purchase_Orders!$H$2:$H$301,$A42)&"") | K42: =IF($A42="","",IF(INDEX(Purchase_Orders!$P$2:$P$301,$A42)=1,"Yes","")) | L42: =IF($A42="","",INDEX(Purchase_Orders!$Q$2:$Q$301,$A42))
A43: =IFERROR(MATCH(9,Purchase_Orders!$T$2:$T$301,0),"") | B43: =IF($A43="","",INDEX(Purchase_Orders!$A$2:$A$301,$A43)&"") | C43: =IF($A43="","",INDEX(Purchase_Orders!$K$2:$K$301,$A43)&"") | D43: =IF($A43="","",INDEX(Purchase_Orders!$C$2:$C$301,$A43)&"") | E43: =IF($A43="","",INDEX(Purchase_Orders!$D$2:$D$301,$A43)) | F43: =IF($A43="","",INDEX(Purchase_Orders!$M$2:$M$301,$A43)) | G43: =IF($A43="","",INDEX(Purchase_Orders!$N$2:$N$301,$A43)) | H43: =IF($A43="","",INDEX(Purchase_Orders!$F$2:$F$301,$A43)) | I43: =IF($A43="","",INDEX(Purchase_Orders!$G$2:$G$301,$A43)) | J43: =IF($A43="","",INDEX(Purchase_Orders!$H$2:$H$301,$A43)&"") | K43: =IF($A43="","",IF(INDEX(Purchase_Orders!$P$2:$P$301,$A43)=1,"Yes","")) | L43: =IF($A43="","",INDEX(Purchase_Orders!$Q$2:$Q$301,$A43))
A44: =IFERROR(MATCH(10,Purchase_Orders!$T$2:$T$301,0),"") | B44: =IF($A44="","",INDEX(Purchase_Orders!$A$2:$A$301,$A44)&"") | C44: =IF($A44="","",INDEX(Purchase_Orders!$K$2:$K$301,$A44)&"") | D44: =IF($A44="","",INDEX(Purchase_Orders!$C$2:$C$301,$A44)&"") | E44: =IF($A44="","",INDEX(Purchase_Orders!$D$2:$D$301,$A44)) | F44: =IF($A44="","",INDEX(Purchase_Orders!$M$2:$M$301,$A44)) | G44: =IF($A44="","",INDEX(Purchase_Orders!$N$2:$N$301,$A44)) | H44: =IF($A44="","",INDEX(Purchase_Orders!$F$2:$F$301,$A44)) | I44: =IF($A44="","",INDEX(Purchase_Orders!$G$2:$G$301,$A44)) | J44: =IF($A44="","",INDEX(Purchase_Orders!$H$2:$H$301,$A44)&"") | K44: =IF($A44="","",IF(INDEX(Purchase_Orders!$P$2:$P$301,$A44)=1,"Yes","")) | L44: =IF($A44="","",INDEX(Purchase_Orders!$Q$2:$Q$301,$A44))
A45: =IFERROR(MATCH(11,Purchase_Orders!$T$2:$T$301,0),"") | B45: =IF($A45="","",INDEX(Purchase_Orders!$A$2:$A$301,$A45)&"") | C45: =IF($A45="","",INDEX(Purchase_Orders!$K$2:$K$301,$A45)&"") | D45: =IF($A45="","",INDEX(Purchase_Orders!$C$2:$C$301,$A45)&"") | E45: =IF($A45="","",INDEX(Purchase_Orders!$D$2:$D$301,$A45)) | F45: =IF($A45="","",INDEX(Purchase_Orders!$M$2:$M$301,$A45)) | G45: =IF($A45="","",INDEX(Purchase_Orders!$N$2:$N$301,$A45)) | H45: =IF($A45="","",INDEX(Purchase_Orders!$F$2:$F$301,$A45)) | I45: =IF($A45="","",INDEX(Purchase_Orders!$G$2:$G$301,$A45)) | J45: =IF($A45="","",INDEX(Purchase_Orders!$H$2:$H$301,$A45)&"") | K45: =IF($A45="","",IF(INDEX(Purchase_Orders!$P$2:$P$301,$A45)=1,"Yes","")) | L45: =IF($A45="","",INDEX(Purchase_Orders!$Q$2:$Q$301,$A45))
A46: =IFERROR(MATCH(12,Purchase_Orders!$T$2:$T$301,0),"") | B46: =IF($A46="","",INDEX(Purchase_Orders!$A$2:$A$301,$A46)&"") | C46: =IF($A46="","",INDEX(Purchase_Orders!$K$2:$K$301,$A46)&"") | D46: =IF($A46="","",INDEX(Purchase_Orders!$C$2:$C$301,$A46)&"") | E46: =IF($A46="","",INDEX(Purchase_Orders!$D$2:$D$301,$A46)) | F46: =IF($A46="","",INDEX(Purchase_Orders!$M$2:$M$301,$A46)) | G46: =IF($A46="","",INDEX(Purchase_Orders!$N$2:$N$301,$A46)) | H46: =IF($A46="","",INDEX(Purchase_Orders!$F$2:$F$301,$A46)) | I46: =IF($A46="","",INDEX(Purchase_Orders!$G$2:$G$301,$A46)) | J46: =IF($A46="","",INDEX(Purchase_Orders!$H$2:$H$301,$A46)&"") | K46: =IF($A46="","",IF(INDEX(Purchase_Orders!$P$2:$P$301,$A46)=1,"Yes","")) | L46: =IF($A46="","",INDEX(Purchase_Orders!$Q$2:$Q$301,$A46))
A47: =IFERROR(MATCH(13,Purchase_Orders!$T$2:$T$301,0),"") | B47: =IF($A47="","",INDEX(Purchase_Orders!$A$2:$A$301,$A47)&"") | C47: =IF($A47="","",INDEX(Purchase_Orders!$K$2:$K$301,$A47)&"") | D47: =IF($A47="","",INDEX(Purchase_Orders!$C$2:$C$301,$A47)&"") | E47: =IF($A47="","",INDEX(Purchase_Orders!$D$2:$D$301,$A47)) | F47: =IF($A47="","",INDEX(Purchase_Orders!$M$2:$M$301,$A47)) | G47: =IF($A47="","",INDEX(Purchase_Orders!$N$2:$N$301,$A47)) | H47: =IF($A47="","",INDEX(Purchase_Orders!$F$2:$F$301,$A47)) | I47: =IF($A47="","",INDEX(Purchase_Orders!$G$2:$G$301,$A47)) | J47: =IF($A47="","",INDEX(Purchase_Orders!$H$2:$H$301,$A47)&"") | K47: =IF($A47="","",IF(INDEX(Purchase_Orders!$P$2:$P$301,$A47)=1,"Yes","")) | L47: =IF($A47="","",INDEX(Purchase_Orders!$Q$2:$Q$301,$A47))
A48: =IFERROR(MATCH(14,Purchase_Orders!$T$2:$T$301,0),"") | B48: =IF($A48="","",INDEX(Purchase_Orders!$A$2:$A$301,$A48)&"") | C48: =IF($A48="","",INDEX(Purchase_Orders!$K$2:$K$301,$A48)&"") | D48: =IF($A48="","",INDEX(Purchase_Orders!$C$2:$C$301,$A48)&"") | E48: =IF($A48="","",INDEX(Purchase_Orders!$D$2:$D$301,$A48)) | F48: =IF($A48="","",INDEX(Purchase_Orders!$M$2:$M$301,$A48)) | G48: =IF($A48="","",INDEX(Purchase_Orders!$N$2:$N$301,$A48)) | H48: =IF($A48="","",INDEX(Purchase_Orders!$F$2:$F$301,$A48)) | I48: =IF($A48="","",INDEX(Purchase_Orders!$G$2:$G$301,$A48)) | J48: =IF($A48="","",INDEX(Purchase_Orders!$H$2:$H$301,$A48)&"") | K48: =IF($A48="","",IF(INDEX(Purchase_Orders!$P$2:$P$301,$A48)=1,"Yes","")) | L48: =IF($A48="","",INDEX(Purchase_Orders!$Q$2:$Q$301,$A48))
A49: =IFERROR(MATCH(15,Purchase_Orders!$T$2:$T$301,0),"") | B49: =IF($A49="","",INDEX(Purchase_Orders!$A$2:$A$301,$A49)&"") | C49: =IF($A49="","",INDEX(Purchase_Orders!$K$2:$K$301,$A49)&"") | D49: =IF($A49="","",INDEX(Purchase_Orders!$C$2:$C$301,$A49)&"") | E49: =IF($A49="","",INDEX(Purchase_Orders!$D$2:$D$301,$A49)) | F49: =IF($A49="","",INDEX(Purchase_Orders!$M$2:$M$301,$A49)) | G49: =IF($A49="","",INDEX(Purchase_Orders!$N$2:$N$301,$A49)) | H49: =IF($A49="","",INDEX(Purchase_Orders!$F$2:$F$301,$A49)) | I49: =IF($A49="","",INDEX(Purchase_Orders!$G$2:$G$301,$A49)) | J49: =IF($A49="","",INDEX(Purchase_Orders!$H$2:$H$301,$A49)&"") | K49: =IF($A49="","",IF(INDEX(Purchase_Orders!$P$2:$P$301,$A49)=1,"Yes","")) | L49: =IF($A49="","",INDEX(Purchase_Orders!$Q$2:$Q$301,$A49))
B51: Lots approaching expiry
B52: ="Lots with stock on hand that are expired or within "&Config!$B$8&" days of expiry, earliest first. Up to 20 shown. Dates are company-supplied." -> Lots with stock on hand that are expired or within 90 days of expiry, earliest first. Up to 20 shown. Dates are company-supplied.
B53: Lot | C53: Product | D53: SKU | E53: On hand | F53: Expiry date | G53: Days left | H53: Window | I53: Lot status | J53: Held qty
A54: =IFERROR(MATCH(1,Batches!$R$2:$R$301,0),"") -> 15 | B54: =IF($A54="","",INDEX(Batches!$A$2:$A$301,$A54)&"") -> CKD2510A | C54: =IF($A54="","",INDEX(Batches!$J$2:$J$301,$A54)&"") -> Protein Bar, Cookie Dough, 12-pack | D54: =IF($A54="","",INDEX(Batches!$B$2:$B$301,$A54)&"") -> BAR-CKD-12 | E54: =IF($A54="","",INDEX(Batches!$L$2:$L$301,$A54)) -> 36 | F54: =IF($A54="","",INDEX(Batches!$E$2:$E$301,$A54)) -> 46297 | G54: =IF($A54="","",INDEX(Batches!$M$2:$M$301,$A54)) -> -13 | H54: =IF($A54="","",INDEX(Batches!$N$2:$N$301,$A54)&"") -> Expired | I54: =IF($A54="","",INDEX(Batches!$G$2:$G$301,$A54)&"") -> On hold | J54: =IF($A54="","",INDEX(Batches!$P$2:$P$301,$A54)) -> 36
A55: =IFERROR(MATCH(2,Batches!$R$2:$R$301,0),"") -> 13 | B55: =IF($A55="","",INDEX(Batches!$A$2:$A$301,$A55)&"") -> PBC2511A | C55: =IF($A55="","",INDEX(Batches!$J$2:$J$301,$A55)&"") -> Protein Bar, Peanut Butter Chocolate, 12-pack | D55: =IF($A55="","",INDEX(Batches!$B$2:$B$301,$A55)&"") -> BAR-PBC-12 | E55: =IF($A55="","",INDEX(Batches!$L$2:$L$301,$A55)) -> 344 | F55: =IF($A55="","",INDEX(Batches!$E$2:$E$301,$A55)) -> 46326 | G55: =IF($A55="","",INDEX(Batches!$M$2:$M$301,$A55)) -> 16 | H55: =IF($A55="","",INDEX(Batches!$N$2:$N$301,$A55)&"") -> <=30 | I55: =IF($A55="","",INDEX(Batches!$G$2:$G$301,$A55)&"") -> Released | J55: =IF($A55="","",INDEX(Batches!$P$2:$P$301,$A55)) -> 0
A56: =IFERROR(MATCH(3,Batches!$R$2:$R$301,0),"") -> 16 | B56: =IF($A56="","",INDEX(Batches!$A$2:$A$301,$A56)&"") -> CKD2511A | C56: =IF($A56="","",INDEX(Batches!$J$2:$J$301,$A56)&"") -> Protein Bar, Cookie Dough, 12-pack | D56: =IF($A56="","",INDEX(Batches!$B$2:$B$301,$A56)&"") -> BAR-CKD-12 | E56: =IF($A56="","",INDEX(Batches!$L$2:$L$301,$A56)) -> 212 | F56: =IF($A56="","",INDEX(Batches!$E$2:$E$301,$A56)) -> 46334 | G56: =IF($A56="","",INDEX(Batches!$M$2:$M$301,$A56)) -> 24 | H56: =IF($A56="","",INDEX(Batches!$N$2:$N$301,$A56)&"") -> <=30 | I56: =IF($A56="","",INDEX(Batches!$G$2:$G$301,$A56)&"") -> Released | J56: =IF($A56="","",INDEX(Batches!$P$2:$P$301,$A56)) -> 0
A57: =IFERROR(MATCH(4,Batches!$R$2:$R$301,0),"") -> 11 | B57: =IF($A57="","",INDEX(Batches!$A$2:$A$301,$A57)&"") -> PVA2411A | C57: =IF($A57="","",INDEX(Batches!$J$2:$J$301,$A57)&"") -> Plant Protein, Vanilla, 2 lb | D57: =IF($A57="","",INDEX(Batches!$B$2:$B$301,$A57)&"") -> PLT-VAN-2LB | E57: =IF($A57="","",INDEX(Batches!$L$2:$L$301,$A57)) -> 53 | F57: =IF($A57="","",INDEX(Batches!$E$2:$E$301,$A57)) -> 46340 | G57: =IF($A57="","",INDEX(Batches!$M$2:$M$301,$A57)) -> 30 | H57: =IF($A57="","",INDEX(Batches!$N$2:$N$301,$A57)&"") -> <=30 | I57: =IF($A57="","",INDEX(Batches!$G$2:$G$301,$A57)&"") -> Released | J57: =IF($A57="","",INDEX(Batches!$P$2:$P$301,$A57)) -> 0
A58: =IFERROR(MATCH(5,Batches!$R$2:$R$301,0),"") -> 4 | B58: =IF($A58="","",INDEX(Batches!$A$2:$A$301,$A58)&"") -> WVA2411A | C58: =IF($A58="","",INDEX(Batches!$J$2:$J$301,$A58)&"") -> Whey Protein Isolate, Vanilla, 2 lb | D58: =IF($A58="","",INDEX(Batches!$B$2:$B$301,$A58)&"") -> WPI-VAN-2LB | E58: =IF($A58="","",INDEX(Batches!$L$2:$L$301,$A58)) -> 48 | F58: =IF($A58="","",INDEX(Batches!$E$2:$E$301,$A58)) -> 46353 | G58: =IF($A58="","",INDEX(Batches!$M$2:$M$301,$A58)) -> 43 | H58: =IF($A58="","",INDEX(Batches!$N$2:$N$301,$A58)&"") -> 31-60 | I58: =IF($A58="","",INDEX(Batches!$G$2:$G$301,$A58)&"") -> Released | J58: =IF($A58="","",INDEX(Batches!$P$2:$P$301,$A58)) -> 0
A59: =IFERROR(MATCH(6,Batches!$R$2:$R$301,0),"") -> 26 | B59: =IF($A59="","",INDEX(Batches!$A$2:$A$301,$A59)&"") -> CCA2412A | C59: =IF($A59="","",INDEX(Batches!$J$2:$J$301,$A59)&"") -> Micellar Casein, Chocolate, 2 lb | D59: =IF($A59="","",INDEX(Batches!$B$2:$B$301,$A59)&"") -> CAS-CHO-2LB | E59: =IF($A59="","",INDEX(Batches!$L$2:$L$301,$A59)) -> 80 | F59: =IF($A59="","",INDEX(Batches!$E$2:$E$301,$A59)) -> 46366 | G59: =IF($A59="","",INDEX(Batches!$M$2:$M$301,$A59)) -> 56 | H59: =IF($A59="","",INDEX(Batches!$N$2:$N$301,$A59)&"") -> 31-60 | I59: =IF($A59="","",INDEX(Batches!$G$2:$G$301,$A59)&"") -> Released | J59: =IF($A59="","",INDEX(Batches!$P$2:$P$301,$A59)) -> 0
A60: =IFERROR(MATCH(7,Batches!$R$2:$R$301,0),"") -> 9 | B60: =IF($A60="","",INDEX(Batches!$A$2:$A$301,$A60)&"") -> PCH2412A | C60: =IF($A60="","",INDEX(Batches!$J$2:$J$301,$A60)&"") -> Plant Protein, Chocolate, 2 lb | D60: =IF($A60="","",INDEX(Batches!$B$2:$B$301,$A60)&"") -> PLT-CHO-2LB | E60: =IF($A60="","",INDEX(Batches!$L$2:$L$301,$A60)) -> 136 | F60: =IF($A60="","",INDEX(Batches!$E$2:$E$301,$A60)) -> 46378 | G60: =IF($A60="","",INDEX(Batches!$M$2:$M$301,$A60)) -> 68 | H60: =IF($A60="","",INDEX(Batches!$N$2:$N$301,$A60)&"") -> 61-90 | I60: =IF($A60="","",INDEX(Batches!$G$2:$G$301,$A60)&"") -> Released | J60: =IF($A60="","",INDEX(Batches!$P$2:$P$301,$A60)) -> 0
A61: =IFERROR(MATCH(8,Batches!$R$2:$R$301,0),"") -> 22 | B61: =IF($A61="","",INDEX(Batches!$A$2:$A$301,$A61)&"") -> PBZ2501A | C61: =IF($A61="","",INDEX(Batches!$J$2:$J$301,$A61)&"") -> Pre-Workout, Blue Raspberry, 30 servings | D61: =IF($A61="","",INDEX(Batches!$B$2:$B$301,$A61)&"") -> PRE-BRZ-30 | E61: =IF($A61="","",INDEX(Batches!$L$2:$L$301,$A61)) -> 75 | F61: =IF($A61="","",INDEX(Batches!$E$2:$E$301,$A61)) -> 46392 | G61: =IF($A61="","",INDEX(Batches!$M$2:$M$301,$A61)) -> 82 | H61: =IF($A61="","",INDEX(Batches!$N$2:$N$301,$A61)&"") -> 61-90 | I61: =IF($A61="","",INDEX(Batches!$G$2:$G$301,$A61)&"") -> Released | J61: =IF($A61="","",INDEX(Batches!$P$2:$P$301,$A61)) -> 0
A62: =IFERROR(MATCH(9,Batches!$R$2:$R$301,0),"") -> 7 | B62: =IF($A62="","",INDEX(Batches!$A$2:$A$301,$A62)&"") -> W5C2501A | C62: =IF($A62="","",INDEX(Batches!$J$2:$J$301,$A62)&"") -> Whey Protein Isolate, Chocolate, 5 lb | D62: =IF($A62="","",INDEX(Batches!$B$2:$B$301,$A62)&"") -> WPI-CHO-5LB | E62: =IF($A62="","",INDEX(Batches!$L$2:$L$301,$A62)) -> 104 | F62: =IF($A62="","",INDEX(Batches!$E$2:$E$301,$A62)) -> 46399 | G62: =IF($A62="","",INDEX(Batches!$M$2:$M$301,$A62)) -> 89 | H62: =IF($A62="","",INDEX(Batches!$N$2:$N$301,$A62)&"") -> 61-90 | I62: =IF($A62="","",INDEX(Batches!$G$2:$G$301,$A62)&"") -> Released | J62: =IF($A62="","",INDEX(Batches!$P$2:$P$301,$A62)) -> 0
A63: =IFERROR(MATCH(10,Batches!$R$2:$R$301,0),"") | B63: =IF($A63="","",INDEX(Batches!$A$2:$A$301,$A63)&"") | C63: =IF($A63="","",INDEX(Batches!$J$2:$J$301,$A63)&"") | D63: =IF($A63="","",INDEX(Batches!$B$2:$B$301,$A63)&"") | E63: =IF($A63="","",INDEX(Batches!$L$2:$L$301,$A63)) | F63: =IF($A63="","",INDEX(Batches!$E$2:$E$301,$A63)) | G63: =IF($A63="","",INDEX(Batches!$M$2:$M$301,$A63)) | H63: =IF($A63="","",INDEX(Batches!$N$2:$N$301,$A63)&"") | I63: =IF($A63="","",INDEX(Batches!$G$2:$G$301,$A63)&"") | J63: =IF($A63="","",INDEX(Batches!$P$2:$P$301,$A63))
A64: =IFERROR(MATCH(11,Batches!$R$2:$R$301,0),"") | B64: =IF($A64="","",INDEX(Batches!$A$2:$A$301,$A64)&"") | C64: =IF($A64="","",INDEX(Batches!$J$2:$J$301,$A64)&"") | D64: =IF($A64="","",INDEX(Batches!$B$2:$B$301,$A64)&"") | E64: =IF($A64="","",INDEX(Batches!$L$2:$L$301,$A64)) | F64: =IF($A64="","",INDEX(Batches!$E$2:$E$301,$A64)) | G64: =IF($A64="","",INDEX(Batches!$M$2:$M$301,$A64)) | H64: =IF($A64="","",INDEX(Batches!$N$2:$N$301,$A64)&"") | I64: =IF($A64="","",INDEX(Batches!$G$2:$G$301,$A64)&"") | J64: =IF($A64="","",INDEX(Batches!$P$2:$P$301,$A64))
A65: =IFERROR(MATCH(12,Batches!$R$2:$R$301,0),"") | B65: =IF($A65="","",INDEX(Batches!$A$2:$A$301,$A65)&"") | C65: =IF($A65="","",INDEX(Batches!$J$2:$J$301,$A65)&"") | D65: =IF($A65="","",INDEX(Batches!$B$2:$B$301,$A65)&"") | E65: =IF($A65="","",INDEX(Batches!$L$2:$L$301,$A65)) | F65: =IF($A65="","",INDEX(Batches!$E$2:$E$301,$A65)) | G65: =IF($A65="","",INDEX(Batches!$M$2:$M$301,$A65)) | H65: =IF($A65="","",INDEX(Batches!$N$2:$N$301,$A65)&"") | I65: =IF($A65="","",INDEX(Batches!$G$2:$G$301,$A65)&"") | J65: =IF($A65="","",INDEX(Batches!$P$2:$P$301,$A65))
A66: =IFERROR(MATCH(13,Batches!$R$2:$R$301,0),"") | B66: =IF($A66="","",INDEX(Batches!$A$2:$A$301,$A66)&"") | C66: =IF($A66="","",INDEX(Batches!$J$2:$J$301,$A66)&"") | D66: =IF($A66="","",INDEX(Batches!$B$2:$B$301,$A66)&"") | E66: =IF($A66="","",INDEX(Batches!$L$2:$L$301,$A66)) | F66: =IF($A66="","",INDEX(Batches!$E$2:$E$301,$A66)) | G66: =IF($A66="","",INDEX(Batches!$M$2:$M$301,$A66)) | H66: =IF($A66="","",INDEX(Batches!$N$2:$N$301,$A66)&"") | I66: =IF($A66="","",INDEX(Batches!$G$2:$G$301,$A66)&"") | J66: =IF($A66="","",INDEX(Batches!$P$2:$P$301,$A66))
A67: =IFERROR(MATCH(14,Batches!$R$2:$R$301,0),"") | B67: =IF($A67="","",INDEX(Batches!$A$2:$A$301,$A67)&"") | C67: =IF($A67="","",INDEX(Batches!$J$2:$J$301,$A67)&"") | D67: =IF($A67="","",INDEX(Batches!$B$2:$B$301,$A67)&"") | E67: =IF($A67="","",INDEX(Batches!$L$2:$L$301,$A67)) | F67: =IF($A67="","",INDEX(Batches!$E$2:$E$301,$A67)) | G67: =IF($A67="","",INDEX(Batches!$M$2:$M$301,$A67)) | H67: =IF($A67="","",INDEX(Batches!$N$2:$N$301,$A67)&"") | I67: =IF($A67="","",INDEX(Batches!$G$2:$G$301,$A67)&"") | J67: =IF($A67="","",INDEX(Batches!$P$2:$P$301,$A67))
A68: =IFERROR(MATCH(15,Batches!$R$2:$R$301,0),"") | B68: =IF($A68="","",INDEX(Batches!$A$2:$A$301,$A68)&"") | C68: =IF($A68="","",INDEX(Batches!$J$2:$J$301,$A68)&"") | D68: =IF($A68="","",INDEX(Batches!$B$2:$B$301,$A68)&"") | E68: =IF($A68="","",INDEX(Batches!$L$2:$L$301,$A68)) | F68: =IF($A68="","",INDEX(Batches!$E$2:$E$301,$A68)) | G68: =IF($A68="","",INDEX(Batches!$M$2:$M$301,$A68)) | H68: =IF($A68="","",INDEX(Batches!$N$2:$N$301,$A68)&"") | I68: =IF($A68="","",INDEX(Batches!$G$2:$G$301,$A68)&"") | J68: =IF($A68="","",INDEX(Batches!$P$2:$P$301,$A68))
A69: =IFERROR(MATCH(16,Batches!$R$2:$R$301,0),"") | B69: =IF($A69="","",INDEX(Batches!$A$2:$A$301,$A69)&"") | C69: =IF($A69="","",INDEX(Batches!$J$2:$J$301,$A69)&"") | D69: =IF($A69="","",INDEX(Batches!$B$2:$B$301,$A69)&"") | E69: =IF($A69="","",INDEX(Batches!$L$2:$L$301,$A69)) | F69: =IF($A69="","",INDEX(Batches!$E$2:$E$301,$A69)) | G69: =IF($A69="","",INDEX(Batches!$M$2:$M$301,$A69)) | H69: =IF($A69="","",INDEX(Batches!$N$2:$N$301,$A69)&"") | I69: =IF($A69="","",INDEX(Batches!$G$2:$G$301,$A69)&"") | J69: =IF($A69="","",INDEX(Batches!$P$2:$P$301,$A69))
A70: =IFERROR(MATCH(17,Batches!$R$2:$R$301,0),"") | B70: =IF($A70="","",INDEX(Batches!$A$2:$A$301,$A70)&"") | C70: =IF($A70="","",INDEX(Batches!$J$2:$J$301,$A70)&"") | D70: =IF($A70="","",INDEX(Batches!$B$2:$B$301,$A70)&"") | E70: =IF($A70="","",INDEX(Batches!$L$2:$L$301,$A70)) | F70: =IF($A70="","",INDEX(Batches!$E$2:$E$301,$A70)) | G70: =IF($A70="","",INDEX(Batches!$M$2:$M$301,$A70)) | H70: =IF($A70="","",INDEX(Batches!$N$2:$N$301,$A70)&"") | I70: =IF($A70="","",INDEX(Batches!$G$2:$G$301,$A70)&"") | J70: =IF($A70="","",INDEX(Batches!$P$2:$P$301,$A70))
A71: =IFERROR(MATCH(18,Batches!$R$2:$R$301,0),"") | B71: =IF($A71="","",INDEX(Batches!$A$2:$A$301,$A71)&"") | C71: =IF($A71="","",INDEX(Batches!$J$2:$J$301,$A71)&"") | D71: =IF($A71="","",INDEX(Batches!$B$2:$B$301,$A71)&"") | E71: =IF($A71="","",INDEX(Batches!$L$2:$L$301,$A71)) | F71: =IF($A71="","",INDEX(Batches!$E$2:$E$301,$A71)) | G71: =IF($A71="","",INDEX(Batches!$M$2:$M$301,$A71)) | H71: =IF($A71="","",INDEX(Batches!$N$2:$N$301,$A71)&"") | I71: =IF($A71="","",INDEX(Batches!$G$2:$G$301,$A71)&"") | J71: =IF($A71="","",INDEX(Batches!$P$2:$P$301,$A71))
A72: =IFERROR(MATCH(19,Batches!$R$2:$R$301,0),"") | B72: =IF($A72="","",INDEX(Batches!$A$2:$A$301,$A72)&"") | C72: =IF($A72="","",INDEX(Batches!$J$2:$J$301,$A72)&"") | D72: =IF($A72="","",INDEX(Batches!$B$2:$B$301,$A72)&"") | E72: =IF($A72="","",INDEX(Batches!$L$2:$L$301,$A72)) | F72: =IF($A72="","",INDEX(Batches!$E$2:$E$301,$A72)) | G72: =IF($A72="","",INDEX(Batches!$M$2:$M$301,$A72)) | H72: =IF($A72="","",INDEX(Batches!$N$2:$N$301,$A72)&"") | I72: =IF($A72="","",INDEX(Batches!$G$2:$G$301,$A72)&"") | J72: =IF($A72="","",INDEX(Batches!$P$2:$P$301,$A72))
A73: =IFERROR(MATCH(20,Batches!$R$2:$R$301,0),"") | B73: =IF($A73="","",INDEX(Batches!$A$2:$A$301,$A73)&"") | C73: =IF($A73="","",INDEX(Batches!$J$2:$J$301,$A73)&"") | D73: =IF($A73="","",INDEX(Batches!$B$2:$B$301,$A73)&"") | E73: =IF($A73="","",INDEX(Batches!$L$2:$L$301,$A73)) | F73: =IF($A73="","",INDEX(Batches!$E$2:$E$301,$A73)) | G73: =IF($A73="","",INDEX(Batches!$M$2:$M$301,$A73)) | H73: =IF($A73="","",INDEX(Batches!$N$2:$N$301,$A73)&"") | I73: =IF($A73="","",INDEX(Batches!$G$2:$G$301,$A73)&"") | J73: =IF($A73="","",INDEX(Batches!$P$2:$P$301,$A73))
B75: Open tasks
B76: Tasks not done, earliest due date first. Up to 15 shown.
B77: Task ID | C77: Task | D77: Owner | E77: Due date | F77: Status | G77: Priority | H77: Overdue | I77: Days overdue | J77: Related to
A78: =IFERROR(MATCH(1,Tasks!$L$2:$L$301,0),"") -> 6 | B78: =IF($A78="","",INDEX(Tasks!$A$2:$A$301,$A78)&"") -> TSK-006 | C78: =IF($A78="","",INDEX(Tasks!$B$2:$B$301,$A78)&"") -> Get a new arrival date for PO-2026-031 from the carrier | D78: =IF($A78="","",INDEX(Tasks!$D$2:$D$301,$A78)&"") -> Luis Romero | E78: =IF($A78="","",INDEX(Tasks!$E$2:$E$301,$A78)) -> 46308 | F78: =IF($A78="","",INDEX(Tasks!$F$2:$F$301,$A78)&"") -> Blocked | G78: =IF($A78="","",INDEX(Tasks!$G$2:$G$301,$A78)&"") -> Medium | H78: =IF($A78="","",IF(INDEX(Tasks!$J$2:$J$301,$A78)=1,"Yes","")) -> Yes | I78: =IF($A78="","",INDEX(Tasks!$K$2:$K$301,$A78)) -> 2 | J78: =IF($A78="","",INDEX(Tasks!$C$2:$C$301,$A78)&"") -> PO-2026-031
A79: =IFERROR(MATCH(2,Tasks!$L$2:$L$301,0),"") -> 11 | B79: =IF($A79="","",INDEX(Tasks!$A$2:$A$301,$A79)&"") -> TSK-011 | C79: =IF($A79="","",INDEX(Tasks!$B$2:$B$301,$A79)&"") -> Ask finance for the August company sales total | D79: =IF($A79="","",INDEX(Tasks!$D$2:$D$301,$A79)&"") -> Hannah Becker | E79: =IF($A79="","",INDEX(Tasks!$E$2:$E$301,$A79)) -> 46309 | F79: =IF($A79="","",INDEX(Tasks!$F$2:$F$301,$A79)&"") -> In progress | G79: =IF($A79="","",INDEX(Tasks!$G$2:$G$301,$A79)&"") -> Low | H79: =IF($A79="","",IF(INDEX(Tasks!$J$2:$J$301,$A79)=1,"Yes","")) -> Yes | I79: =IF($A79="","",INDEX(Tasks!$K$2:$K$301,$A79)) -> 1 | J79: =IF($A79="","",INDEX(Tasks!$C$2:$C$301,$A79)&"") -> CMP-2026-02
A80: =IFERROR(MATCH(3,Tasks!$L$2:$L$301,0),"") -> 1 | B80: =IF($A80="","",INDEX(Tasks!$A$2:$A$301,$A80)&"") -> TSK-001 | C80: =IF($A80="","",INDEX(Tasks!$B$2:$B$301,$A80)&"") -> Chase Corliss Plant Proteins for the PO-2026-029 delivery date | D80: =IF($A80="","",INDEX(Tasks!$D$2:$D$301,$A80)&"") -> Luis Romero | E80: =IF($A80="","",INDEX(Tasks!$E$2:$E$301,$A80)) -> 46311 | F80: =IF($A80="","",INDEX(Tasks!$F$2:$F$301,$A80)&"") -> In progress | G80: =IF($A80="","",INDEX(Tasks!$G$2:$G$301,$A80)&"") -> High | H80: =IF($A80="","",IF(INDEX(Tasks!$J$2:$J$301,$A80)=1,"Yes","")) | I80: =IF($A80="","",INDEX(Tasks!$K$2:$K$301,$A80)) -> 0 | J80: =IF($A80="","",INDEX(Tasks!$C$2:$C$301,$A80)&"") -> PO-2026-029
A81: =IFERROR(MATCH(4,Tasks!$L$2:$L$301,0),"") -> 5 | B81: =IF($A81="","",INDEX(Tasks!$A$2:$A$301,$A81)&"") -> TSK-005 | C81: =IF($A81="","",INDEX(Tasks!$B$2:$B$301,$A81)&"") -> Sign off and send PO-2026-034 (creatine 500 g) | D81: =IF($A81="","",INDEX(Tasks!$D$2:$D$301,$A81)&"") -> Sam Whitfield | E81: =IF($A81="","",INDEX(Tasks!$E$2:$E$301,$A81)) -> 46311 | F81: =IF($A81="","",INDEX(Tasks!$F$2:$F$301,$A81)&"") -> Not started | G81: =IF($A81="","",INDEX(Tasks!$G$2:$G$301,$A81)&"") -> High | H81: =IF($A81="","",IF(INDEX(Tasks!$J$2:$J$301,$A81)=1,"Yes","")) | I81: =IF($A81="","",INDEX(Tasks!$K$2:$K$301,$A81)) -> 0 | J81: =IF($A81="","",INDEX(Tasks!$C$2:$C$301,$A81)&"") -> PO-2026-034
A82: =IFERROR(MATCH(5,Tasks!$L$2:$L$301,0),"") -> 2 | B82: =IF($A82="","",INDEX(Tasks!$A$2:$A$301,$A82)&"") -> TSK-002 | C82: =IF($A82="","",INDEX(Tasks!$B$2:$B$301,$A82)&"") -> Review the certificate of analysis and release lot WVA2609A | D82: =IF($A82="","",INDEX(Tasks!$D$2:$D$301,$A82)&"") -> Priya Nair | E82: =IF($A82="","",INDEX(Tasks!$E$2:$E$301,$A82)) -> 46312 | F82: =IF($A82="","",INDEX(Tasks!$F$2:$F$301,$A82)&"") -> Not started | G82: =IF($A82="","",INDEX(Tasks!$G$2:$G$301,$A82)&"") -> High | H82: =IF($A82="","",IF(INDEX(Tasks!$J$2:$J$301,$A82)=1,"Yes","")) | I82: =IF($A82="","",INDEX(Tasks!$K$2:$K$301,$A82)) -> 0 | J82: =IF($A82="","",INDEX(Tasks!$C$2:$C$301,$A82)&"") -> WVA2609A
A83: =IFERROR(MATCH(6,Tasks!$L$2:$L$301,0),"") -> 4 | B83: =IF($A83="","",INDEX(Tasks!$A$2:$A$301,$A83)&"") -> TSK-004 | C83: =IF($A83="","",INDEX(Tasks!$B$2:$B$301,$A83)&"") -> Plan a clearance offer for lot PBC2511A before it expires | D83: =IF($A83="","",INDEX(Tasks!$D$2:$D$301,$A83)&"") -> Maya Torres | E83: =IF($A83="","",INDEX(Tasks!$E$2:$E$301,$A83)) -> 46312 | F83: =IF($A83="","",INDEX(Tasks!$F$2:$F$301,$A83)&"") -> In progress | G83: =IF($A83="","",INDEX(Tasks!$G$2:$G$301,$A83)&"") -> High | H83: =IF($A83="","",IF(INDEX(Tasks!$J$2:$J$301,$A83)=1,"Yes","")) | I83: =IF($A83="","",INDEX(Tasks!$K$2:$K$301,$A83)) -> 0 | J83: =IF($A83="","",INDEX(Tasks!$C$2:$C$301,$A83)&"") -> PBC2511A
A84: =IFERROR(MATCH(7,Tasks!$L$2:$L$301,0),"") -> 3 | B84: =IF($A84="","",INDEX(Tasks!$A$2:$A$301,$A84)&"") -> TSK-003 | C84: =IF($A84="","",INDEX(Tasks!$B$2:$B$301,$A84)&"") -> Approve destruction of expired lot CKD2510A and post the write-off | D84: =IF($A84="","",INDEX(Tasks!$D$2:$D$301,$A84)&"") -> Ben Okafor | E84: =IF($A84="","",INDEX(Tasks!$E$2:$E$301,$A84)) -> 46315 | F84: =IF($A84="","",INDEX(Tasks!$F$2:$F$301,$A84)&"") -> Not started | G84: =IF($A84="","",INDEX(Tasks!$G$2:$G$301,$A84)&"") -> Medium | H84: =IF($A84="","",IF(INDEX(Tasks!$J$2:$J$301,$A84)=1,"Yes","")) | I84: =IF($A84="","",INDEX(Tasks!$K$2:$K$301,$A84)) -> 0 | J84: =IF($A84="","",INDEX(Tasks!$C$2:$C$301,$A84)&"") -> CKD2510A
A85: =IFERROR(MATCH(8,Tasks!$L$2:$L$301,0),"") -> 9 | B85: =IF($A85="","",INDEX(Tasks!$A$2:$A$301,$A85)&"") -> TSK-009 | C85: =IF($A85="","",INDEX(Tasks!$B$2:$B$301,$A85)&"") -> Approve the budget for CMP-2026-07 | D85: =IF($A85="","",INDEX(Tasks!$D$2:$D$301,$A85)&"") -> Sam Whitfield | E85: =IF($A85="","",INDEX(Tasks!$E$2:$E$301,$A85)) -> 46316 | F85: =IF($A85="","",INDEX(Tasks!$F$2:$F$301,$A85)&"") -> Not started | G85: =IF($A85="","",INDEX(Tasks!$G$2:$G$301,$A85)&"") -> Medium | H85: =IF($A85="","",IF(INDEX(Tasks!$J$2:$J$301,$A85)=1,"Yes","")) | I85: =IF($A85="","",INDEX(Tasks!$K$2:$K$301,$A85)) -> 0 | J85: =IF($A85="","",INDEX(Tasks!$C$2:$C$301,$A85)&"") -> CMP-2026-07
A86: =IFERROR(MATCH(9,Tasks!$L$2:$L$301,0),"") -> 10 | B86: =IF($A86="","",INDEX(Tasks!$A$2:$A$301,$A86)&"") -> TSK-010 | C86: =IF($A86="","",INDEX(Tasks!$B$2:$B$301,$A86)&"") -> Collect creator results for CMP-2026-04 | D86: =IF($A86="","",INDEX(Tasks!$D$2:$D$301,$A86)&"") -> Hannah Becker | E86: =IF($A86="","",INDEX(Tasks!$E$2:$E$301,$A86)) -> 46319 | F86: =IF($A86="","",INDEX(Tasks!$F$2:$F$301,$A86)&"") -> Not started | G86: =IF($A86="","",INDEX(Tasks!$G$2:$G$301,$A86)&"") -> Low | H86: =IF($A86="","",IF(INDEX(Tasks!$J$2:$J$301,$A86)=1,"Yes","")) | I86: =IF($A86="","",INDEX(Tasks!$K$2:$K$301,$A86)) -> 0 | J86: =IF($A86="","",INDEX(Tasks!$C$2:$C$301,$A86)&"") -> CMP-2026-04
A87: =IFERROR(MATCH(10,Tasks!$L$2:$L$301,0),"") | B87: =IF($A87="","",INDEX(Tasks!$A$2:$A$301,$A87)&"") | C87: =IF($A87="","",INDEX(Tasks!$B$2:$B$301,$A87)&"") | D87: =IF($A87="","",INDEX(Tasks!$D$2:$D$301,$A87)&"") | E87: =IF($A87="","",INDEX(Tasks!$E$2:$E$301,$A87)) | F87: =IF($A87="","",INDEX(Tasks!$F$2:$F$301,$A87)&"") | G87: =IF($A87="","",INDEX(Tasks!$G$2:$G$301,$A87)&"") | H87: =IF($A87="","",IF(INDEX(Tasks!$J$2:$J$301,$A87)=1,"Yes","")) | I87: =IF($A87="","",INDEX(Tasks!$K$2:$K$301,$A87)) | J87: =IF($A87="","",INDEX(Tasks!$C$2:$C$301,$A87)&"")
A88: =IFERROR(MATCH(11,Tasks!$L$2:$L$301,0),"") | B88: =IF($A88="","",INDEX(Tasks!$A$2:$A$301,$A88)&"") | C88: =IF($A88="","",INDEX(Tasks!$B$2:$B$301,$A88)&"") | D88: =IF($A88="","",INDEX(Tasks!$D$2:$D$301,$A88)&"") | E88: =IF($A88="","",INDEX(Tasks!$E$2:$E$301,$A88)) | F88: =IF($A88="","",INDEX(Tasks!$F$2:$F$301,$A88)&"") | G88: =IF($A88="","",INDEX(Tasks!$G$2:$G$301,$A88)&"") | H88: =IF($A88="","",IF(INDEX(Tasks!$J$2:$J$301,$A88)=1,"Yes","")) | I88: =IF($A88="","",INDEX(Tasks!$K$2:$K$301,$A88)) | J88: =IF($A88="","",INDEX(Tasks!$C$2:$C$301,$A88)&"")
A89: =IFERROR(MATCH(12,Tasks!$L$2:$L$301,0),"") | B89: =IF($A89="","",INDEX(Tasks!$A$2:$A$301,$A89)&"") | C89: =IF($A89="","",INDEX(Tasks!$B$2:$B$301,$A89)&"") | D89: =IF($A89="","",INDEX(Tasks!$D$2:$D$301,$A89)&"") | E89: =IF($A89="","",INDEX(Tasks!$E$2:$E$301,$A89)) | F89: =IF($A89="","",INDEX(Tasks!$F$2:$F$301,$A89)&"") | G89: =IF($A89="","",INDEX(Tasks!$G$2:$G$301,$A89)&"") | H89: =IF($A89="","",IF(INDEX(Tasks!$J$2:$J$301,$A89)=1,"Yes","")) | I89: =IF($A89="","",INDEX(Tasks!$K$2:$K$301,$A89)) | J89: =IF($A89="","",INDEX(Tasks!$C$2:$C$301,$A89)&"")
A90: =IFERROR(MATCH(13,Tasks!$L$2:$L$301,0),"") | B90: =IF($A90="","",INDEX(Tasks!$A$2:$A$301,$A90)&"") | C90: =IF($A90="","",INDEX(Tasks!$B$2:$B$301,$A90)&"") | D90: =IF($A90="","",INDEX(Tasks!$D$2:$D$301,$A90)&"") | E90: =IF($A90="","",INDEX(Tasks!$E$2:$E$301,$A90)) | F90: =IF($A90="","",INDEX(Tasks!$F$2:$F$301,$A90)&"") | G90: =IF($A90="","",INDEX(Tasks!$G$2:$G$301,$A90)&"") | H90: =IF($A90="","",IF(INDEX(Tasks!$J$2:$J$301,$A90)=1,"Yes","")) | I90: =IF($A90="","",INDEX(Tasks!$K$2:$K$301,$A90)) | J90: =IF($A90="","",INDEX(Tasks!$C$2:$C$301,$A90)&"")
A91: =IFERROR(MATCH(14,Tasks!$L$2:$L$301,0),"") | B91: =IF($A91="","",INDEX(Tasks!$A$2:$A$301,$A91)&"") | C91: =IF($A91="","",INDEX(Tasks!$B$2:$B$301,$A91)&"") | D91: =IF($A91="","",INDEX(Tasks!$D$2:$D$301,$A91)&"") | E91: =IF($A91="","",INDEX(Tasks!$E$2:$E$301,$A91)) | F91: =IF($A91="","",INDEX(Tasks!$F$2:$F$301,$A91)&"") | G91: =IF($A91="","",INDEX(Tasks!$G$2:$G$301,$A91)&"") | H91: =IF($A91="","",IF(INDEX(Tasks!$J$2:$J$301,$A91)=1,"Yes","")) | I91: =IF($A91="","",INDEX(Tasks!$K$2:$K$301,$A91)) | J91: =IF($A91="","",INDEX(Tasks!$C$2:$C$301,$A91)&"")
A92: =IFERROR(MATCH(15,Tasks!$L$2:$L$301,0),"") | B92: =IF($A92="","",INDEX(Tasks!$A$2:$A$301,$A92)&"") | C92: =IF($A92="","",INDEX(Tasks!$B$2:$B$301,$A92)&"") | D92: =IF($A92="","",INDEX(Tasks!$D$2:$D$301,$A92)&"") | E92: =IF($A92="","",INDEX(Tasks!$E$2:$E$301,$A92)) | F92: =IF($A92="","",INDEX(Tasks!$F$2:$F$301,$A92)&"") | G92: =IF($A92="","",INDEX(Tasks!$G$2:$G$301,$A92)&"") | H92: =IF($A92="","",IF(INDEX(Tasks!$J$2:$J$301,$A92)=1,"Yes","")) | I92: =IF($A92="","",INDEX(Tasks!$K$2:$K$301,$A92)) | J92: =IF($A92="","",INDEX(Tasks!$C$2:$C$301,$A92)&"")
B94: Record checks
B95: Rows whose Record check column is not OK (missing required fields, duplicate IDs, unknown references, inconsistent values).
B96: Sheet | C96: What is checked | D96: Rows | E96: Issues
B97: Products | C97: required fields, duplicate SKU, supplier, opening = lot openings, lots = recorded, negative stock | D97: =SUMPRODUCT(--(Products!$AB$2:$AB$101<>"")) -> 12 | E97: =SUMPRODUCT((Products!$AB$2:$AB$101<>"")*(Products!$AB$2:$AB$101<>"OK")) -> 0
B98: Suppliers | C98: required fields, duplicate ID, type and status lists | D98: =SUMPRODUCT(--(Suppliers!$P$2:$P$51<>"")) -> 5 | E98: =SUMPRODUCT((Suppliers!$P$2:$P$51<>"")*(Suppliers!$P$2:$P$51<>"OK")) -> 0
B99: Purchase_Orders | C99: required fields, duplicate PO, supplier and SKU exist, dates, received vs ordered vs status | D99: =SUMPRODUCT(--(Purchase_Orders!$S$2:$S$301<>"")) -> 12 | E99: =SUMPRODUCT((Purchase_Orders!$S$2:$S$301<>"")*(Purchase_Orders!$S$2:$S$301<>"OK")) -> 0
B100: Inventory_Ledger | C100: required fields, duplicate entry, SKU and lot exist, reason, quantity sign, date range | D100: =SUMPRODUCT(--(Inventory_Ledger!$P$2:$P$2001<>"")) -> 62 | E100: =SUMPRODUCT((Inventory_Ledger!$P$2:$P$2001<>"")*(Inventory_Ledger!$P$2:$P$2001<>"OK")) -> 0
B101: Batches | C101: required fields, duplicate lot, SKU and supplier exist, negative or closed lot balance | D101: =SUMPRODUCT(--(Batches!$S$2:$S$301<>"")) -> 27 | E101: =SUMPRODUCT((Batches!$S$2:$S$301<>"")*(Batches!$S$2:$S$301<>"OK")) -> 0
B102: Reservations | C102: required fields, duplicate ID, SKU exists, dates | D102: =SUMPRODUCT(--(Reservations!$M$2:$M$201<>"")) -> 8 | E102: =SUMPRODUCT((Reservations!$M$2:$M$201<>"")*(Reservations!$M$2:$M$201<>"OK")) -> 0
B103: Marketing | C103: required fields, duplicate ID, featured SKUs exist, channel and status lists | D103: =SUMPRODUCT(--(Marketing!$U$2:$U$101<>"")) -> 8 | E103: =SUMPRODUCT((Marketing!$U$2:$U$101<>"")*(Marketing!$U$2:$U$101<>"OK")) -> 0
B104: Milestones | C104: required fields, duplicate ID, product or campaign exists | D104: =SUMPRODUCT(--(Milestones!$K$2:$K$201<>"")) -> 20 | E104: =SUMPRODUCT((Milestones!$K$2:$K$201<>"")*(Milestones!$K$2:$K$201<>"OK")) -> 0
B105: Tasks | C105: required fields, duplicate ID, status list | D105: =SUMPRODUCT(--(Tasks!$M$2:$M$301<>"")) -> 12 | E105: =SUMPRODUCT((Tasks!$M$2:$M$301<>"")*(Tasks!$M$2:$M$301<>"OK")) -> 0
B106: Documents | C106: required fields, duplicate ID, link, type and status lists | D106: =SUMPRODUCT(--(Documents!$M$2:$M$201<>"")) -> 10 | E106: =SUMPRODUCT((Documents!$M$2:$M$201<>"")*(Documents!$M$2:$M$201<>"OK")) -> 0
B107: Total | D107: =SUM(D97:D106) -> 176 | E107: =SUM(E97:E106) -> 0
...

Sheet Config
A1: Config: settings, lists and import checks
A2: White cells can be changed. Every formula in the workbook reads these settings and lists.
A3: Setting | B3: Value | C3: What it does
A4: As-of date | B4: 46310 | C4: All day counts, overdue flags and expiry windows use this date. Change it to see the workbook on another day.
A5: Opening balance date | B5: 46204 | C5: Opening balances in Products and Batches are the units on hand on this date.
A6: Expiry window 1 (days) | B6: 30 | C6: First expiry window ends at this many days left.
A7: Expiry window 2 (days) | B7: 60 | C7: Second expiry window ends here.
A8: Expiry window 3 (days) | B8: 90 | C8: Third expiry window ends here. Lots beyond it are not alerted.
A9: Reorder test uses | B9: Available | C9: Available or Recorded: which stock is compared with the reorder point.
A10: Expired lots are held | B10: Yes | C10: Yes = units in expired lots are not available.
A11: File in Import_Staging | B11: warehouse-movements-2026-10-14.csv | C11: Name of the file now pasted in Import_Staging.
A13: Lists for dropdowns and rules. Add new values in the empty white cells under a list.
A14: Movement types | B14: Adjustment reasons | C14: PO statuses | D14: PO counts as open | E14: Lot statuses | F14: Lot holds stock | G14: Lot allowed on receipt | H14: Reservation statuses | I14: Reservation holds stock | J14: Task statuses | K14: Task counts as open | L14: Supplier types | M14: Supplier statuses | N14: Product categories | O14: Product statuses | P14: Campaign statuses | Q14: Channels | R14: Priorities | S14: Document types | T14: Document statuses | U14: Milestone kinds | V14: Milestone statuses | W14: Yes/No | X14: Reorder basis
A15: Receipt | B15: Cycle count | C15: Draft | D15: No | E15: Released | F15: No | G15: Yes | H15: Active | I15: Yes | J15: Not started | K15: Yes | L15: Manufacturer | M15: Active | N15: Whey protein | O15: Active | P15: Draft | Q15: Paid social | R15: High | S15: Spec sheet | T15: Current | U15: Product | V15: Planned | W15: Yes | X15: Available
A16: Shipment | B16: Damaged in warehouse | C16: Ordered | D16: Yes | E16: Quarantine | F16: Yes | G16: Yes | H16: Pending | I16: No | J16: In progress | K16: Yes | L16: Co-packer | M16: On hold | N16: Plant protein | O16: Discontinued | P16: In review | Q16: Short-form video | R16: Medium | S16: Certificate of analysis | T16: In review | U16: Campaign | V16: On track | W16: No | X16: Recorded
A17: Adjustment | B17: Expired write-off | C17: Confirmed | D17: Yes | E17: On hold | F17: Yes | G17: Yes | H17: Released | I17: No | J17: Blocked | K17: Yes | L17: Ingredient supplier | M17: Inactive | N17: Casein | P17: Approved | Q17: Email | R17: Low | S17: Label artwork | T17: Superseded | V17: At risk
B18: Marketing samples | C18: In transit | D18: Yes | E18: Closed | F18: No | G18: No | H18: Cancelled | I18: No | J18: Done | K18: No | L18: 3PL | N18: Protein bars | P18: Live | Q18: Influencer | S18: Agreement | V18: Late
B19: Customer return | C19: Partially received | D19: Yes | J19: Cancelled | K19: No | N19: Creatine | P19: Completed | Q19: Marketplace ads | S19: Allergen statement | V19: Done
B20: Other | C20: Received | D20: No | N20: Pre-workout | P20: Cancelled | Q20: Search ads | S20: SOP
C21: Cancelled | D21: No | Q21: Retail promotion | S21: Insurance certificate
Q22: Affiliate | S22: Campaign brief
A37: Import checks run on every Import_Staging row (catalog read by the formulas; do not reorder)
A38: # | B38: Code | C38: Field | D38: Issue | E38: Applies to | F38: What to do
A39: 1 | B39: ID_MISSING | C39: movement_id | D39: Missing required field | E39: All rows | F39: Add a unique movement_id.
A40: 2 | B40: ID_DUP_FILE | C40: movement_id | D40: Duplicate ID | E40: All rows | F40: Give the row its own ID, or delete it if it repeats an earlier row.
A41: 3 | B41: ID_DUP_LEDGER | C41: movement_id | D41: Duplicate ID | E41: All rows | F41: Delete the row if it was posted before; a new movement needs a new ID.
A42: 4 | B42: DATE_MISSING | C42: date | D42: Missing required field | E42: All rows | F42: Add the movement date (yyyy-mm-dd).
A43: 5 | B43: DATE_INVALID | C43: date | D43: Invalid date | E43: All rows | F43: Fix the date (yyyy-mm-dd).
A44: 6 | B44: DATE_FUTURE | C44: date | D44: Invalid date | E44: All rows | F44: Check the date; a movement cannot be after the as-of date.
A45: 7 | B45: TYPE_MISSING | C45: type | D45: Missing required field | E45: All rows | F45: Add the type: Receipt, Shipment or Adjustment.
A46: 8 | B46: TYPE_UNSUPPORTED | C46: type | D46: Unsupported type | E46: All rows | F46: Use a movement type listed on Config.
A47: 9 | B47: SKU_MISSING | C47: sku | D47: Missing required field | E47: All rows | F47: Add the SKU.
A48: 10 | B48: SKU_UNKNOWN | C48: sku | D48: Unknown product | E48: All rows | F48: Add the product in Products first, or correct the SKU.
A49: 11 | B49: SUP_MISSING | C49: supplier_id | D49: Missing required field | E49: Receipts | F49: Add the supplier ID.
A50: 12 | B50: SUP_UNKNOWN | C50: supplier_id | D50: Unknown supplier | E50: Rows with a supplier_id | F50: Add the supplier in Suppliers first, or correct the ID.
... A61: 23 | B61: NEG_STOCK | C61: qty | D61: Negative inventory | E61: Rows that change stock | F61: Check the quantity and sign against the warehouse count before posting.

Sheet Products
A1: SKU * | B1: Product name * | C1: Category * | D1: Flavour | E1: Size | F1: Primary supplier ID * | G1: Unit cost (USD) | H1: Opening balance * | I1: Reorder point * | J1: Reorder qty * | K1: Shelf life (months) | L1: Status * | M1: Notes | N1: Supplier name | O1: Receipts | P1: Shipments | Q1: Adjustments | R1: Recorded stock | S1: Reserved | T1: Held in lots | U1: Available | V1: On order (open POs) | W1: Lot balances total | X1: Lot openings total | Y1: Below reorder (1 = yes) | Z1: Stock status | AA1: Stock value (USD) | AB1: Record check | AC1: Alert order
A2: WPI-CHO-2LB | B2: Whey Protein Isolate, Chocolate, 2 lb | C2: Whey protein | D2: Chocolate | E2: 2 lb | F2: SUP-01 | G2: 18.4 | H2: 1240 | I2: 600 | J2: 1500 | K2: 24 | L2: Active | N2: =IF($A2="","",IFERROR(INDEX(Suppliers!$B$2:$B$51,MATCH($F2,Suppliers!$A$2:$A$51,0))&"","(not found)")) -> Alder Creek Dairy Proteins | O2: =IF($A2="","",SUMIFS(Inventory_Ledger!$E$2:$E$2001,Inventory_Ledger!$D$2:$D$2001,$A2,Inventory_Ledger!$C$2:$C$2001,"Receipt")) -> 1500 | P2: =IF($A2="","",SUMIFS(Inventory_Ledger!$E$2:$E$2001,Inventory_Ledger!$D$2:$D$2001,$A2,Inventory_Ledger!$C$2:$C$2001,"Shipment")) -> 2305 | Q2: =IF($A2="","",SUMIFS(Inventory_Ledger!$E$2:$E$2001,Inventory_Ledger!$D$2:$D$2001,$A2,Inventory_Ledger!$C$2:$C$2001,"Adjustment")) -> -6 | R2: =IF($A2="","",IF(ISNUMBER($H2),$H2,0)+$O2-$P2+$Q2) -> 429 | S2: =IF($A2="","",SUMIFS(Reservations!$L$2:$L$201,Reservations!$B$2:$B$201,$A2)) -> 120 | T2: =IF($A2="","",SUMIFS(Batches!$P$2:$P$301,Batches!$B$2:$B$301,$A2)) -> 0 | U2: =IF($A2="","",$R2-$S2-$T2) -> 309 | V2: =IF($A2="","",SUMIFS(Purchase_Orders!$N$2:$N$301,Purchase_Orders!$C$2:$C$301,$A2,Purchase_Orders!$O$2:$O$301,1)) -> 1500 | W2: =IF($A2="","",SUMIFS(Batches!$L$2:$L$301,Batches!$B$2:$B$301,$A2)) -> 429 | X2: =IF($A2="","",SUMIFS(Batches!$F$2:$F$301,Batches!$B$2:$B$301,$A2)) -> 1240 | Y2: =IF($A2="","",IF(ISNUMBER($I2),IF(IF(Config!$B$9="Recorded",$R2,$U2)<$I2,1,0),0)) -> 1 | Z2: =IF($A2="","",IF($R2<0,"Negative",IF($Y2=1,"Below reorder","OK"))) -> Below reorder | AA2: =IF($A2="","",IF(ISNUMBER($G2),$R2*$G2,"")) -> 7893.6 | AB2: =IF(COUNTA($A2:$M2)=0,"",IF($A2="","Missing: SKU",IF(COUNTIF($A$2:$A$101,$A2)>1,"Duplicate SKU",IF($B2="","Missing: product name",IF($C2="","Missing: category",IF($F2="","Missing: primary supplier",IF(NOT(ISNUMBER($H2)),"Missing: opening balance",IF(NOT(ISNUMBER($I2)),"Missing: reorder point",IF(NOT(ISNUMBER($J2)),"Missing: reorder qty",IF($L2="","Missing: status",IF(COUNTIF(Suppliers!$A$2:$A$51,$F2)=0,"Unknown supplier",IF(COUNTIF(Config!$N$15:$N$34,$C2)=0,"Unsupported category",IF(COUNTIF(Config!$O$15:$O$34,$L2)=0,"Unsupported status",IF($X2<>$H2,"Opening balance differs from lot openings",IF($W2<>$R2,"Lot balances differ from recorded stock",IF($R2<0,"Negative recorded stock","OK")))))))))))))))) -> OK | AC2: =IF($Y2=1,COUNTIF($Y$2:$Y2,1),"") -> 1
A3: WPI-VAN-2LB | B3: Whey Protein Isolate, Vanilla, 2 lb | C3: Whey protein | D3: Vanilla | E3: 2 lb | F3: SUP-01 | G3: 18.4 | H3: 846 | I3: 450 | J3: 1200 | K3: 24 | L3: Active | N3: =IF($A3="","",IFERROR(INDEX(Suppliers!$B$2:$B$51,MATCH($F3,Suppliers!$A$2:$A$51,0))&"","(not found)")) -> Alder Creek Dairy Proteins | O3: =IF($A3="","",SUMIFS(Inventory_Ledger!$E$2:$E$2001,Inventory_Ledger!$D$2:$D$2001,$A3,Inventory_Ledger!$C$2:$C$2001,"Receipt")) -> 600 | P3: =IF($A3="","",SUMIFS(Inventory_Ledger!$E$2:$E$2001,Inventory_Ledger!$D$2:$D$2001,$A3,Inventory_Ledger!$C$2:$C$2001,"Shipment")) -> 638 | Q3: =IF($A3="","",SUMIFS(Inventory_Ledger!$E$2:$E$2001,Inventory_Ledger!$D$2:$D$2001,$A3,Inventory_Ledger!$C$2:$C$2001,"Adjustment")) -> 0 | R3: =IF($A3="","",IF(ISNUMBER($H3),$H3,0)+$O3-$P3+$Q3) -> 808 | S3: =IF($A3="","",SUMIFS(Reservations!$L$2:$L$201,Reservations!$B$2:$B$201,$A3)) -> 0 | T3: =IF($A3="","",SUMIFS(Batches!$P$2:$P$301,Batches!$B$2:$B$301,$A3)) -> 600 | U3: =IF($A3="","",$R3-$S3-$T3) -> 208 | V3: =IF($A3="","",SUMIFS(Purchase_Orders!$N$2:$N$301,Purchase_Orders!$C$2:$C$301,$A3,Purchase_Orders!$O$2:$O$301,1)) -> 600 | W3: =IF($A3="","",SUMIFS(Batches!$L$2:$L$301,Batches!$B$2:$B$301,$A3)) -> 808 | X3: =IF($A3="","",SUMIFS(Batches!$F$2:$F$301,Batches!$B$2:$B$301,$A3)) -> 846 | Y3: =IF($A3="","",IF(ISNUMBER($I3),IF(IF(Config!$B$9="Recorded",$R3,$U3)<$I3,1,0),0)) -> 1 | Z3: =IF($A3="","",IF($R3<0,"Negative",IF($Y3=1,"Below reorder","OK"))) -> Below reorder | AA3: =IF($A3="","",IF(ISNUMBER($G3),$R3*$G3,"")) -> 14867.2 | AB3: =IF(COUNTA($A3:$M3)=0,"",IF($A3="","Missing: SKU",IF(COUNTIF($A$2:$A$101,$A3)>1,"Duplicate SKU",IF($B3="","Missing: product name",IF($C3="","Missing: category",IF($F3="","Missing: primary supplier",IF(NOT(ISNUMBER($H3)),"Missing: opening balance",IF(NOT(ISNUMBER($I3)),"Missing: reorder point",IF(NOT(ISNUMBER($J3)),"Missing: reorder qty",IF($L3="","Missing: status",IF(COUNTIF(Suppliers!$A$2:$A$51,$F3)=0,"Unknown supplier",IF(COUNTIF(Config!$N$15:$N$34,$C3)=0,"Unsupported category",IF(COUNTIF(Config!$O$15:$O$34,$L3)=0,"Unsupported status",IF($X3<>$H3,"Opening balance differs from lot openings",IF($W3<>$R3,"Lot balances differ from recorded stock",IF($R3<0,"Negative recorded stock","OK")))))))))))))))) -> OK | AC3: =IF($Y3=1,COUNTIF($Y$2:$Y3,1),"") -> 2
A4: WPI-CHO-5LB | B4: Whey Protein Isolate, Chocolate, 5 lb | C4: Whey protein | D4: Chocolate | E4: 5 lb | F4: SUP-05 | G4: 39.8 | H4: 467 | I4: 150 | J4: 400 | K4: 24 | L4: Active | N4: =IF($A4="","",IFERROR(INDEX(Suppliers!$B$2:$B$51,MATCH($F4,Suppliers!$A$2:$A$51,0))&"","(not found)")) -> Elmstead Co-Packing | O4: =IF($A4="","",SUMIFS(Inventory_Ledger!$E$2:$E$2001,Inventory_Ledger!$D$2:$D$2001,$A4,Inventory_Ledger!$C$2:$C$2001,"Receipt")) -> 0 | P4: =IF($A4="","",SUMIFS(Inventory_Ledger!$E$2:$E$2001,Inventory_Ledger!$D$2:$D$2001,$A4,Inventory_Ledger!$C$2:$C$2001,"Shipment")) -> 203 | Q4: =IF($A4="","",SUMIFS(Inventory_Ledger!$E$2:$E$2001,Inventory_Ledger!$D$2:$D$2001,$A4,Inventory_Ledger!$C$2:$C$2001,"Adjustment")) -> 0 | R4: =IF($A4="","",IF(ISNUMBER($H4),$H4,0)+$O4-$P4+$Q4) -> 264 | S4: =IF($A4="","",SUMIFS(Reservations!$L$2:$L$201,Reservations!$B$2:$B$201,$A4)) -> 0 | T4: =IF($A4="","",SUMIFS(Batches!$P$2:$P$301,Batches!$B$2:$B$301,$A4)) -> 0 | U4: =IF($A4="","",$R4-$S4-$T4) -> 264 | V4: =IF($A4="","",SUMIFS(Purchase_Orders!$N$2:$N$301,Purchase_Orders!$C$2:$C$301,$A4,Purchase_Orders!$O$2:$O$301,1)) -> 0 | W4: =IF($A4="","",SUMIFS(Batches!$L$2:$L$301,Batches!$B$2:$B$301,$A4)) -> 264 | X4: =IF($A4="","",SUMIFS(Batches!$F$2:$F$301,Batches!$B$2:$B$301,$A4)) -> 467 | Y4: =IF($A4="","",IF(ISNUMBER($I4),IF(IF(Config!$B$9="Recorded",$R4,$U4)<$I4,1,0),0)) -> 0 | Z4: =IF($A4="","",IF($R4<0,"Negative",IF($Y4=1,"Below reorder","OK"))) -> OK | AA4: =IF($A4="","",IF(ISNUMBER($G4),$R4*$G4,"")) -> 10507.2 | AB4: =IF(COUNTA($A4:$M4)=0,"",IF($A4="","Missing: SKU",IF(COUNTIF($A$2:$A$101,$A4)>1,"Duplicate SKU",IF($B4="","Missing: product name",IF($C4="","Missing: category",IF($F4="","Missing: primary supplier",IF(NOT(ISNUMBER($H4)),"Missing: opening balance",IF(NOT(ISNUMBER($I4)),"Missing: reorder point",IF(NOT(ISNUMBER($J4)),"Missing: reorder qty",IF($L4="","Missing: status",IF(COUNTIF(Suppliers!$A$2:$A$51,$F4)=0,"Unknown supplier",IF(COUNTIF(Config!$N$15:$N$34,$C4)=0,"Unsupported category",IF(COUNTIF(Config!$O$15:$O$34,$L4)=0,"Unsupported status",IF($X4<>$H4,"Opening balance differs from lot openings",IF($W4<>$R4,"Lot balances differ from recorded stock",IF($R4<0,"Negative recorded stock","OK")))))))))))))))) -> OK | AC4: =IF($Y4=1,COUNTIF($Y$2:$Y4,1),"")
A5: PLT-CHO-2LB | B5: Plant Protein, Chocolate, 2 lb | C5: Plant protein | D5: Chocolate | E5: 2 lb | F5: SUP-03 | G5: 16.1 | H5: 850 | I5: 250 | J5: 600 | K5: 24 | L5: Active | N5: =IF($A5="","",IFERROR(INDEX(Suppliers!$B$2:$B$51,MATCH($F5,Suppliers!$A$2:$A$51,0))&"","(not found)")) -> Corliss Plant Proteins | O5: =IF($A5="","",SUMIFS(Inventory_Ledger!$E$2:$E$2001,Inventory_Ledger!$D$2:$D$2001,$A5,Inventory_Ledger!$C$2:$C$2001,"Receipt")) -> 0 | P5: =IF($A5="","",SUMIFS(Inventory_Ledger!$E$2:$E$2001,Inventory_Ledger!$D$2:$D$2001,$A5,Inventory_Ledger!$C$2:$C$2001,"Shipment")) -> 451 | Q5: =IF($A5="","",SUMIFS(Inventory_Ledger!$E$2:$E$2001,Inventory_Ledger!$D$2:$D$2001,$A5,Inventory_Ledger!$C$2:$C$2001,"Adjustment")) -> -3 | R5: =IF($A5="","",IF(ISNUMBER($H5),$H5,0)+$O5-$P5+$Q5) -> 396 | S5: =IF($A5="","",SUMIFS(Reservations!$L$2:$L$201,Reservations!$B$2:$B$201,$A5)) -> 0 | T5: =IF($A5="","",SUMIFS(Batches!$P$2:$P$301,Batches!$B$2:$B$301,$A5)) -> 0 | U5: =IF($A5="","",$R5-$S5-$T5) -> 396 | V5: =IF($A5="","",SUMIFS(Purchase_Orders!$N$2:$N$301,Purchase_Orders!$C$2:$C$301,$A5,Purchase_Orders!$O$2:$O$301,1)) -> 0 | W5: =IF($A5="","",SUMIFS(Batches!$L$2:$L$301,Batches!$B$2:$B$301,$A5)) -> 396 | X5: =IF($A5="","",SUMIFS(Batches!$F$2:$F$301,Batches!$B$2:$B$301,$A5)) -> 850 | Y5: =IF($A5="","",IF(ISNUMBER($I5),IF(IF(Config!$B$9="Recorded",$R5,$U5)<$I5,1,0),0)) -> 0 | Z5: =IF($A5="","",IF($R5<0,"Negative",IF($Y5=1,"Below reorder","OK"))) -> OK | AA5: =IF($A5="","",IF(ISNUMBER($G5),$R5*$G5,"")) -> 6375.6 | AB5: =IF(COUNTA($A5:$M5)=0,"",IF($A5="","Missing: SKU",IF(COUNTIF($A$2:$A$101,$A5)>1,"Duplicate SKU",IF($B5="","Missing: product name",IF($C5="","Missing: category",IF($F5="","Missing: primary supplier",IF(NOT(ISNUMBER($H5)),"Missing: opening balance",IF(NOT(ISNUMBER($I5)),"Missing: reorder point",IF(NOT(ISNUMBER($J5)),"Missing: reorder qty",IF($L5="","Missing: status",IF(COUNTIF(Suppliers!$A$2:$A$51,$F5)=0,"Unknown supplier",IF(COUNTIF(Config!$N$15:$N$34,$C5)=0,"Unsupported category",IF(COUNTIF(Config!$O$15:$O$34,$L5)=0,"Unsupported status",IF($X5<>$H5,"Opening balance differs from lot openings",IF($W5<>$R5,"Lot balances differ from recorded stock",IF($R5<0,"Negative recorded stock","OK")))))))))))))))) -> OK | AC5: =IF($Y5=1,COUNTIF($Y$2:$Y5,1),"")
A6: PLT-VAN-2LB | B6: Plant Protein, Vanilla, 2 lb | C6: Plant protein | D6: Vanilla | E6: 2 lb | F6: SUP-03 | G6: 16.1 | H6: 407 | I6: 200 | J6: 500 | K6: 24 | L6: Active | N6: =IF($A6="","",IFERROR(INDEX(Suppliers!$B$2:$B$51,MATCH($F6,Suppliers!$A$2:$A$51,0))&"","(not found)")) -> Corliss Plant Proteins | O6: =IF($A6="","",SUMIFS(Inventory_Ledger!$E$2:$E$2001,Inventory_Ledger!$D$2:$D$2001,$A6,Inventory_Ledger!$C$2:$C$2001,"Receipt")) -> 0 | P6: =IF($A6="","",SUMIFS(Inventory_Ledger!$E$2:$E$2001,Inventory_Ledger!$D$2:$D$2001,$A6,Inventory_Ledger!$C$2:$C$2001,"Shipment")) -> 274 | Q6: =IF($A6="","",SUMIFS(Inventory_Ledger!$E$2:$E$2001,Inventory_Ledger!$D$2:$D$2001,$A6,Inventory_Ledger!$C$2:$C$2001,"Adjustment")) -> 0 | R6: =IF($A6="","",IF(ISNUMBER($H6),$H6,0)+$O6-$P6+$Q6) -> 133 | S6: =IF($A6="","",SUMIFS(Reservations!$L$2:$L$201,Reservations!$B$2:$B$201,$A6)) -> 0 | T6: =IF($A6="","",SUMIFS(Batches!$P$2:$P$301,Batches!$B$2:$B$301,$A6)) -> 0 | U6: =IF($A6="","",$R6-$S6-$T6) -> 133 | V6: =IF($A6="","",SUMIFS(Purchase_Orders!$N$2:$N$301,Purchase_Orders!$C$2:$C$301,$A6,Purchase_Orders!$O$2:$O$301,1)) -> 500 | W6: =IF($A6="","",SUMIFS(Batches!$L$2:$L$301,Batches!$B$2:$B$301,$A6)) -> 133 | X6: =IF($A6="","",SUMIFS(Batches!$F$2:$F$301,Batches!$B$2:$B$301,$A6)) -> 407 | Y6: =IF($A6="","",IF(ISNUMBER($I6),IF(IF(Config!$B$9="Recorded",$R6,$U6)<$I6,1,0),0)) -> 1 | Z6: =IF($A6="","",IF($R6<0,"Negative",IF($Y6=1,"Below reorder","OK"))) -> Below reorder | AA6: =IF($A6="","",IF(ISNUMBER($G6),$R6*$G6,"")) -> 2141.3 | AB6: =IF(COUNTA($A6:$M6)=0,"",IF($A6="","Missing: SKU",IF(COUNTIF($A$2:$A$101,$A6)>1,"Duplicate SKU",IF($B6="","Missing: product name",IF($C6="","Missing: category",IF($F6="","Missing: primary supplier",IF(NOT(ISNUMBER($H6)),"Missing: opening balance",IF(NOT(ISNUMBER($I6)),"Missing: reorder point",IF(NOT(ISNUMBER($J6)),"Missing: reorder qty",IF($L6="","Missing: status",IF(COUNTIF(Suppliers!$A$2:$A$51,$F6)=0,"Unknown supplier",IF(COUNTIF(Config!$N$15:$N$34,$C6)=0,"Unsupported category",IF(COUNTIF(Config!$O$15:$O$34,$L6)=0,"Unsupported status",IF($X6<>$H6,"Opening balance differs from lot openings",IF($W6<>$R6,"Lot balances differ from recorded stock",IF($R6<0,"Negative recorded stock","OK")))))))))))))))) -> OK | AC6: =IF($Y6=1,COUNTIF($Y$2:$Y6,1),"") -> 3
A7: BAR-PBC-12 | B7: Protein Bar, Peanut Butter Chocolate, 12-pack | C7: Protein bars | D7: Peanut butter chocolate | E7: 12-pack | F7: SUP-02 | G7: 11.2 | H7: 2288 | I7: 900 | J7: 2400 | K7: 12 | L7: Active | N7: =IF($A7="","",IFERROR(INDEX(Suppliers!$B$2:$B$51,MATCH($F7,Suppliers!$A$2:$A$51,0))&"","(not found)")) -> Bramwell Bar Works | O7: =IF($A7="","",SUMIFS(Inventory_Ledger!$E$2:$E$2001,Inventory_Ledger!$D$2:$D$2001,$A7,Inventory_Ledger!$C$2:$C$2001,"Receipt")) -> 2400 | P7: =IF($A7="","",SUMIFS(Inventory_Ledger!$E$2:$E$2001,Inventory_Ledger!$D$2:$D$2001,$A7,Inventory_Ledger!$C$2:$C$2001,"Shipment")) -> 1944 | Q7: =IF($A7="","",SUMIFS(Inventory_Ledger!$E$2:$E$2001,Inventory_Ledger!$D$2:$D$2001,$A7,Inventory_Ledger!$C$2:$C$2001,"Adjustment")) -> 0 | R7: =IF($A7="","",IF(ISNUMBER($H7),$H7,0)+$O7-$P7+$Q7) -> 2744 | S7: =IF($A7="","",SUMIFS(Reservations!$L$2:$L$201,Reservations!$B$2:$B$201,$A7)) -> 200 | T7: =IF($A7="","",SUMIFS(Batches!$P$2:$P$301,Batches!$B$2:$B$301,$A7)) -> 0 | U7: =IF($A7="","",$R7-$S7-$T7) -> 2544 | V7: =IF($A7="","",SUMIFS(Purchase_Orders!$N$2:$N$301,Purchase_Orders!$C$2:$C$301,$A7,Purchase_Orders!$O$2:$O$301,1)) -> 0 | W7: =IF($A7="","",SUMIFS(Batches!$L$2:$L$301,Batches!$B$2:$B$301,$A7)) -> 2744 | X7: =IF($A7="","",SUMIFS(Batches!$F$2:$F$301,Batches!$B$2:$B$301,$A7)) -> 2288 | Y7: =IF($A7="","",IF(ISNUMBER($I7),IF(IF(Config!$B$9="Recorded",$R7,$U7)<$I7,1,0),0)) -> 0 | Z7: =IF($A7="","",IF($R7<0,"Negative",IF($Y7=1,"Below reorder","OK"))) -> OK | AA7: =IF($A7="","",IF(ISNUMBER($G7),$R7*$G7,"")) -> 30732.8 | AB7: =IF(COUNTA($A7:$M7)=0,"",IF($A7="","Missing: SKU",IF(COUNTIF($A$2:$A$101,$A7)>1,"Duplicate SKU",IF($B7="","Missing: product name",IF($C7="","Missing: category",IF($F7="","Missing: primary supplier",IF(NOT(ISNUMBER($H7)),"Missing: opening balance",IF(NOT(ISNUMBER($I7)),"Missing: reorder point",IF(NOT(ISNUMBER($J7)),"Missing: reorder qty",IF($L7="","Missing: status",IF(COUNTIF(Suppliers!$A$2:$A$51,$F7)=0,"Unknown supplier",IF(COUNTIF(Config!$N$15:$N$34,$C7)=0,"Unsupported category",IF(COUNTIF(Config!$O$15:$O$34,$L7)=0,"Unsupported status",IF($X7<>$H7,"Opening balance differs from lot openings",IF($W7<>$R7,"Lot balances differ from recorded stock",IF($R7<0,"Negative recorded stock","OK")))))))))))))))) -> OK | AC7: =IF($Y7=1,COUNTIF($Y$2:$Y7,1),"")
A8: BAR-CKD-12 | B8: Protein Bar, Cookie Dough, 12-pack | C8: Protein bars | D8: Cookie dough | E8: 12-pack | F8: SUP-02 | G8: 11.2 | H8: 1889 | I8: 700 | J8: 1500 | K8: 12 | L8: Active | N8: =IF($A8="","",IFERROR(INDEX(Suppliers!$B$2:$B$51,MATCH($F8,Suppliers!$A$2:$A$51,0))&"","(not found)")) -> Bramwell Bar Works | O8: =IF($A8="","",SUMIFS(Inventory_Ledger!$E$2:$E$2001,Inventory_Ledger!$D$2:$D$2001,$A8,Inventory_Ledger!$C$2:$C$2001,"Receipt")) -> 1500 | P8: =IF($A8="","",SUMIFS(Inventory_Ledger!$E$2:$E$2001,Inventory_Ledger!$D$2:$D$2001,$A8,Inventory_Ledger!$C$2:$C$2001,"Shipment")) -> 1581 | Q8: =IF($A8="","",SUMIFS(Inventory_Ledger!$E$2:$E$2001,Inventory_Ledger!$D$2:$D$2001,$A8,Inventory_Ledger!$C$2:$C$2001,"Adjustment")) -> -60 | R8: =IF($A8="","",IF(ISNUMBER($H8),$H8,0)+$O8-$P8+$Q8) -> 1748 | S8: =IF($A8="","",SUMIFS(Reservations!$L$2:$L$201,Reservations!$B$2:$B$201,$A8)) -> 150 | T8: =IF($A8="","",SUMIFS(Batches!$P$2:$P$301,Batches!$B$2:$B$301,$A8)) -> 36 | U8: =IF($A8="","",$R8-$S8-$T8) -> 1562 | V8: =IF($A8="","",SUMIFS(Purchase_Orders!$N$2:$N$301,Purchase_Orders!$C$2:$C$301,$A8,Purchase_Orders!$O$2:$O$301,1)) -> 0 | W8: =IF($A8="","",SUMIFS(Batches!$L$2:$L$301,Batches!$B$2:$B$301,$A8)) -> 1748 | X8: =IF($A8="","",SUMIFS(Batches!$F$2:$F$301,Batches!$B$2:$B$301,$A8)) -> 1889 | Y8: =IF($A8="","",IF(ISNUMBER($I8),IF(IF(Config!$B$9="Recorded",$R8,$U8)<$I8,1,0),0)) -> 0 | Z8: =IF($A8="","",IF($R8<0,"Negative",IF($Y8=1,"Below reorder","OK"))) -> OK | AA8: =IF($A8="","",IF(ISNUMBER($G8),$R8*$G8,"")) -> 19577.6 | AB8: =IF(COUNTA($A8:$M8)=0,"",IF($A8="","Missing: SKU",IF(COUNTIF($A$2:$A$101,$A8)>1,"Duplicate SKU",IF($B8="","Missing: product name",IF($C8="","Missing: category",IF($F8="","Missing: primary supplier",IF(NOT(ISNUMBER($H8)),"Missing: opening balance",IF(NOT(ISNUMBER($I8)),"Missing: reorder point",IF(NOT(ISNUMBER($J8)),"Missing: reorder qty",IF($L8="","Missing: status",IF(COUNTIF(Suppliers!$A$2:$A$51,$F8)=0,"Unknown supplier",IF(COUNTIF(Config!$N$15:$N$34,$C8)=0,"Unsupported category",IF(COUNTIF(Config!$O$15:$O$34,$L8)=0,"Unsupported status",IF($X8<>$H8,"Opening balance differs from lot openings",IF($W8<>$R8,"Lot balances differ from recorded stock",IF($R8<0,"Negative recorded stock","OK")))))))))))))))) -> OK | AC8: =IF($Y8=1,COUNTIF($Y$2:$Y8,1),"")
A9: CRE-UNF-300G | B9: Creatine Monohydrate, Unflavoured, 300 g | C9: Creatine | D9: Unflavoured | E9: 300 g | F9: SUP-04 | G9: 6.9 | H9: 980 | I9: 400 | J9: 1000 | K9: 36 | L9: Active | N9: =IF($A9="","",IFERROR(INDEX(Suppliers!$B$2:$B$51,MATCH($F9,Suppliers!$A$2:$A$51,0))&"","(not found)")) -> Dunmore Powder Labs | O9: =IF($A9="","",SUMIFS(Inventory_Ledger!$E$2:$E$2001,Inventory_Ledger!$D$2:$D$2001,$A9,Inventory_Ledger!$C$2:$C$2001,"Receipt")) -> 1000 | P9: =IF($A9="","",SUMIFS(Inventory_Ledger!$E$2:$E$2001,Inventory_Ledger!$D$2:$D$2001,$A9,Inventory_Ledger!$C$2:$C$2001,"Shipment")) -> 865 | Q9: =IF($A9="","",SUMIFS(Inventory_Ledger!$E$2:$E$2001,Inventory_Ledger!$D$2:$D$2001,$A9,Inventory_Ledger!$C$2:$C$2001,"Adjustment")) -> 4 | R9: =IF($A9="","",IF(ISNUMBER($H9),$H9,0)+$O9-$P9+$Q9) -> 1119 | S9: =IF($A9="","",SUMIFS(Reservations!$L$2:$L$201,Reservations!$B$2:$B$201,$A9)) -> 0 | T9: =IF($A9="","",SUMIFS(Batches!$P$2:$P$301,Batches!$B$2:$B$301,$A9)) -> 0 | U9: =IF($A9="","",$R9-$S9-$T9) -> 1119 | V9: =IF($A9="","",SUMIFS(Purchase_Orders!$N$2:$N$301,Purchase_Orders!$C$2:$C$301,$A9,Purchase_Orders!$O$2:$O$301,1)) -> 0 | W9: =IF($A9="","",SUMIFS(Batches!$L$2:$L$301,Batches!$B$2:$B$301,$A9)) -> 1119 | X9: =IF($A9="","",SUMIFS(Batches!$F$2:$F$301,Batches!$B$2:$B$301,$A9)) -> 980 | Y9: =IF($A9="","",IF(ISNUMBER($I9),IF(IF(Config!$B$9="Recorded",$R9,$U9)<$I9,1,0),0)) -> 0 | Z9: =IF($A9="","",IF($R9<0,"Negative",IF($Y9=1,"Below reorder","OK"))) -> OK | AA9: =IF($A9="","",IF(ISNUMBER($G9),$R9*$G9,"")) -> 7721.1 | AB9: =IF(COUNTA($A9:$M9)=0,"",IF($A9="","Missing: SKU",IF(COUNTIF($A$2:$A$101,$A9)>1,"Duplicate SKU",IF($B9="","Missing: product name",IF($C9="","Missing: category",IF($F9="","Missing: primary supplier",IF(NOT(ISNUMBER($H9)),"Missing: opening balance",IF(NOT(ISNUMBER($I9)),"Missing: reorder point",IF(NOT(ISNUMBER($J9)),"Missing: reorder qty",IF($L9="","Missing: status",IF(COUNTIF(Suppliers!$A$2:$A$51,$F9)=0,"Unknown supplier",IF(COUNTIF(Config!$N$15:$N$34,$C9)=0,"Unsupported category",IF(COUNTIF(Config!$O$15:$O$34,$L9)=0,"Unsupported status",IF($X9<>$H9,"Opening balance differs from lot openings",IF($W9<>$R9,"Lot balances differ from recorded stock",IF($R9<0,"Negative recorded stock","OK")))))))))))))))) -> OK | AC9: =IF($Y9=1,COUNTIF($Y$2:$Y9,1),"")
A10: CRE-UNF-500G | B10: Creatine Monohydrate, Unflavoured, 500 g | C10: Creatine | D10: Unflavoured | E10: 500 g | F10: SUP-04 | G10: 10.3 | H10: 640 | I10: 250 | J10: 700 | K10: 36 | L10: Active | N10: =IF($A10="","",IFERROR(INDEX(Suppliers!$B$2:$B$51,MATCH($F10,Suppliers!$A$2:$A$51,0))&"","(not found)")) -> Dunmore Powder Labs | O10: =IF($A10="","",SUMIFS(Inventory_Ledger!$E$2:$E$2001,Inventory_Ledger!$D$2:$D$2001,$A10,Inventory_Ledger!$C$2:$C$2001,"Receipt")) -> 0 | P10: =IF($A10="","",SUMIFS(Inventory_Ledger!$E$2:$E$2001,Inventory_Ledger!$D$2:$D$2001,$A10,Inventory_Ledger!$C$2:$C$2001,"Shipment")) -> 350 | Q10: =IF($A10="","",SUMIFS(Inventory_Ledger!$E$2:$E$2001,Inventory_Ledger!$D$2:$D$2001,$A10,Inventory_Ledger!$C$2:$C$2001,"Adjustment")) -> 0 | R10: =IF($A10="","",IF(ISNUMBER($H10),$H10,0)+$O10-$P10+$Q10) -> 290 | S10: =IF($A10="","",SUMIFS(Reservations!$L$2:$L$201,Reservations!$B$2:$B$201,$A10)) -> 80 | T10: =IF($A10="","",SUMIFS(Batches!$P$2:$P$301,Batches!$B$2:$B$301,$A10)) -> 0 | U10: =IF($A10="","",$R10-$S10-$T10) -> 210 | V10: =IF($A10="","",SUMIFS(Purchase_Orders!$N$2:$N$301,Purchase_Orders!$C$2:$C$301,$A10,Purchase_Orders!$O$2:$O$301,1)) -> 0 | W10: =IF($A10="","",SUMIFS(Batches!$L$2:$L$301,Batches!$B$2:$B$301,$A10)) -> 290 | X10: =IF($A10="","",SUMIFS(Batches!$F$2:$F$301,Batches!$B$2:$B$301,$A10)) -> 640 | Y10: =IF($A10="","",IF(ISNUMBER($I10),IF(IF(Config!$B$9="Recorded",$R10,$U10)<$I10,1,0),0)) -> 1 | Z10: =IF($A10="","",IF($R10<0,"Negative",IF($Y10=1,"Below reorder","OK"))) -> Below reorder | AA10: =IF($A10="","",IF(ISNUMBER($G10),$R10*$G10,"")) -> 2987 | AB10: =IF(COUNTA($A10:$M10)=0,"",IF($A10="","Missing: SKU",IF(COUNTIF($A$2:$A$101,$A10)>1,"Duplicate SKU",IF($B10="","Missing: product name",IF($C10="","Missing: category",IF($F10="","Missing: primary supplier",IF(NOT(ISNUMBER($H10)),"Missing: opening balance",IF(NOT(ISNUMBER($I10)),"Missing: reorder point",IF(NOT(ISNUMBER($J10)),"Missing: reorder qty",IF($L10="","Missing: status",IF(COUNTIF(Suppliers!$A$2:$A$51,$F10)=0,"Unknown supplier",IF(COUNTIF(Config!$N$15:$N$34,$C10)=0,"Unsupported category",IF(COUNTIF(Config!$O$15:$O$34,$L10)=0,"Unsupported status",IF($X10<>$H10,"Opening balance differs from lot openings",IF($W10<>$R10,"Lot balances differ from recorded stock",IF($R10<0,"Negative recorded stock","OK")))))))))))))))) -> OK | AC10: =IF($Y10=1,COUNTIF($Y$2:$Y10,1),"") -> 4
A11: PRE-BRZ-30 | B11: Pre-Workout, Blue Raspberry, 30 servings | C11: Pre-workout | D11: Blue raspberry | E11: 30 servings | F11: SUP-04 | G11: 9.6 | H11: 746 | I11: 300 | J11: 800 | K11: 24 | L11: Active | N11: =IF($A11="","",IFERROR(INDEX(Suppliers!$B$2:$B$51,MATCH($F11,Suppliers!$A$2:$A$51,0))&"","(not found)")) -> Dunmore Powder Labs | O11: =IF($A11="","",SUMIFS(Inventory_Ledger!$E$2:$E$2001,Inventory_Ledger!$D$2:$D$2001,$A11,Inventory_Ledger!$C$2:$C$2001,"Receipt")) -> 800 | P11: =IF($A11="","",SUMIFS(Inventory_Ledger!$E$2:$E$2001,Inventory_Ledger!$D$2:$D$2001,$A11,Inventory_Ledger!$C$2:$C$2001,"Shipment")) -> 671 | Q11: =IF($A11="","",SUMIFS(Inventory_Ledger!$E$2:$E$2001,Inventory_Ledger!$D$2:$D$2001,$A11,Inventory_Ledger!$C$2:$C$2001,"Adjustment")) -> 0 | R11: =IF($A11="","",IF(ISNUMBER($H11),$H11,0)+$O11-$P11+$Q11) -> 875 | S11: =IF($A11="","",SUMIFS(Reservations!$L$2:$L$201,Reservations!$B$2:$B$201,$A11)) -> 0 | T11: =IF($A11="","",SUMIFS(Batches!$P$2:$P$301,Batches!$B$2:$B$301,$A11)) -> 0 | U11: =IF($A11="","",$R11-$S11-$T11) -> 875 | V11: =IF($A11="","",SUMIFS(Purchase_Orders!$N$2:$N$301,Purchase_Orders!$C$2:$C$301,$A11,Purchase_Orders!$O$2:$O$301,1)) -> 0 | W11: =IF($A11="","",SUMIFS(Batches!$L$2:$L$301,Batches!$B$2:$B$301,$A11)) -> 875 | X11: =IF($A11="","",SUMIFS(Batches!$F$2:$F$301,Batches!$B$2:$B$301,$A11)) -> 746 | Y11: =IF($A11="","",IF(ISNUMBER($I11),IF(IF(Config!$B$9="Recorded",$R11,$U11)<$I11,1,0),0)) -> 0 | Z11: =IF($A11="","",IF($R11<0,"Negative",IF($Y11=1,"Below reorder","OK"))) -> OK | AA11: =IF($A11="","",IF(ISNUMBER($G11),$R11*$G11,"")) -> 8400 | AB11: =IF(COUNTA($A11:$M11)=0,"",IF($A11="","Missing: SKU",IF(COUNTIF($A$2:$A$101,$A11)>1,"Duplicate SKU",IF($B11="","Missing: product name",IF($C11="","Missing: category",IF($F11="","Missing: primary supplier",IF(NOT(ISNUMBER($H11)),"Missing: opening balance",IF(NOT(ISNUMBER($I11)),"Missing: reorder point",IF(NOT(ISNUMBER($J11)),"Missing: reorder qty",IF($L11="","Missing: status",IF(COUNTIF(Suppliers!$A$2:$A$51,$F11)=0,"Unknown supplier",IF(COUNTIF(Config!$N$15:$N$34,$C11)=0,"Unsupported category",IF(COUNTIF(Config!$O$15:$O$34,$L11)=0,"Unsupported status",IF($X11<>$H11,"Opening balance differs from lot openings",IF($W11<>$R11,"Lot balances differ from recorded stock",IF($R11<0,"Negative recorded stock","OK")))))))))))))))) -> OK | AC11: =IF($Y11=1,COUNTIF($Y$2:$Y11,1),"")
A12: PRE-WTM-30 | B12: Pre-Workout, Watermelon, 30 servings | C12: Pre-workout | D12: Watermelon | E12: 30 servings | F12: SUP-04 | G12: 9.6 | H12: 626 | I12: 200 | J12: 600 | K12: 24 | L12: Active | N12: =IF($A12="","",IFERROR(INDEX(Suppliers!$B$2:$B$51,MATCH($F12,Suppliers!$A$2:$A$51,0))&"","(not found)")) -> Dunmore Powder Labs | O12: =IF($A12="","",SUMIFS(Inventory_Ledger!$E$2:$E$2001,Inventory_Ledger!$D$2:$D$2001,$A12,Inventory_Ledger!$C$2:$C$2001,"Receipt")) -> 0 | P12: =IF($A12="","",SUMIFS(Inventory_Ledger!$E$2:$E$2001,Inventory_Ledger!$D$2:$D$2001,$A12,Inventory_Ledger!$C$2:$C$2001,"Shipment")) -> 374 | Q12: =IF($A12="","",SUMIFS(Inventory_Ledger!$E$2:$E$2001,Inventory_Ledger!$D$2:$D$2001,$A12,Inventory_Ledger!$C$2:$C$2001,"Adjustment")) -> -24 | R12: =IF($A12="","",IF(ISNUMBER($H12),$H12,0)+$O12-$P12+$Q12) -> 228 | S12: =IF($A12="","",SUMIFS(Reservations!$L$2:$L$201,Reservations!$B$2:$B$201,$A12)) -> 0 | T12: =IF($A12="","",SUMIFS(Batches!$P$2:$P$301,Batches!$B$2:$B$301,$A12)) -> 0 | U12: =IF($A12="","",$R12-$S12-$T12) -> 228 | V12: =IF($A12="","",SUMIFS(Purchase_Orders!$N$2:$N$301,Purchase_Orders!$C$2:$C$301,$A12,Purchase_Orders!$O$2:$O$301,1)) -> 600 | W12: =IF($A12="","",SUMIFS(Batches!$L$2:$L$301,Batches!$B$2:$B$301,$A12)) -> 228 | X12: =IF($A12="","",SUMIFS(Batches!$F$2:$F$301,Batches!$B$2:$B$301,$A12)) -> 626 | Y12: =IF($A12="","",IF(ISNUMBER($I12),IF(IF(Config!$B$9="Recorded",$R12,$U12)<$I12,1,0),0)) -> 0 | Z12: =IF($A12="","",IF($R12<0,"Negative",IF($Y12=1,"Below reorder","OK"))) -> OK | AA12: =IF($A12="","",IF(ISNUMBER($G12),$R12*$G12,"")) -> 2188.8 | AB12: =IF(COUNTA($A12:$M12)=0,"",IF($A12="","Missing: SKU",IF(COUNTIF($A$2:$A$101,$A12)>1,"Duplicate SKU",IF($B12="","Missing: product name",IF($C12="","Missing: category",IF($F12="","Missing: primary supplier",IF(NOT(ISNUMBER($H12)),"Missing: opening balance",IF(NOT(ISNUMBER($I12)),"Missing: reorder point",IF(NOT(ISNUMBER($J12)),"Missing: reorder qty",IF($L12="","Missing: status",IF(COUNTIF(Suppliers!$A$2:$A$51,$F12)=0,"Unknown supplier",IF(COUNTIF(Config!$N$15:$N$34,$C12)=0,"Unsupported category",IF(COUNTIF(Config!$O$15:$O$34,$L12)=0,"Unsupported status",IF($X12<>$H12,"Opening balance differs from lot openings",IF($W12<>$R12,"Lot balances differ from recorded stock",IF($R12<0,"Negative recorded stock","OK")))))))))))))))) -> OK | AC12: =IF($Y12=1,COUNTIF($Y$2:$Y12,1),"")
A13: CAS-CHO-2LB | B13: Micellar Casein, Chocolate, 2 lb | C13: Casein | D13: Chocolate | E13: 2 lb | F13: SUP-05 | G13: 19.7 | H13: 423 | I13: 200 | J13: 360 | K13: 24 | L13: Active | N13: =IF($A13="","",IFERROR(INDEX(Suppliers!$B$2:$B$51,MATCH($F13,Suppliers!$A$2:$A$51,0))&"","(not found)")) -> Elmstead Co-Packing | O13: =IF($A13="","",SUMIFS(Inventory_Ledger!$E$2:$E$2001,Inventory_Ledger!$D$2:$D$2001,$A13,Inventory_Ledger!$C$2:$C$2001,"Receipt")) -> 0 | P13: =IF($A13="","",SUMIFS(Inventory_Ledger!$E$2:$E$2001,Inventory_Ledger!$D$2:$D$2001,$A13,Inventory_Ledger!$C$2:$C$2001,"Shipment")) -> 223 | Q13: =IF($A13="","",SUMIFS(Inventory_Ledger!$E$2:$E$2001,Inventory_Ledger!$D$2:$D$2001,$A13,Inventory_Ledger!$C$2:$C$2001,"Adjustment")) -> 0 | R13: =IF($A13="","",IF(ISNUMBER($H13),$H13,0)+$O13-$P13+$Q13) -> 200 | S13: =IF($A13="","",SUMIFS(Reservations!$L$2:$L$201,Reservations!$B$2:$B$201,$A13)) -> 0 | T13: =IF($A13="","",SUMIFS(Batches!$P$2:$P$301,Batches!$B$2:$B$301,$A13)) -> 0 | U13: =IF($A13="","",$R13-$S13-$T13) -> 200 | V13: =IF($A13="","",SUMIFS(Purchase_Orders!$N$2:$N$301,Purchase_Orders!$C$2:$C$301,$A13,Purchase_Orders!$O$2:$O$301,1)) -> 360 | W13: =IF($A13="","",SUMIFS(Batches!$L$2:$L$301,Batches!$B$2:$B$301,$A13)) -> 200 | X13: =IF($A13="","",SUMIFS(Batches!$F$2:$F$301,Batches!$B$2:$B$301,$A13)) -> 423 | Y13: =IF($A13="","",IF(ISNUMBER($I13),IF(IF(Config!$B$9="Recorded",$R13,$U13)<$I13,1,0),0)) -> 0 | Z13: =IF($A13="","",IF($R13<0,"Negative",IF($Y13=1,"Below reorder","OK"))) -> OK | AA13: =IF($A13="","",IF(ISNUMBER($G13),$R13*$G13,"")) -> 3940 | AB13: =IF(COUNTA($A13:$M13)=0,"",IF($A13="","Missing: SKU",IF(COUNTIF($A$2:$A$101,$A13)>1,"Duplicate SKU",IF($B13="","Missing: product name",IF($C13="","Missing: category",IF($F13="","Missing: primary supplier",IF(NOT(ISNUMBER($H13)),"Missing: opening balance",IF(NOT(ISNUMBER($I13)),"Missing: reorder point",IF(NOT(ISNUMBER($J13)),"Missing: reorder qty",IF($L13="","Missing: status",IF(COUNTIF(Suppliers!$A$2:$A$51,$F13)=0,"Unknown supplier",IF(COUNTIF(Config!$N$15:$N$34,$C13)=0,"Unsupported category",IF(COUNTIF(Config!$O$15:$O$34,$L13)=0,"Unsupported status",IF($X13<>$H13,"Opening balance differs from lot openings",IF($W13<>$R13,"Lot balances differ from recorded stock",IF($R13<0,"Negative recorded stock","OK")))))))))))))))) -> OK | AC13: =IF($Y13=1,COUNTIF($Y$2:$Y13,1),"")
N14: =IF($A14="","",IFERROR(INDEX(Suppliers!$B$2:$B$51,MATCH($F14,Suppliers!$A$2:$A$51,0))&"","(not found)")) | O14: =IF($A14="","",SUMIFS(Inventory_Ledger!$E$2:$E$2001,Inventory_Ledger!$D$2:$D$2001,$A14,Inventory_Ledger!$C$2:$C$2001,"Receipt")) | P14: =IF($A14="","",SUMIFS(Inventory_Ledger!$E$2:$E$2001,Inventory_Ledger!$D$2:$D$2001,$A14,Inventory_Ledger!$C$2:$C$2001,"Shipment")) | Q14: =IF($A14="","",SUMIFS(Inventory_Ledger!$E$2:$E$2001,Inventory_Ledger!$D$2:$D$2001,$A14,Inventory_Ledger!$C$2:$C$2001,"Adjustment")) | R14: =IF($A14="","",IF(ISNUMBER($H14),$H14,0)+$O14-$P14+$Q14) | S14: =IF($A14="","",SUMIFS(Reservations!$L$2:$L$201,Reservations!$B$2:$B$201,$A14)) | T14: =IF($A14="","",SUMIFS(Batches!$P$2:$P$301,Batches!$B$2:$B$301,$A14)) | U14: =IF($A14="","",$R14-$S14-$T14) | V14: =IF($A14="","",SUMIFS(Purchase_Orders!$N$2:$N$301,Purchase_Orders!$C$2:$C$301,$A14,Purchase_Orders!$O$2:$O$301,1)) | W14: =IF($A14="","",SUMIFS(Batches!$L$2:$L$301,Batches!$B$2:$B$301,$A14)) | X14: =IF($A14="","",SUMIFS(Batches!$F$2:$F$301,Batches!$B$2:$B$301,$A14)) | Y14: =IF($A14="","",IF(ISNUMBER($I14),IF(IF(Config!$B$9="Recorded",$R14,$U14)<$I14,1,0),0)) | Z14: =IF($A14="","",IF($R14<0,"Negative",IF($Y14=1,"Below reorder","OK"))) | AA14: =IF($A14="","",IF(ISNUMBER($G14),$R14*$G14,"")) | AB14: =IF(COUNTA($A14:$M14)=0,"",IF($A14="","Missing: SKU",IF(COUNTIF($A$2:$A$101,$A14)>1,"Duplicate SKU",IF($B14="","Missing: product name",IF($C14="","Missing: category",IF($F14="","Missing: primary supplier",IF(NOT(ISNUMBER($H14)),"Missing: opening balance",IF(NOT(ISNUMBER($I14)),"Missing: reorder point",IF(NOT(ISNUMBER($J14)),"Missing: reorder qty",IF($L14="","Missing: status",IF(COUNTIF(Suppliers!$A$2:$A$51,$F14)=0,"Unknown supplier",IF(COUNTIF(Config!$N$15:$N$34,$C14)=0,"Unsupported category",IF(COUNTIF(Config!$O$15:$O$34,$L14)=0,"Unsupported status",IF($X14<>$H14,"Opening balance differs from lot openings",IF($W14<>$R14,"Lot balances differ from recorded stock",IF($R14<0,"Negative recorded stock","OK")))))))))))))))) | AC14: =IF($Y14=1,COUNTIF($Y$2:$Y14,1),"")
N15: =IF($A15="","",IFERROR(INDEX(Suppliers!$B$2:$B$51,MATCH($F15,Suppliers!$A$2:$A$51,0))&"","(not found)")) | O15: =IF($A15="","",SUMIFS(Inventory_Ledger!$E$2:$E$2001,Inventory_Ledger!$D$2:$D$2001,$A15,Inventory_Ledger!$C$2:$C$2001,"Receipt")) | P15: =IF($A15="","",SUMIFS(Inventory_Ledger!$E$2:$E$2001,Inventory_Ledger!$D$2:$D$2001,$A15,Inventory_Ledger!$C$2:$C$2001,"Shipment")) | Q15: =IF($A15="","",SUMIFS(Inventory_Ledger!$E$2:$E$2001,Inventory_Ledger!$D$2:$D$2001,$A15,Inventory_Ledger!$C$2:$C$2001,"Adjustment")) | R15: =IF($A15="","",IF(ISNUMBER($H15),$H15,0)+$O15-$P15+$Q15) | S15: =IF($A15="","",SUMIFS(Reservations!$L$2:$L$201,Reservations!$B$2:$B$201,$A15)) | T15: =IF($A15="","",SUMIFS(Batches!$P$2:$P$301,Batches!$B$2:$B$301,$A15)) | U15: =IF($A15="","",$R15-$S15-$T15) | V15: =IF($A15="","",SUMIFS(Purchase_Orders!$N$2:$N$301,Purchase_Orders!$C$2:$C$301,$A15,Purchase_Orders!$O$2:$O$301,1)) | W15: =IF($A15="","",SUMIFS(Batches!$L$2:$L$301,Batches!$B$2:$B$301,$A15)) | X15: =IF($A15="","",SUMIFS(Batches!$F$2:$F$301,Batches!$B$2:$B$301,$A15)) | Y15: =IF($A15="","",IF(ISNUMBER($I15),IF(IF(Config!$B$9="Recorded",$R15,$U15)<$I15,1,0),0)) | Z15: =IF($A15="","",IF($R15<0,"Negative",IF($Y15=1,"Below reorder","OK"))) | AA15: =IF($A15="","",IF(ISNUMBER($G15),$R15*$G15,"")) | AB15: =IF(COUNTA($A15:$M15)=0,"",IF($A15="","Missing: SKU",IF(COUNTIF($A$2:$A$101,$A15)>1,"Duplicate SKU",IF($B15="","Missing: product name",IF($C15="","Missing: category",IF($F15="","Missing: primary supplier",IF(NOT(ISNUMBER($H15)),"Missing: opening balance",IF(NOT(ISNUMBER($I15)),"Missing: reorder point",IF(NOT(ISNUMBER($J15)),"Missing: reorder qty",IF($L15="","Missing: status",IF(COUNTIF(Suppliers!$A$2:$A$51,$F15)=0,"Unknown supplier",IF(COUNTIF(Config!$N$15:$N$34,$C15)=0,"Unsupported category",IF(COUNTIF(Config!$O$15:$O$34,$L15)=0,"Unsupported status",IF($X15<>$H15,"Opening balance differs from lot openings",IF($W15<>$R15,"Lot balances differ from recorded stock",IF($R15<0,"Negative recorded stock","OK")))))))))))))))) | AC15: =IF($Y15=1,COUNTIF($Y$2:$Y15,1),"")
N16: =IF($A16="","",IFERROR(INDEX(Suppliers!$B$2:$B$51,MATCH($F16,Suppliers!$A$2:$A$51,0))&"","(not found)")) | O16: =IF($A16="","",SUMIFS(Inventory_Ledger!$E$2:$E$2001,Inventory_Ledger!$D$2:$D$2001,$A16,Inventory_Ledger!$C$2:$C$2001,"Receipt")) | P16: =IF($A16="","",SUMIFS(Inventory_Ledger!$E$2:$E$2001,Inventory_Ledger!$D$2:$D$2001,$A16,Inventory_Ledger!$C$2:$C$2001,"Shipment")) | Q16: =IF($A16="","",SUMIFS(Inventory_Ledger!$E$2:$E$2001,Inventory_Ledger!$D$2:$D$2001,$A16,Inventory_Ledger!$C$2:$C$2001,"Adjustment")) | R16: =IF($A16="","",IF(ISNUMBER($H16),$H16,0)+$O16-$P16+$Q16) | S16: =IF($A16="","",SUMIFS(Reservations!$L$2:$L$201,Reservations!$B$2:$B$201,$A16)) | T16: =IF($A16="","",SUMIFS(Batches!$P$2:$P$301,Batches!$B$2:$B$301,$A16)) | U16: =IF($A16="","",$R16-$S16-$T16) | V16: =IF($A16="","",SUMIFS(Purchase_Orders!$N$2:$N$301,Purchase_Orders!$C$2:$C$301,$A16,Purchase_Orders!$O$2:$O$301,1)) | W16: =IF($A16="","",SUMIFS(Batches!$L$2:$L$301,Batches!$B$2:$B$301,$A16)) | X16: =IF($A16="","",SUMIFS(Batches!$F$2:$F$301,Batches!$B$2:$B$301,$A16)) | Y16: =IF($A16="","",IF(ISNUMBER($I16),IF(IF(Config!$B$9="Recorded",$R16,$U16)<$I16,1,0),0)) | Z16: =IF($A16="","",IF($R16<0,"Negative",IF($Y16=1,"Below reorder","OK"))) | AA16: =IF($A16="","",IF(ISNUMBER($G16),$R16*$G16,"")) | AB16: =IF(COUNTA($A16:$M16)=0,"",IF($A16="","Missing: SKU",IF(COUNTIF($A$2:$A$101,$A16)>1,"Duplicate SKU",IF($B16="","Missing: product name",IF($C16="","Missing: category",IF($F16="","Missing: primary supplier",IF(NOT(ISNUMBER($H16)),"Missing: opening balance",IF(NOT(ISNUMBER($I16)),"Missing: reorder point",IF(NOT(ISNUMBER($J16)),"Missing: reorder qty",IF($L16="","Missing: status",IF(COUNTIF(Suppliers!$A$2:$A$51,$F16)=0,"Unknown supplier",IF(COUNTIF(Config!$N$15:$N$34,$C16)=0,"Unsupported category",IF(COUNTIF(Config!$O$15:$O$34,$L16)=0,"Unsupported status",IF($X16<>$H16,"Opening balance differs from lot openings",IF($W16<>$R16,"Lot balances differ from recorded stock",IF($R16<0,"Negative recorded stock","OK")))))))))))))))) | AC16: =IF($Y16=1,COUNTIF($Y$2:$Y16,1),"")
N17: =IF($A17="","",IFERROR(INDEX(Suppliers!$B$2:$B$51,MATCH($F17,Suppliers!$A$2:$A$51,0))&"","(not found)")) | O17: =IF($A17="","",SUMIFS(Inventory_Ledger!$E$2:$E$2001,Inventory_Ledger!$D$2:$D$2001,$A17,Inventory_Ledger!$C$2:$C$2001,"Receipt")) | P17: =IF($A17="","",SUMIFS(Inventory_Ledger!$E$2:$E$2001,Inventory_Ledger!$D$2:$D$2001,$A17,Inventory_Ledger!$C$2:$C$2001,"Shipment")) | Q17: =IF($A17="","",SUMIFS(Inventory_Ledger!$E$2:$E$2001,Inventory_Ledger!$D$2:$D$2001,$A17,Inventory_Ledger!$C$2:$C$2001,"Adjustment")) | R17: =IF($A17="","",IF(ISNUMBER($H17),$H17,0)+$O17-$P17+$Q17) | S17: =IF($A17="","",SUMIFS(Reservations!$L$2:$L$201,Reservations!$B$2:$B$201,$A17)) | T17: =IF($A17="","",SUMIFS(Batches!$P$2:$P$301,Batches!$B$2:$B$301,$A17)) | U17: =IF($A17="","",$R17-$S17-$T17) | V17: =IF($A17="","",SUMIFS(Purchase_Orders!$N$2:$N$301,Purchase_Orders!$C$2:$C$301,$A17,Purchase_Orders!$O$2:$O$301,1)) | W17: =IF($A17="","",SUMIFS(Batches!$L$2:$L$301,Batches!$B$2:$B$301,$A17)) | X17: =IF($A17="","",SUMIFS(Batches!$F$2:$F$301,Batches!$B$2:$B$301,$A17)) | Y17: =IF($A17="","",IF(ISNUMBER($I17),IF(IF(Config!$B$9="Recorded",$R17,$U17)<$I17,1,0),0)) | Z17: =IF($A17="","",IF($R17<0,"Negative",IF($Y17=1,"Below reorder","OK"))) | AA17: =IF($A17="","",IF(ISNUMBER($G17),$R17*$G17,"")) | AB17: =IF(COUNTA($A17:$M17)=0,"",IF($A17="","Missing: SKU",IF(COUNTIF($A$2:$A$101,$A17)>1,"Duplicate SKU",IF($B17="","Missing: product name",IF($C17="","Missing: category",IF($F17="","Missing: primary supplier",IF(NOT(ISNUMBER($H17)),"Missing: opening balance",IF(NOT(ISNUMBER($I17)),"Missing: reorder point",IF(NOT(ISNUMBER($J17)),"Missing: reorder qty",IF($L17="","Missing: status",IF(COUNTIF(Suppliers!$A$2:$A$51,$F17)=0,"Unknown supplier",IF(COUNTIF(Config!$N$15:$N$34,$C17)=0,"Unsupported category",IF(COUNTIF(Config!$O$15:$O$34,$L17)=0,"Unsupported status",IF($X17<>$H17,"Opening balance differs from lot openings",IF($W17<>$R17,"Lot balances differ from recorded stock",IF($R17<0,"Negative recorded stock","OK")))))))))))))))) | AC17: =IF($Y17=1,COUNTIF($Y$2:$Y17,1),"")
N18: =IF($A18="","",IFERROR(INDEX(Suppliers!$B$2:$B$51,MATCH($F18,Suppliers!$A$2:$A$51,0))&"","(not found)")) | O18: =IF($A18="","",SUMIFS(Inventory_Ledger!$E$2:$E$2001,Inventory_Ledger!$D$2:$D$2001,$A18,Inventory_Ledger!$C$2:$C$2001,"Receipt")) | P18: =IF($A18="","",SUMIFS(Inventory_Ledger!$E$2:$E$2001,Inventory_Ledger!$D$2:$D$2001,$A18,Inventory_Ledger!$C$2:$C$2001,"Shipment")) | Q18: =IF($A18="","",SUMIFS(Inventory_Ledger!$E$2:$E$2001,Inventory_Ledger!$D$2:$D$2001,$A18,Inventory_Ledger!$C$2:$C$2001,"Adjustment")) | R18: =IF($A18="","",IF(ISNUMBER($H18),$H18,0)+$O18-$P18+$Q18) | S18: =IF($A18="","",SUMIFS(Reservations!$L$2:$L$201,Reservations!$B$2:$B$201,$A18)) | T18: =IF($A18="","",SUMIFS(Batches!$P$2:$P$301,Batches!$B$2:$B$301,$A18)) | U18: =IF($A18="","",$R18-$S18-$T18) | V18: =IF($A18="","",SUMIFS(Purchase_Orders!$N$2:$N$301,Purchase_Orders!$C$2:$C$301,$A18,Purchase_Orders!$O$2:$O$301,1)) | W18: =IF($A18="","",SUMIFS(Batches!$L$2:$L$301,Batches!$B$2:$B$301,$A18)) | X18: =IF($A18="","",SUMIFS(Batches!$F$2:$F$301,Batches!$B$2:$B$301,$A18)) | Y18: =IF($A18="","",IF(ISNUMBER($I18),IF(IF(Config!$B$9="Recorded",$R18,$U18)<$I18,1,0),0)) | Z18: =IF($A18="","",IF($R18<0,"Negative",IF($Y18=1,"Below reorder","OK"))) | AA18: =IF($A18="","",IF(ISNUMBER($G18),$R18*$G18,"")) | AB18: =IF(COUNTA($A18:$M18)=0,"",IF($A18="","Missing: SKU",IF(COUNTIF($A$2:$A$101,$A18)>1,"Duplicate SKU",IF($B18="","Missing: product name",IF($C18="","Missing: category",IF($F18="","Missing: primary supplier",IF(NOT(ISNUMBER($H18)),"Missing: opening balance",IF(NOT(ISNUMBER($I18)),"Missing: reorder point",IF(NOT(ISNUMBER($J18)),"Missing: reorder qty",IF($L18="","Missing: status",IF(COUNTIF(Suppliers!$A$2:$A$51,$F18)=0,"Unknown supplier",IF(COUNTIF(Config!$N$15:$N$34,$C18)=0,"Unsupported category",IF(COUNTIF(Config!$O$15:$O$34,$L18)=0,"Unsupported status",IF($X18<>$H18,"Opening balance differs from lot openings",IF($W18<>$R18,"Lot balances differ from recorded stock",IF($R18<0,"Negative recorded stock","OK")))))))))))))))) | AC18: =IF($Y18=1,COUNTIF($Y$2:$Y18,1),"")
N19: =IF($A19="","",IFERROR(INDEX(Suppliers!$B$2:$B$51,MATCH($F19,Suppliers!$A$2:$A$51,0))&"","(not found)")) | O19: =IF($A19="","",SUMIFS(Inventory_Ledger!$E$2:$E$2001,Inventory_Ledger!$D$2:$D$2001,$A19,Inventory_Ledger!$C$2:$C$2001,"Receipt")) | P19: =IF($A19="","",SUMIFS(Inventory_Ledger!$E$2:$E$2001,Inventory_Ledger!$D$2:$D$2001,$A19,Inventory_Ledger!$C$2:$C$2001,"Shipment")) | Q19: =IF($A19="","",SUMIFS(Inventory_Ledger!$E$2:$E$2001,Inventory_Ledger!$D$2:$D$2001,$A19,Inventory_Ledger!$C$2:$C$2001,"Adjustment")) | R19: =IF($A19="","",IF(ISNUMBER($H19),$H19,0)+$O19-$P19+$Q19) | S19: =IF($A19="","",SUMIFS(Reservations!$L$2:$L$201,Reservations!$B$2:$B$201,$A19)) | T19: =IF($A19="","",SUMIFS(Batches!$P$2:$P$301,Batches!$B$2:$B$301,$A19)) | U19: =IF($A19="","",$R19-$S19-$T19) | V19: =IF($A19="","",SUMIFS(Purchase_Orders!$N$2:$N$301,Purchase_Orders!$C$2:$C$301,$A19,Purchase_Orders!$O$2:$O$301,1)) | W19: =IF($A19="","",SUMIFS(Batches!$L$2:$L$301,Batches!$B$2:$B$301,$A19)) | X19: =IF($A19="","",SUMIFS(Batches!$F$2:$F$301,Batches!$B$2:$B$301,$A19)) | Y19: =IF($A19="","",IF(ISNUMBER($I19),IF(IF(Config!$B$9="Recorded",$R19,$U19)<$I19,1,0),0)) | Z19: =IF($A19="","",IF($R19<0,"Negative",IF($Y19=1,"Below reorder","OK"))) | AA19: =IF($A19="","",IF(ISNUMBER($G19),$R19*$G19,"")) | AB19: =IF(COUNTA($A19:$M19)=0,"",IF($A19="","Missing: SKU",IF(COUNTIF($A$2:$A$101,$A19)>1,"Duplicate SKU",IF($B19="","Missing: product name",IF($C19="","Missing: category",IF($F19="","Missing: primary supplier",IF(NOT(ISNUMBER($H19)),"Missing: opening balance",IF(NOT(ISNUMBER($I19)),"Missing: reorder point",IF(NOT(ISNUMBER($J19)),"Missing: reorder qty",IF($L19="","Missing: status",IF(COUNTIF(Suppliers!$A$2:$A$51,$F19)=0,"Unknown supplier",IF(COUNTIF(Config!$N$15:$N$34,$C19)=0,"Unsupported category",IF(COUNTIF(Config!$O$15:$O$34,$L19)=0,"Unsupported status",IF($X19<>$H19,"Opening balance differs from lot openings",IF($W19<>$R19,"Lot balances differ from recorded stock",IF($R19<0,"Negative recorded stock","OK")))))))))))))))) | AC19: =IF($Y19=1,COUNTIF($Y$2:$Y19,1),"")
N20: =IF($A20="","",IFERROR(INDEX(Suppliers!$B$2:$B$51,MATCH($F20,Suppliers!$A$2:$A$51,0))&"","(not found)")) | O20: =IF($A20="","",SUMIFS(Inventory_Ledger!$E$2:$E$2001,Inventory_Ledger!$D$2:$D$2001,$A20,Inventory_Ledger!$C$2:$C$2001,"Receipt")) | P20: =IF($A20="","",SUMIFS(Inventory_Ledger!$E$2:$E$2001,Inventory_Ledger!$D$2:$D$2001,$A20,Inventory_Ledger!$C$2:$C$2001,"Shipment")) | Q20: =IF($A20="","",SUMIFS(Inventory_Ledger!$E$2:$E$2001,Inventory_Ledger!$D$2:$D$2001,$A20,Inventory_Ledger!$C$2:$C$2001,"Adjustment")) | R20: =IF($A20="","",IF(ISNUMBER($H20),$H20,0)+$O20-$P20+$Q20) | S20: =IF($A20="","",SUMIFS(Reservations!$L$2:$L$201,Reservations!$B$2:$B$201,$A20)) | T20: =IF($A20="","",SUMIFS(Batches!$P$2:$P$301,Batches!$B$2:$B$301,$A20)) | U20: =IF($A20="","",$R20-$S20-$T20) | V20: =IF($A20="","",SUMIFS(Purchase_Orders!$N$2:$N$301,Purchase_Orders!$C$2:$C$301,$A20,Purchase_Orders!$O$2:$O$301,1)) | W20: =IF($A20="","",SUMIFS(Batches!$L$2:$L$301,Batches!$B$2:$B$301,$A20)) | X20: =IF($A20="","",SUMIFS(Batches!$F$2:$F$301,Batches!$B$2:$B$301,$A20)) | Y20: =IF($A20="","",IF(ISNUMBER($I20),IF(IF(Config!$B$9="Recorded",$R20,$U20)<$I20,1,0),0)) | Z20: =IF($A20="","",IF($R20<0,"Negative",IF($Y20=1,"Below reorder","OK"))) | AA20: =IF($A20="","",IF(ISNUMBER($G20),$R20*$G20,"")) | AB20: =IF(COUNTA($A20:$M20)=0,"",IF($A20="","Missing: SKU",IF(COUNTIF($A$2:$A$101,$A20)>1,"Duplicate SKU",IF($B20="","Missing: product name",IF($C20="","Missing: category",IF($F20="","Missing: primary supplier",IF(NOT(ISNUMBER($H20)),"Missing: opening balance",IF(NOT(ISNUMBER($I20)),"Missing: reorder point",IF(NOT(ISNUMBER($J20)),"Missing: reorder qty",IF($L20="","Missing: status",IF(COUNTIF(Suppliers!$A$2:$A$51,$F20)=0,"Unknown supplier",IF(COUNTIF(Config!$N$15:$N$34,$C20)=0,"Unsupported category",IF(COUNTIF(Config!$O$15:$O$34,$L20)=0,"Unsupported status",IF($X20<>$H20,"Opening balance differs from lot openings",IF($W20<>$R20,"Lot balances differ from recorded stock",IF($R20<0,"Negative recorded stock","OK")))))))))))))))) | AC20: =IF($Y20=1,COUNTIF($Y$2:$Y20,1),"")
N21: =IF($A21="","",IFERROR(INDEX(Suppliers!$B$2:$B$51,MATCH($F21,Suppliers!$A$2:$A$51,0))&"","(not found)")) | O21: =IF($A21="","",SUMIFS(Inventory_Ledger!$E$2:$E$2001,Inventory_Ledger!$D$2:$D$2001,$A21,Inventory_Ledger!$C$2:$C$2001,"Receipt")) | P21: =IF($A21="","",SUMIFS(Inventory_Ledger!$E$2:$E$2001,Inventory_Ledger!$D$2:$D$2001,$A21,Inventory_Ledger!$C$2:$C$2001,"Shipment")) | Q21: =IF($A21="","",SUMIFS(Inventory_Ledger!$E$2:$E$2001,Inventory_Ledger!$D$2:$D$2001,$A21,Inventory_Ledger!$C$2:$C$2001,"Adjustment")) | R21: =IF($A21="","",IF(ISNUMBER($H21),$H21,0)+$O21-$P21+$Q21) | S21: =IF($A21="","",SUMIFS(Reservations!$L$2:$L$201,Reservations!$B$2:$B$201,$A21)) | T21: =IF($A21="","",SUMIFS(Batches!$P$2:$P$301,Batches!$B$2:$B$301,$A21)) | U21: =IF($A21="","",$R21-$S21-$T21) | V21: =IF($A21="","",SUMIFS(Purchase_Orders!$N$2:$N$301,Purchase_Orders!$C$2:$C$301,$A21,Purchase_Orders!$O$2:$O$301,1)) | W21: =IF($A21="","",SUMIFS(Batches!$L$2:$L$301,Batches!$B$2:$B$301,$A21)) | X21: =IF($A21="","",SUMIFS(Batches!$F$2:$F$301,Batches!$B$2:$B$301,$A21)) | Y21: =IF($A21="","",IF(ISNUMBER($I21),IF(IF(Config!$B$9="Recorded",$R21,$U21)<$I21,1,0),0)) | Z21: =IF($A21="","",IF($R21<0,"Negative",IF($Y21=1,"Below reorder","OK"))) | AA21: =IF($A21="","",IF(ISNUMBER($G21),$R21*$G21,"")) | AB21: =IF(COUNTA($A21:$M21)=0,"",IF($A21="","Missing: SKU",IF(COUNTIF($A$2:$A$101,$A21)>1,"Duplicate SKU",IF($B21="","Missing: product name",IF($C21="","Missing: category",IF($F21="","Missing: primary supplier",IF(NOT(ISNUMBER($H21)),"Missing: opening balance",IF(NOT(ISNUMBER($I21)),"Missing: reorder point",IF(NOT(ISNUMBER($J21)),"Missing: reorder qty",IF($L21="","Missing: status",IF(COUNTIF(Suppliers!$A$2:$A$51,$F21)=0,"Unknown supplier",IF(COUNTIF(Config!$N$15:$N$34,$C21)=0,"Unsupported category",IF(COUNTIF(Config!$O$15:$O$34,$L21)=0,"Unsupported status",IF($X21<>$H21,"Opening balance differs from lot openings",IF($W21<>$R21,"Lot balances differ from recorded stock",IF($R21<0,"Negative recorded stock","OK")))))))))))))))) | AC21: =IF($Y21=1,COUNTIF($Y$2:$Y21,1),"")
N22: =IF($A22="","",IFERROR(INDEX(Suppliers!$B$2:$B$51,MATCH($F22,Suppliers!$A$2:$A$51,0))&"","(not found)")) | O22: =IF($A22="","",SUMIFS(Inventory_Ledger!$E$2:$E$2001,Inventory_Ledger!$D$2:$D$2001,$A22,Inventory_Ledger!$C$2:$C$2001,"Receipt")) | P22: =IF($A22="","",SUMIFS(Inventory_Ledger!$E$2:$E$2001,Inventory_Ledger!$D$2:$D$2001,$A22,Inventory_Ledger!$C$2:$C$2001,"Shipment")) | Q22: =IF($A22="","",SUMIFS(Inventory_Ledger!$E$2:$E$2001,Inventory_Ledger!$D$2:$D$2001,$A22,Inventory_Ledger!$C$2:$C$2001,"Adjustment")) | R22: =IF($A22="","",IF(ISNUMBER($H22),$H22,0)+$O22-$P22+$Q22) | S22: =IF($A22="","",SUMIFS(Reservations!$L$2:$L$201,Reservations!$B$2:$B$201,$A22)) | T22: =IF($A22="","",SUMIFS(Batches!$P$2:$P$301,Batches!$B$2:$B$301,$A22)) | U22: =IF($A22="","",$R22-$S22-$T22) | V22: =IF($A22="","",SUMIFS(Purchase_Orders!$N$2:$N$301,Purchase_Orders!$C$2:$C$301,$A22,Purchase_Orders!$O$2:$O$301,1)) | W22: =IF($A22="","",SUMIFS(Batches!$L$2:$L$301,Batches!$B$2:$B$301,$A22)) | X22: =IF($A22="","",SUMIFS(Batches!$F$2:$F$301,Batches!$B$2:$B$301,$A22)) | Y22: =IF($A22="","",IF(ISNUMBER($I22),IF(IF(Config!$B$9="Recorded",$R22,$U22)<$I22,1,0),0)) | Z22: =IF($A22="","",IF($R22<0,"Negative",IF($Y22=1,"Below reorder","OK"))) | AA22: =IF($A22="","",IF(ISNUMBER($G22),$R22*$G22,"")) | AB22: =IF(COUNTA($A22:$M22)=0,"",IF($A22="","Missing: SKU",IF(COUNTIF($A$2:$A$101,$A22)>1,"Duplicate SKU",IF($B22="","Missing: product name",IF($C22="","Missing: category",IF($F22="","Missing: primary supplier",IF(NOT(ISNUMBER($H22)),"Missing: opening balance",IF(NOT(ISNUMBER($I22)),"Missing: reorder point",IF(NOT(ISNUMBER($J22)),"Missing: reorder qty",IF($L22="","Missing: status",IF(COUNTIF(Suppliers!$A$2:$A$51,$F22)=0,"Unknown supplier",IF(COUNTIF(Config!$N$15:$N$34,$C22)=0,"Unsupported category",IF(COUNTIF(Config!$O$15:$O$34,$L22)=0,"Unsupported status",IF($X22<>$H22,"Opening balance differs from lot openings",IF($W22<>$R22,"Lot balances differ from recorded stock",IF($R22<0,"Negative recorded stock","OK")))))))))))))))) | AC22: =IF($Y22=1,COUNTIF($Y$2:$Y22,1),"")
N23: =IF($A23="","",IFERROR(INDEX(Suppliers!$B$2:$B$51,MATCH($F23,Suppliers!$A$2:$A$51,0))&"","(not found)")) | O23: =IF($A23="","",SUMIFS(Inventory_Ledger!$E$2:$E$2001,Inventory_Ledger!$D$2:$D$2001,$A23,Inventory_Ledger!$C$2:$C$2001,"Receipt")) | P23: =IF($A23="","",SUMIFS(Inventory_Ledger!$E$2:$E$2001,Inventory_Ledger!$D$2:$D$2001,$A23,Inventory_Ledger!$C$2:$C$2001,"Shipment")) | Q23: =IF($A23="","",SUMIFS(Inventory_Ledger!$E$2:$E$2001,Inventory_Ledger!$D$2:$D$2001,$A23,Inventory_Ledger!$C$2:$C$2001,"Adjustment")) | R23: =IF($A23="","",IF(ISNUMBER($H23),$H23,0)+$O23-$P23+$Q23) | S23: =IF($A23="","",SUMIFS(Reservations!$L$2:$L$201,Reservations!$B$2:$B$201,$A23)) | T23: =IF($A23="","",SUMIFS(Batches!$P$2:$P$301,Batches!$B$2:$B$301,$A23)) | U23: =IF($A23="","",$R23-$S23-$T23) | V23: =IF($A23="","",SUMIFS(Purchase_Orders!$N$2:$N$301,Purchase_Orders!$C$2:$C$301,$A23,Purchase_Orders!$O$2:$O$301,1)) | W23: =IF($A23="","",SUMIFS(Batches!$L$2:$L$301,Batches!$B$2:$B$301,$A23)) | X23: =IF($A23="","",SUMIFS(Batches!$F$2:$F$301,Batches!$B$2:$B$301,$A23)) | Y23: =IF($A23="","",IF(ISNUMBER($I23),IF(IF(Config!$B$9="Recorded",$R23,$U23)<$I23,1,0),0)) | Z23: =IF($A23="","",IF($R23<0,"Negative",IF($Y23=1,"Below reorder","OK"))) | AA23: =IF($A23="","",IF(ISNUMBER($G23),$R23*$G23,"")) | AB23: =IF(COUNTA($A23:$M23)=0,"",IF($A23="","Missing: SKU",IF(COUNTIF($A$2:$A$101,$A23)>1,"Duplicate SKU",IF($B23="","Missing: product name",IF($C23="","Missing: category",IF($F23="","Missing: primary supplier",IF(NOT(ISNUMBER($H23)),"Missing: opening balance",IF(NOT(ISNUMBER($I23)),"Missing: reorder point",IF(NOT(ISNUMBER($J23)),"Missing: reorder qty",IF($L23="","Missing: status",IF(COUNTIF(Suppliers!$A$2:$A$51,$F23)=0,"Unknown supplier",IF(COUNTIF(Config!$N$15:$N$34,$C23)=0,"Unsupported category",IF(COUNTIF(Config!$O$15:$O$34,$L23)=0,"Unsupported status",IF($X23<>$H23,"Opening balance differs from lot openings",IF($W23<>$R23,"Lot balances differ from recorded stock",IF($R23<0,"Negative recorded stock","OK")))))))))))))))) | AC23: =IF($Y23=1,COUNTIF($Y$2:$Y23,1),"")
N24: =IF($A24="","",IFERROR(INDEX(Suppliers!$B$2:$B$51,MATCH($F24,Suppliers!$A$2:$A$51,0))&"","(not found)")) | O24: =IF($A24="","",SUMIFS(Inventory_Ledger!$E$2:$E$2001,Inventory_Ledger!$D$2:$D$2001,$A24,Inventory_Ledger!$C$2:$C$2001,"Receipt")) | P24: =IF($A24="","",SUMIFS(Inventory_Ledger!$E$2:$E$2001,Inventory_Ledger!$D$2:$D$2001,$A24,Inventory_Ledger!$C$2:$C$2001,"Shipment")) | Q24: =IF($A24="","",SUMIFS(Inventory_Ledger!$E$2:$E$2001,Inventory_Ledger!$D$2:$D$2001,$A24,Inventory_Ledger!$C$2:$C$2001,"Adjustment")) | R24: =IF($A24="","",IF(ISNUMBER($H24),$H24,0)+$O24-$P24+$Q24) | S24: =IF($A24="","",SUMIFS(Reservations!$L$2:$L$201,Reservations!$B$2:$B$201,$A24)) | T24: =IF($A24="","",SUMIFS(Batches!$P$2:$P$301,Batches!$B$2:$B$301,$A24)) | U24: =IF($A24="","",$R24-$S24-$T24) | V24: =IF($A24="","",SUMIFS(Purchase_Orders!$N$2:$N$301,Purchase_Orders!$C$2:$C$301,$A24,Purchase_Orders!$O$2:$O$301,1)) | W24: =IF($A24="","",SUMIFS(Batches!$L$2:$L$301,Batches!$B$2:$B$301,$A24)) | X24: =IF($A24="","",SUMIFS(Batches!$F$2:$F$301,Batches!$B$2:$B$301,$A24)) | Y24: =IF($A24="","",IF(ISNUMBER($I24),IF(IF(Config!$B$9="Recorded",$R24,$U24)<$I24,1,0),0)) | Z24: =IF($A24="","",IF($R24<0,"Negative",IF($Y24=1,"Below reorder","OK"))) | AA24: =IF($A24="","",IF(ISNUMBER($G24),$R24*$G24,"")) | AB24: =IF(COUNTA($A24:$M24)=0,"",IF($A24="","Missing: SKU",IF(COUNTIF($A$2:$A$101,$A24)>1,"Duplicate SKU",IF($B24="","Missing: product name",IF($C24="","Missing: category",IF($F24="","Missing: primary supplier",IF(NOT(ISNUMBER($H24)),"Missing: opening balance",IF(NOT(ISNUMBER($I24)),"Missing: reorder point",IF(NOT(ISNUMBER($J24)),"Missing: reorder qty",IF($L24="","Missing: status",IF(COUNTIF(Suppliers!$A$2:$A$51,$F24)=0,"Unknown supplier",IF(COUNTIF(Config!$N$15:$N$34,$C24)=0,"Unsupported category",IF(COUNTIF(Config!$O$15:$O$34,$L24)=0,"Unsupported status",IF($X24<>$H24,"Opening balance differs from lot openings",IF($W24<>$R24,"Lot balances differ from recorded stock",IF($R24<0,"Negative recorded stock","OK")))))))))))))))) | AC24: =IF($Y24=1,COUNTIF($Y$2:$Y24,1),"")
N25: =IF($A25="","",IFERROR(INDEX(Suppliers!$B$2:$B$51,MATCH($F25,Suppliers!$A$2:$A$51,0))&"","(not found)")) | O25: =IF($A25="","",SUMIFS(Inventory_Ledger!$E$2:$E$2001,Inventory_Ledger!$D$2:$D$2001,$A25,Inventory_Ledger!$C$2:$C$2001,"Receipt")) | P25: =IF($A25="","",SUMIFS(Inventory_Ledger!$E$2:$E$2001,Inventory_Ledger!$D$2:$D$2001,$A25,Inventory_Ledger!$C$2:$C$2001,"Shipment")) | Q25: =IF($A25="","",SUMIFS(Inventory_Ledger!$E$2:$E$2001,Inventory_Ledger!$D$2:$D$2001,$A25,Inventory_Ledger!$C$2:$C$2001,"Adjustment")) | R25: =IF($A25="","",IF(ISNUMBER($H25),$H25,0)+$O25-$P25+$Q25) | S25: =IF($A25="","",SUMIFS(Reservations!$L$2:$L$201,Reservations!$B$2:$B$201,$A25)) | T25: =IF($A25="","",SUMIFS(Batches!$P$2:$P$301,Batches!$B$2:$B$301,$A25)) | U25: =IF($A25="","",$R25-$S25-$T25) | V25: =IF($A25="","",SUMIFS(Purchase_Orders!$N$2:$N$301,Purchase_Orders!$C$2:$C$301,$A25,Purchase_Orders!$O$2:$O$301,1)) | W25: =IF($A25="","",SUMIFS(Batches!$L$2:$L$301,Batches!$B$2:$B$301,$A25)) | X25: =IF($A25="","",SUMIFS(Batches!$F$2:$F$301,Batches!$B$2:$B$301,$A25)) | Y25: =IF($A25="","",IF(ISNUMBER($I25),IF(IF(Config!$B$9="Recorded",$R25,$U25)<$I25,1,0),0)) | Z25: =IF($A25="","",IF($R25<0,"Negative",IF($Y25=1,"Below reorder","OK"))) | AA25: =IF($A25="","",IF(ISNUMBER($G25),$R25*$G25,"")) | AB25: =IF(COUNTA($A25:$M25)=0,"",IF($A25="","Missing: SKU",IF(COUNTIF($A$2:$A$101,$A25)>1,"Duplicate SKU",IF($B25="","Missing: product name",IF($C25="","Missing: category",IF($F25="","Missing: primary supplier",IF(NOT(ISNUMBER($H25)),"Missing: opening balance",IF(NOT(ISNUMBER($I25)),"Missing: reorder point",IF(NOT(ISNUMBER($J25)),"Missing: reorder qty",IF($L25="","Missing: status",IF(COUNTIF(Suppliers!$A$2:$A$51,$F25)=0,"Unknown supplier",IF(COUNTIF(Config!$N$15:$N$34,$C25)=0,"Unsupported category",IF(COUNTIF(Config!$O$15:$O$34,$L25)=0,"Unsupported status",IF($X25<>$H25,"Opening balance differs from lot openings",IF($W25<>$R25,"Lot balances differ from recorded stock",IF($R25<0,"Negative recorded stock","OK")))))))))))))))) | AC25: =IF($Y25=1,COUNTIF($Y$2:$Y25,1),"")
... N101: =IF($A101="","",IFERROR(INDEX(Suppliers!$B$2:$B$51,MATCH($F101,Suppliers!$A$2:$A$51,0))&"","(not found)")) | O101: =IF($A101="","",SUMIFS(Inventory_Ledger!$E$2:$E$2001,Inventory_Ledger!$D$2:$D$2001,$A101,Inventory_Ledger!$C$2:$C$2001,"Receipt")) | P101: =IF($A101="","",SUMIFS(Inventory_Ledger!$E$2:$E$2001,Inventory_Ledger!$D$2:$D$2001,$A101,Inventory_Ledger!$C$2:$C$2001,"Shipment")) | Q101: =IF($A101="","",SUMIFS(Inventory_Ledger!$E$2:$E$2001,Inventory_Ledger!$D$2:$D$2001,$A101,Inventory_Ledger!$C$2:$C$2001,"Adjustment")) | R101: =IF($A101="","",IF(ISNUMBER($H101),$H101,0)+$O101-$P101+$Q101) | S101: =IF($A101="","",SUMIFS(Reservations!$L$2:$L$201,Reservations!$B$2:$B$201,$A101)) | T101: =IF($A101="","",SUMIFS(Batches!$P$2:$P$301,Batches!$B$2:$B$301,$A101)) | U101: =IF($A101="","",$R101-$S101-$T101) | V101: =IF($A101="","",SUMIFS(Purchase_Orders!$N$2:$N$301,Purchase_Orders!$C$2:$C$301,$A101,Purchase_Orders!$O$2:$O$301,1)) | W101: =IF($A101="","",SUMIFS(Batches!$L$2:$L$301,Batches!$B$2:$B$301,$A101)) | X101: =IF($A101="","",SUMIFS(Batches!$F$2:$F$301,Batches!$B$2:$B$301,$A101)) | Y101: =IF($A101="","",IF(ISNUMBER($I101),IF(IF(Config!$B$9="Recorded",$R101,$U101)<$I101,1,0),0)) | Z101: =IF($A101="","",IF($R101<0,"Negative",IF($Y101=1,"Below reorder","OK"))) | AA101: =IF($A101="","",IF(ISNUMBER($G101),$R101*$G101,"")) | AB101: =IF(COUNTA($A101:$M101)=0,"",IF($A101="","Missing: SKU",IF(COUNTIF($A$2:$A$101,$A101)>1,"Duplicate SKU",IF($B101="","Missing: product name",IF($C101="","Missing: category",IF($F101="","Missing: primary supplier",IF(NOT(ISNUMBER($H101)),"Missing: opening balance",IF(NOT(ISNUMBER($I101)),"Missing: reorder point",IF(NOT(ISNUMBER($J101)),"Missing: reorder qty",IF($L101="","Missing: status",IF(COUNTIF(Suppliers!$A$2:$A$51,$F101)=0,"Unknown supplier",IF(COUNTIF(Config!$N$15:$N$34,$C101)=0,"Unsupported category",IF(COUNTIF(Config!$O$15:$O$34,$L101)=0,"Unsupported status",IF($X101<>$H101,"Opening balance differs from lot openings",IF($W101<>$R101,"Lot balances differ from recorded stock",IF($R101<0,"Negative recorded stock","OK")))))))))))))))) | AC101: =IF($Y101=1,COUNTIF($Y$2:$Y101,1),"")

Sheet Suppliers
A1: Supplier ID * | B1: Name * | C1: Type * | D1: Supplies | E1: Contact | F1: Email | G1: Phone | H1: Lead time (days) | I1: Payment terms | J1: Location | K1: Status * | L1: Agreement link | M1: Notes | N1: Products (primary) | O1: Open POs | P1: Record check
A2: SUP-01 | B2: Alder Creek Dairy Proteins | C2: Manufacturer | D2: Whey protein isolate (2 lb) | E2: Dana Whitlock | F2: dana.whitlock@example.com | G2: 555-0101 | H2: 35 | I2: Net 30 | J2: Wisconsin, US | K2: Active | L2: https://example.com/suppliers/SUP-01/agreement | M2: Minimum run 1,200 tubs | N2: =IF($A2="","",COUNTIF(Products!$F$2:$F$101,$A2)) -> 2 | O2: =IF($A2="","",SUMIFS(Purchase_Orders!$O$2:$O$301,Purchase_Orders!$B$2:$B$301,$A2)) -> 2 | P2: =IF(COUNTA($A2:$M2)=0,"",IF($A2="","Missing: supplier ID",IF(COUNTIF($A$2:$A$51,$A2)>1,"Duplicate supplier ID",IF($B2="","Missing: name",IF($C2="","Missing: type",IF($K2="","Missing: status",IF(COUNTIF(Config!$L$15:$L$34,$C2)=0,"Unsupported type",IF(COUNTIF(Config!$M$15:$M$34,$K2)=0,"Unsupported status","OK")))))))) -> OK
A3: SUP-02 | B3: Bramwell Bar Works | C3: Co-packer | D3: Protein bars (12-pack) | E3: Marcus Hale | F3: marcus.hale@example.com | G3: 555-0102 | H3: 30 | I3: Net 30 | J3: Minnesota, US | K3: Active | L3: https://example.com/suppliers/SUP-02/agreement | M3: Bars ship in master cases of 12 boxes | N3: =IF($A3="","",COUNTIF(Products!$F$2:$F$101,$A3)) -> 2 | O3: =IF($A3="","",SUMIFS(Purchase_Orders!$O$2:$O$301,Purchase_Orders!$B$2:$B$301,$A3)) -> 0 | P3: =IF(COUNTA($A3:$M3)=0,"",IF($A3="","Missing: supplier ID",IF(COUNTIF($A$2:$A$51,$A3)>1,"Duplicate supplier ID",IF($B3="","Missing: name",IF($C3="","Missing: type",IF($K3="","Missing: status",IF(COUNTIF(Config!$L$15:$L$34,$C3)=0,"Unsupported type",IF(COUNTIF(Config!$M$15:$M$34,$K3)=0,"Unsupported status","OK")))))))) -> OK
A4: SUP-03 | B4: Corliss Plant Proteins | C4: Manufacturer | D4: Plant protein blends | E4: Elena Vidal | F4: elena.vidal@example.com | G4: 555-0103 | H4: 40 | I4: Net 45 | J4: Iowa, US | K4: Active | L4: https://example.com/suppliers/SUP-03/agreement | M4: Pea and rice protein blend | N4: =IF($A4="","",COUNTIF(Products!$F$2:$F$101,$A4)) -> 2 | O4: =IF($A4="","",SUMIFS(Purchase_Orders!$O$2:$O$301,Purchase_Orders!$B$2:$B$301,$A4)) -> 1 | P4: =IF(COUNTA($A4:$M4)=0,"",IF($A4="","Missing: supplier ID",IF(COUNTIF($A$2:$A$51,$A4)>1,"Duplicate supplier ID",IF($B4="","Missing: name",IF($C4="","Missing: type",IF($K4="","Missing: status",IF(COUNTIF(Config!$L$15:$L$34,$C4)=0,"Unsupported type",IF(COUNTIF(Config!$M$15:$M$34,$K4)=0,"Unsupported status","OK")))))))) -> OK
A5: SUP-04 | B5: Dunmore Powder Labs | C5: Co-packer | D5: Creatine and pre-workout blending and filling | E5: Raj Patel | F5: raj.patel@example.com | G5: 555-0104 | H5: 30 | I5: Net 30 | J5: New Jersey, US | K5: Active | L5: https://example.com/suppliers/SUP-04/agreement | N5: =IF($A5="","",COUNTIF(Products!$F$2:$F$101,$A5)) -> 4 | O5: =IF($A5="","",SUMIFS(Purchase_Orders!$O$2:$O$301,Purchase_Orders!$B$2:$B$301,$A5)) -> 1 | P5: =IF(COUNTA($A5:$M5)=0,"",IF($A5="","Missing: supplier ID",IF(COUNTIF($A$2:$A$51,$A5)>1,"Duplicate supplier ID",IF($B5="","Missing: name",IF($C5="","Missing: type",IF($K5="","Missing: status",IF(COUNTIF(Config!$L$15:$L$34,$C5)=0,"Unsupported type",IF(COUNTIF(Config!$M$15:$M$34,$K5)=0,"Unsupported status","OK")))))))) -> OK
A6: SUP-05 | B6: Elmstead Co-Packing | C6: Co-packer | D6: Whey 5 lb and micellar casein | E6: Grace Lindqvist | F6: grace.lindqvist@example.com | G6: 555-0105 | H6: 45 | I6: Net 30 | J6: Utah, US | K6: Active | L6: https://example.com/suppliers/SUP-05/agreement | M6: Second source for powders | N6: =IF($A6="","",COUNTIF(Products!$F$2:$F$101,$A6)) -> 2 | O6: =IF($A6="","",SUMIFS(Purchase_Orders!$O$2:$O$301,Purchase_Orders!$B$2:$B$301,$A6)) -> 1 | P6: =IF(COUNTA($A6:$M6)=0,"",IF($A6="","Missing: supplier ID",IF(COUNTIF($A$2:$A$51,$A6)>1,"Duplicate supplier ID",IF($B6="","Missing: name",IF($C6="","Missing: type",IF($K6="","Missing: status",IF(COUNTIF(Config!$L$15:$L$34,$C6)=0,"Unsupported type",IF(COUNTIF(Config!$M$15:$M$34,$K6)=0,"Unsupported status","OK")))))))) -> OK
N7: =IF($A7="","",COUNTIF(Products!$F$2:$F$101,$A7)) | O7: =IF($A7="","",SUMIFS(Purchase_Orders!$O$2:$O$301,Purchase_Orders!$B$2:$B$301,$A7)) | P7: =IF(COUNTA($A7:$M7)=0,"",IF($A7="","Missing: supplier ID",IF(COUNTIF($A$2:$A$51,$A7)>1,"Duplicate supplier ID",IF($B7="","Missing: name",IF($C7="","Missing: type",IF($K7="","Missing: status",IF(COUNTIF(Config!$L$15:$L$34,$C7)=0,"Unsupported type",IF(COUNTIF(Config!$M$15:$M$34,$K7)=0,"Unsupported status","OK"))))))))
N8: =IF($A8="","",COUNTIF(Products!$F$2:$F$101,$A8)) | O8: =IF($A8="","",SUMIFS(Purchase_Orders!$O$2:$O$301,Purchase_Orders!$B$2:$B$301,$A8)) | P8: =IF(COUNTA($A8:$M8)=0,"",IF($A8="","Missing: supplier ID",IF(COUNTIF($A$2:$A$51,$A8)>1,"Duplicate supplier ID",IF($B8="","Missing: name",IF($C8="","Missing: type",IF($K8="","Missing: status",IF(COUNTIF(Config!$L$15:$L$34,$C8)=0,"Unsupported type",IF(COUNTIF(Config!$M$15:$M$34,$K8)=0,"Unsupported status","OK"))))))))
N9: =IF($A9="","",COUNTIF(Products!$F$2:$F$101,$A9)) | O9: =IF($A9="","",SUMIFS(Purchase_Orders!$O$2:$O$301,Purchase_Orders!$B$2:$B$301,$A9)) | P9: =IF(COUNTA($A9:$M9)=0,"",IF($A9="","Missing: supplier ID",IF(COUNTIF($A$2:$A$51,$A9)>1,"Duplicate supplier ID",IF($B9="","Missing: name",IF($C9="","Missing: type",IF($K9="","Missing: status",IF(COUNTIF(Config!$L$15:$L$34,$C9)=0,"Unsupported type",IF(COUNTIF(Config!$M$15:$M$34,$K9)=0,"Unsupported status","OK"))))))))
N10: =IF($A10="","",COUNTIF(Products!$F$2:$F$101,$A10)) | O10: =IF($A10="","",SUMIFS(Purchase_Orders!$O$2:$O$301,Purchase_Orders!$B$2:$B$301,$A10)) | P10: =IF(COUNTA($A10:$M10)=0,"",IF($A10="","Missing: supplier ID",IF(COUNTIF($A$2:$A$51,$A10)>1,"Duplicate supplier ID",IF($B10="","Missing: name",IF($C10="","Missing: type",IF($K10="","Missing: status",IF(COUNTIF(Config!$L$15:$L$34,$C10)=0,"Unsupported type",IF(COUNTIF(Config!$M$15:$M$34,$K10)=0,"Unsupported status","OK"))))))))
N11: =IF($A11="","",COUNTIF(Products!$F$2:$F$101,$A11)) | O11: =IF($A11="","",SUMIFS(Purchase_Orders!$O$2:$O$301,Purchase_Orders!$B$2:$B$301,$A11)) | P11: =IF(COUNTA($A11:$M11)=0,"",IF($A11="","Missing: supplier ID",IF(COUNTIF($A$2:$A$51,$A11)>1,"Duplicate supplier ID",IF($B11="","Missing: name",IF($C11="","Missing: type",IF($K11="","Missing: status",IF(COUNTIF(Config!$L$15:$L$34,$C11)=0,"Unsupported type",IF(COUNTIF(Config!$M$15:$M$34,$K11)=0,"Unsupported status","OK"))))))))
N12: =IF($A12="","",COUNTIF(Products!$F$2:$F$101,$A12)) | O12: =IF($A12="","",SUMIFS(Purchase_Orders!$O$2:$O$301,Purchase_Orders!$B$2:$B$301,$A12)) | P12: =IF(COUNTA($A12:$M12)=0,"",IF($A12="","Missing: supplier ID",IF(COUNTIF($A$2:$A$51,$A12)>1,"Duplicate supplier ID",IF($B12="","Missing: name",IF($C12="","Missing: type",IF($K12="","Missing: status",IF(COUNTIF(Config!$L$15:$L$34,$C12)=0,"Unsupported type",IF(COUNTIF(Config!$M$15:$M$34,$K12)=0,"Unsupported status","OK"))))))))
N13: =IF($A13="","",COUNTIF(Products!$F$2:$F$101,$A13)) | O13: =IF($A13="","",SUMIFS(Purchase_Orders!$O$2:$O$301,Purchase_Orders!$B$2:$B$301,$A13)) | P13: =IF(COUNTA($A13:$M13)=0,"",IF($A13="","Missing: supplier ID",IF(COUNTIF($A$2:$A$51,$A13)>1,"Duplicate supplier ID",IF($B13="","Missing: name",IF($C13="","Missing: type",IF($K13="","Missing: status",IF(COUNTIF(Config!$L$15:$L$34,$C13)=0,"Unsupported type",IF(COUNTIF(Config!$M$15:$M$34,$K13)=0,"Unsupported status","OK"))))))))
N14: =IF($A14="","",COUNTIF(Products!$F$2:$F$101,$A14)) | O14: =IF($A14="","",SUMIFS(Purchase_Orders!$O$2:$O$301,Purchase_Orders!$B$2:$B$301,$A14)) | P14: =IF(COUNTA($A14:$M14)=0,"",IF($A14="","Missing: supplier ID",IF(COUNTIF($A$2:$A$51,$A14)>1,"Duplicate supplier ID",IF($B14="","Missing: name",IF($C14="","Missing: type",IF($K14="","Missing: status",IF(COUNTIF(Config!$L$15:$L$34,$C14)=0,"Unsupported type",IF(COUNTIF(Config!$M$15:$M$34,$K14)=0,"Unsupported status","OK"))))))))
N15: =IF($A15="","",COUNTIF(Products!$F$2:$F$101,$A15)) | O15: =IF($A15="","",SUMIFS(Purchase_Orders!$O$2:$O$301,Purchase_Orders!$B$2:$B$301,$A15)) | P15: =IF(COUNTA($A15:$M15)=0,"",IF($A15="","Missing: supplier ID",IF(COUNTIF($A$2:$A$51,$A15)>1,"Duplicate supplier ID",IF($B15="","Missing: name",IF($C15="","Missing: type",IF($K15="","Missing: status",IF(COUNTIF(Config!$L$15:$L$34,$C15)=0,"Unsupported type",IF(COUNTIF(Config!$M$15:$M$34,$K15)=0,"Unsupported status","OK"))))))))
N16: =IF($A16="","",COUNTIF(Products!$F$2:$F$101,$A16)) | O16: =IF($A16="","",SUMIFS(Purchase_Orders!$O$2:$O$301,Purchase_Orders!$B$2:$B$301,$A16)) | P16: =IF(COUNTA($A16:$M16)=0,"",IF($A16="","Missing: supplier ID",IF(COUNTIF($A$2:$A$51,$A16)>1,"Duplicate supplier ID",IF($B16="","Missing: name",IF($C16="","Missing: type",IF($K16="","Missing: status",IF(COUNTIF(Config!$L$15:$L$34,$C16)=0,"Unsupported type",IF(COUNTIF(Config!$M$15:$M$34,$K16)=0,"Unsupported status","OK"))))))))
N17: =IF($A17="","",COUNTIF(Products!$F$2:$F$101,$A17)) | O17: =IF($A17="","",SUMIFS(Purchase_Orders!$O$2:$O$301,Purchase_Orders!$B$2:$B$301,$A17)) | P17: =IF(COUNTA($A17:$M17)=0,"",IF($A17="","Missing: supplier ID",IF(COUNTIF($A$2:$A$51,$A17)>1,"Duplicate supplier ID",IF($B17="","Missing: name",IF($C17="","Missing: type",IF($K17="","Missing: status",IF(COUNTIF(Config!$L$15:$L$34,$C17)=0,"Unsupported type",IF(COUNTIF(Config!$M$15:$M$34,$K17)=0,"Unsupported status","OK"))))))))
N18: =IF($A18="","",COUNTIF(Products!$F$2:$F$101,$A18)) | O18: =IF($A18="","",SUMIFS(Purchase_Orders!$O$2:$O$301,Purchase_Orders!$B$2:$B$301,$A18)) | P18: =IF(COUNTA($A18:$M18)=0,"",IF($A18="","Missing: supplier ID",IF(COUNTIF($A$2:$A$51,$A18)>1,"Duplicate supplier ID",IF($B18="","Missing: name",IF($C18="","Missing: type",IF($K18="","Missing: status",IF(COUNTIF(Config!$L$15:$L$34,$C18)=0,"Unsupported type",IF(COUNTIF(Config!$M$15:$M$34,$K18)=0,"Unsupported status","OK"))))))))
... N51: =IF($A51="","",COUNTIF(Products!$F$2:$F$101,$A51)) | O51: =IF($A51="","",SUMIFS(Purchase_Orders!$O$2:$O$301,Purchase_Orders!$B$2:$B$301,$A51)) | P51: =IF(COUNTA($A51:$M51)=0,"",IF($A51="","Missing: supplier ID",IF(COUNTIF($A$2:$A$51,$A51)>1,"Duplicate supplier ID",IF($B51="","Missing: name",IF($C51="","Missing: type",IF($K51="","Missing: status",IF(COUNTIF(Config!$L$15:$L$34,$C51)=0,"Unsupported type",IF(COUNTIF(Config!$M$15:$M$34,$K51)=0,"Unsupported status","OK"))))))))

Sheet Purchase_Orders
A1: PO ID * | B1: Supplier ID * | C1: SKU * | D1: Qty ordered * | E1: Unit cost (USD) | F1: Order date * | G1: Expected date * | H1: Status * | I1: Source link * | J1: Notes | K1: Supplier name | L1: Product name | M1: Received qty (ledger) | N1: Outstanding qty | O1: Open (1 = yes) | P1: Overdue (1 = yes) | Q1: Days late | R1: PO value (USD) | S1: Record check | T1: List order
A2: PO-2026-018 | B2: SUP-01 | C2: WPI-CHO-2LB | D2: 1500 | E2: 18.4 | F2: 46185 | G2: 46225 | H2: Received | I2: https://example.com/purchasing/PO-2026-018 | J2: Arrived 2026-07-24 | K2: =IF($A2="","",IFERROR(INDEX(Suppliers!$B$2:$B$51,MATCH($B2,Suppliers!$A$2:$A$51,0))&"","(not found)")) -> Alder Creek Dairy Proteins | L2: =IF($A2="","",IFERROR(INDEX(Products!$B$2:$B$101,MATCH($C2,Products!$A$2:$A$101,0))&"","(not found)")) -> Whey Protein Isolate, Chocolate, 2 lb | M2: =IF($A2="","",SUMIFS(Inventory_Ledger!$E$2:$E$2001,Inventory_Ledger!$H$2:$H$2001,$A2,Inventory_Ledger!$C$2:$C$2001,"Receipt",Inventory_Ledger!$D$2:$D$2001,$C2)) -> 1500 | N2: =IF($A2="","",IF(IFERROR(INDEX(Config!$D$15:$D$34,MATCH($H2,Config!$C$15:$C$34,0)),"No")="Yes",MAX(0,IF(ISNUMBER($D2),$D2,0)-$M2),0)) -> 0 | O2: =IF($A2="","",IF($N2>0,1,0)) -> 0 | P2: =IF($A2="","",IF(AND($O2=1,ISNUMBER($G2)),IF($G2<Config!$B$4,1,0),0)) -> 0 | Q2: =IF($A2="","",IF($P2=1,Config!$B$4-$G2,0)) -> 0 | R2: =IF($A2="","",IF(AND(ISNUMBER($D2),ISNUMBER($E2)),$D2*$E2,"")) -> 27600 | S2: =IF(COUNTA($A2:$J2)=0,"",IF($A2="","Missing: PO ID",IF(COUNTIF($A$2:$A$301,$A2)>1,"Duplicate PO ID",IF($B2="","Missing: supplier",IF($C2="","Missing: SKU",IF(NOT(ISNUMBER($D2)),"Missing: qty",IF(NOT(ISNUMBER($F2)),"Missing: order date",IF(NOT(ISNUMBER($G2)),"Missing: expected date",IF($H2="","Missing: status",IF($I2="","Missing: source link",IF(COUNTIF(Suppliers!$A$2:$A$51,$B2)=0,"Unknown supplier",IF(COUNTIF(Products!$A$2:$A$101,$C2)=0,"Unknown SKU",IF(COUNTIF(Config!$C$15:$C$34,$H2)=0,"Unsupported status",IF($D2<=0,"Qty must be above 0",IF($G2<$F2,"Expected date before order date",IF($M2>$D2,"Received more than ordered",IF(AND($H2="Received",$M2<$D2),"Status Received but not fully received",IF(AND(IFERROR(INDEX(Config!$D$15:$D$34,MATCH($H2,Config!$C$15:$C$34,0)),"No")="Yes",$M2>=$D2),"Fully received: update status","OK")))))))))))))))))) -> OK | T2: =IF($O2=1,IFERROR(COUNTIFS($O$2:$O$301,1,$G$2:$G$301,"<"&$G2)+COUNTIFS($O$2:$O2,1,$G$2:$G2,$G2),""),"")
A3: PO-2026-021 | B3: SUP-02 | C3: BAR-PBC-12 | D3: 2400 | E3: 11.2 | F3: 46211 | G3: 46244 | H3: Received | I3: https://example.com/purchasing/PO-2026-021 | J3: Arrived 2026-08-12 | K3: =IF($A3="","",IFERROR(INDEX(Suppliers!$B$2:$B$51,MATCH($B3,Suppliers!$A$2:$A$51,0))&"","(not found)")) -> Bramwell Bar Works | L3: =IF($A3="","",IFERROR(INDEX(Products!$B$2:$B$101,MATCH($C3,Products!$A$2:$A$101,0))&"","(not found)")) -> Protein Bar, Peanut Butter Chocolate, 12-pack | M3: =IF($A3="","",SUMIFS(Inventory_Ledger!$E$2:$E$2001,Inventory_Ledger!$H$2:$H$2001,$A3,Inventory_Ledger!$C$2:$C$2001,"Receipt",Inventory_Ledger!$D$2:$D$2001,$C3)) -> 2400 | N3: =IF($A3="","",IF(IFERROR(INDEX(Config!$D$15:$D$34,MATCH($H3,Config!$C$15:$C$34,0)),"No")="Yes",MAX(0,IF(ISNUMBER($D3),$D3,0)-$M3),0)) -> 0 | O3: =IF($A3="","",IF($N3>0,1,0)) -> 0 | P3: =IF($A3="","",IF(AND($O3=1,ISNUMBER($G3)),IF($G3<Config!$B$4,1,0),0)) -> 0 | Q3: =IF($A3="","",IF($P3=1,Config!$B$4-$G3,0)) -> 0 | R3: =IF($A3="","",IF(AND(ISNUMBER($D3),ISNUMBER($E3)),$D3*$E3,"")) -> 26880 | S3: =IF(COUNTA($A3:$J3)=0,"",IF($A3="","Missing: PO ID",IF(COUNTIF($A$2:$A$301,$A3)>1,"Duplicate PO ID",IF($B3="","Missing: supplier",IF($C3="","Missing: SKU",IF(NOT(ISNUMBER($D3)),"Missing: qty",IF(NOT(ISNUMBER($F3)),"Missing: order date",IF(NOT(ISNUMBER($G3)),"Missing: expected date",IF($H3="","Missing: status",IF($I3="","Missing: source link",IF(COUNTIF(Suppliers!$A$2:$A$51,$B3)=0,"Unknown supplier",IF(COUNTIF(Products!$A$2:$A$101,$C3)=0,"Unknown SKU",IF(COUNTIF(Config!$C$15:$C$34,$H3)=0,"Unsupported status",IF($D3<=0,"Qty must be above 0",IF($G3<$F3,"Expected date before order date",IF($M3>$D3,"Received more than ordered",IF(AND($H3="Received",$M3<$D3),"Status Received but not fully received",IF(AND(IFERROR(INDEX(Config!$D$15:$D$34,MATCH($H3,Config!$C$15:$C$34,0)),"No")="Yes",$M3>=$D3),"Fully received: update status","OK")))))))))))))))))) -> OK | T3: =IF($O3=1,IFERROR(COUNTIFS($O$2:$O$301,1,$G$2:$G$301,"<"&$G3)+COUNTIFS($O$2:$O3,1,$G$2:$G3,$G3),""),"")
A4: PO-2026-022 | B4: SUP-04 | C4: CRE-UNF-300G | D4: 1000 | E4: 6.9 | F4: 46223 | G4: 46261 | H4: Received | I4: https://example.com/purchasing/PO-2026-022 | J4: Arrived 2026-08-28 | K4: =IF($A4="","",IFERROR(INDEX(Suppliers!$B$2:$B$51,MATCH($B4,Suppliers!$A$2:$A$51,0))&"","(not found)")) -> Dunmore Powder Labs | L4: =IF($A4="","",IFERROR(INDEX(Products!$B$2:$B$101,MATCH($C4,Products!$A$2:$A$101,0))&"","(not found)")) -> Creatine Monohydrate, Unflavoured, 300 g | M4: =IF($A4="","",SUMIFS(Inventory_Ledger!$E$2:$E$2001,Inventory_Ledger!$H$2:$H$2001,$A4,Inventory_Ledger!$C$2:$C$2001,"Receipt",Inventory_Ledger!$D$2:$D$2001,$C4)) -> 1000 | N4: =IF($A4="","",IF(IFERROR(INDEX(Config!$D$15:$D$34,MATCH($H4,Config!$C$15:$C$34,0)),"No")="Yes",MAX(0,IF(ISNUMBER($D4),$D4,0)-$M4),0)) -> 0 | O4: =IF($A4="","",IF($N4>0,1,0)) -> 0 | P4: =IF($A4="","",IF(AND($O4=1,ISNUMBER($G4)),IF($G4<Config!$B$4,1,0),0)) -> 0 | Q4: =IF($A4="","",IF($P4=1,Config!$B$4-$G4,0)) -> 0 | R4: =IF($A4="","",IF(AND(ISNUMBER($D4),ISNUMBER($E4)),$D4*$E4,"")) -> 6900 | S4: =IF(COUNTA($A4:$J4)=0,"",IF($A4="","Missing: PO ID",IF(COUNTIF($A$2:$A$301,$A4)>1,"Duplicate PO ID",IF($B4="","Missing: supplier",IF($C4="","Missing: SKU",IF(NOT(ISNUMBER($D4)),"Missing: qty",IF(NOT(ISNUMBER($F4)),"Missing: order date",IF(NOT(ISNUMBER($G4)),"Missing: expected date",IF($H4="","Missing: status",IF($I4="","Missing: source link",IF(COUNTIF(Suppliers!$A$2:$A$51,$B4)=0,"Unknown supplier",IF(COUNTIF(Products!$A$2:$A$101,$C4)=0,"Unknown SKU",IF(COUNTIF(Config!$C$15:$C$34,$H4)=0,"Unsupported status",IF($D4<=0,"Qty must be above 0",IF($G4<$F4,"Expected date before order date",IF($M4>$D4,"Received more than ordered",IF(AND($H4="Received",$M4<$D4),"Status Received but not fully received",IF(AND(IFERROR(INDEX(Config!$D$15:$D$34,MATCH($H4,Config!$C$15:$C$34,0)),"No")="Yes",$M4>=$D4),"Fully received: update status","OK")))))))))))))))))) -> OK | T4: =IF($O4=1,IFERROR(COUNTIFS($O$2:$O$301,1,$G$2:$G$301,"<"&$G4)+COUNTIFS($O$2:$O4,1,$G$2:$G4,$G4),""),"")
A5: PO-2026-024 | B5: SUP-02 | C5: BAR-CKD-12 | D5: 1500 | E5: 11.2 | F5: 46239 | G5: 46273 | H5: Received | I5: https://example.com/purchasing/PO-2026-024 | J5: Arrived 2026-09-09 | K5: =IF($A5="","",IFERROR(INDEX(Suppliers!$B$2:$B$51,MATCH($B5,Suppliers!$A$2:$A$51,0))&"","(not found)")) -> Bramwell Bar Works | L5: =IF($A5="","",IFERROR(INDEX(Products!$B$2:$B$101,MATCH($C5,Products!$A$2:$A$101,0))&"","(not found)")) -> Protein Bar, Cookie Dough, 12-pack | M5: =IF($A5="","",SUMIFS(Inventory_Ledger!$E$2:$E$2001,Inventory_Ledger!$H$2:$H$2001,$A5,Inventory_Ledger!$C$2:$C$2001,"Receipt",Inventory_Ledger!$D$2:$D$2001,$C5)) -> 1500 | N5: =IF($A5="","",IF(IFERROR(INDEX(Config!$D$15:$D$34,MATCH($H5,Config!$C$15:$C$34,0)),"No")="Yes",MAX(0,IF(ISNUMBER($D5),$D5,0)-$M5),0)) -> 0 | O5: =IF($A5="","",IF($N5>0,1,0)) -> 0 | P5: =IF($A5="","",IF(AND($O5=1,ISNUMBER($G5)),IF($G5<Config!$B$4,1,0),0)) -> 0 | Q5: =IF($A5="","",IF($P5=1,Config!$B$4-$G5,0)) -> 0 | R5: =IF($A5="","",IF(AND(ISNUMBER($D5),ISNUMBER($E5)),$D5*$E5,"")) -> 16800 | S5: =IF(COUNTA($A5:$J5)=0,"",IF($A5="","Missing: PO ID",IF(COUNTIF($A$2:$A$301,$A5)>1,"Duplicate PO ID",IF($B5="","Missing: supplier",IF($C5="","Missing: SKU",IF(NOT(ISNUMBER($D5)),"Missing: qty",IF(NOT(ISNUMBER($F5)),"Missing: order date",IF(NOT(ISNUMBER($G5)),"Missing: expected date",IF($H5="","Missing: status",IF($I5="","Missing: source link",IF(COUNTIF(Suppliers!$A$2:$A$51,$B5)=0,"Unknown supplier",IF(COUNTIF(Products!$A$2:$A$101,$C5)=0,"Unknown SKU",IF(COUNTIF(Config!$C$15:$C$34,$H5)=0,"Unsupported status",IF($D5<=0,"Qty must be above 0",IF($G5<$F5,"Expected date before order date",IF($M5>$D5,"Received more than ordered",IF(AND($H5="Received",$M5<$D5),"Status Received but not fully received",IF(AND(IFERROR(INDEX(Config!$D$15:$D$34,MATCH($H5,Config!$C$15:$C$34,0)),"No")="Yes",$M5>=$D5),"Fully received: update status","OK")))))))))))))))))) -> OK | T5: =IF($O5=1,IFERROR(COUNTIFS($O$2:$O$301,1,$G$2:$G$301,"<"&$G5)+COUNTIFS($O$2:$O5,1,$G$2:$G5,$G5),""),"")
A6: PO-2026-025 | B6: SUP-04 | C6: PRE-BRZ-30 | D6: 800 | E6: 9.6 | F6: 46248 | G6: 46280 | H6: Received | I6: https://example.com/purchasing/PO-2026-025 | J6: Arrived 2026-09-15 | K6: =IF($A6="","",IFERROR(INDEX(Suppliers!$B$2:$B$51,MATCH($B6,Suppliers!$A$2:$A$51,0))&"","(not found)")) -> Dunmore Powder Labs | L6: =IF($A6="","",IFERROR(INDEX(Products!$B$2:$B$101,MATCH($C6,Products!$A$2:$A$101,0))&"","(not found)")) -> Pre-Workout, Blue Raspberry, 30 servings | M6: =IF($A6="","",SUMIFS(Inventory_Ledger!$E$2:$E$2001,Inventory_Ledger!$H$2:$H$2001,$A6,Inventory_Ledger!$C$2:$C$2001,"Receipt",Inventory_Ledger!$D$2:$D$2001,$C6)) -> 800 | N6: =IF($A6="","",IF(IFERROR(INDEX(Config!$D$15:$D$34,MATCH($H6,Config!$C$15:$C$34,0)),"No")="Yes",MAX(0,IF(ISNUMBER($D6),$D6,0)-$M6),0)) -> 0 | O6: =IF($A6="","",IF($N6>0,1,0)) -> 0 | P6: =IF($A6="","",IF(AND($O6=1,ISNUMBER($G6)),IF($G6<Config!$B$4,1,0),0)) -> 0 | Q6: =IF($A6="","",IF($P6=1,Config!$B$4-$G6,0)) -> 0 | R6: =IF($A6="","",IF(AND(ISNUMBER($D6),ISNUMBER($E6)),$D6*$E6,"")) -> 7680 | S6: =IF(COUNTA($A6:$J6)=0,"",IF($A6="","Missing: PO ID",IF(COUNTIF($A$2:$A$301,$A6)>1,"Duplicate PO ID",IF($B6="","Missing: supplier",IF($C6="","Missing: SKU",IF(NOT(ISNUMBER($D6)),"Missing: qty",IF(NOT(ISNUMBER($F6)),"Missing: order date",IF(NOT(ISNUMBER($G6)),"Missing: expected date",IF($H6="","Missing: status",IF($I6="","Missing: source link",IF(COUNTIF(Suppliers!$A$2:$A$51,$B6)=0,"Unknown supplier",IF(COUNTIF(Products!$A$2:$A$101,$C6)=0,"Unknown SKU",IF(COUNTIF(Config!$C$15:$C$34,$H6)=0,"Unsupported status",IF($D6<=0,"Qty must be above 0",IF($G6<$F6,"Expected date before order date",IF($M6>$D6,"Received more than ordered",IF(AND($H6="Received",$M6<$D6),"Status Received but not fully received",IF(AND(IFERROR(INDEX(Config!$D$15:$D$34,MATCH($H6,Config!$C$15:$C$34,0)),"No")="Yes",$M6>=$D6),"Fully received: update status","OK")))))))))))))))))) -> OK | T6: =IF($O6=1,IFERROR(COUNTIFS($O$2:$O$301,1,$G$2:$G$301,"<"&$G6)+COUNTIFS($O$2:$O6,1,$G$2:$G6,$G6),""),"")
A7: PO-2026-027 | B7: SUP-01 | C7: WPI-VAN-2LB | D7: 1200 | E7: 18.4 | F7: 46267 | G7: 46324 | H7: Partially received | I7: https://example.com/purchasing/PO-2026-027 | J7: First 600 arrived 2026-10-08; balance promised for 2026-10-29 | K7: =IF($A7="","",IFERROR(INDEX(Suppliers!$B$2:$B$51,MATCH($B7,Suppliers!$A$2:$A$51,0))&"","(not found)")) -> Alder Creek Dairy Proteins | L7: =IF($A7="","",IFERROR(INDEX(Products!$B$2:$B$101,MATCH($C7,Products!$A$2:$A$101,0))&"","(not found)")) -> Whey Protein Isolate, Vanilla, 2 lb | M7: =IF($A7="","",SUMIFS(Inventory_Ledger!$E$2:$E$2001,Inventory_Ledger!$H$2:$H$2001,$A7,Inventory_Ledger!$C$2:$C$2001,"Receipt",Inventory_Ledger!$D$2:$D$2001,$C7)) -> 600 | N7: =IF($A7="","",IF(IFERROR(INDEX(Config!$D$15:$D$34,MATCH($H7,Config!$C$15:$C$34,0)),"No")="Yes",MAX(0,IF(ISNUMBER($D7),$D7,0)-$M7),0)) -> 600 | O7: =IF($A7="","",IF($N7>0,1,0)) -> 1 | P7: =IF($A7="","",IF(AND($O7=1,ISNUMBER($G7)),IF($G7<Config!$B$4,1,0),0)) -> 0 | Q7: =IF($A7="","",IF($P7=1,Config!$B$4-$G7,0)) -> 0 | R7: =IF($A7="","",IF(AND(ISNUMBER($D7),ISNUMBER($E7)),$D7*$E7,"")) -> 22080 | S7: =IF(COUNTA($A7:$J7)=0,"",IF($A7="","Missing: PO ID",IF(COUNTIF($A$2:$A$301,$A7)>1,"Duplicate PO ID",IF($B7="","Missing: supplier",IF($C7="","Missing: SKU",IF(NOT(ISNUMBER($D7)),"Missing: qty",IF(NOT(ISNUMBER($F7)),"Missing: order date",IF(NOT(ISNUMBER($G7)),"Missing: expected date",IF($H7="","Missing: status",IF($I7="","Missing: source link",IF(COUNTIF(Suppliers!$A$2:$A$51,$B7)=0,"Unknown supplier",IF(COUNTIF(Products!$A$2:$A$101,$C7)=0,"Unknown SKU",IF(COUNTIF(Config!$C$15:$C$34,$H7)=0,"Unsupported status",IF($D7<=0,"Qty must be above 0",IF($G7<$F7,"Expected date before order date",IF($M7>$D7,"Received more than ordered",IF(AND($H7="Received",$M7<$D7),"Status Received but not fully received",IF(AND(IFERROR(INDEX(Config!$D$15:$D$34,MATCH($H7,Config!$C$15:$C$34,0)),"No")="Yes",$M7>=$D7),"Fully received: update status","OK")))))))))))))))))) -> OK | T7: =IF($O7=1,IFERROR(COUNTIFS($O$2:$O$301,1,$G$2:$G$301,"<"&$G7)+COUNTIFS($O$2:$O7,1,$G$2:$G7,$G7),""),"") -> 4
A8: PO-2026-028 | B8: SUP-03 | C8: PLT-CHO-2LB | D8: 600 | E8: 16.1 | F8: 46262 | G8: 46304 | H8: Cancelled | I8: https://example.com/purchasing/PO-2026-028 | J8: Cancelled 2026-09-04 after a price change; stock still above reorder point | K8: =IF($A8="","",IFERROR(INDEX(Suppliers!$B$2:$B$51,MATCH($B8,Suppliers!$A$2:$A$51,0))&"","(not found)")) -> Corliss Plant Proteins | L8: =IF($A8="","",IFERROR(INDEX(Products!$B$2:$B$101,MATCH($C8,Products!$A$2:$A$101,0))&"","(not found)")) -> Plant Protein, Chocolate, 2 lb | M8: =IF($A8="","",SUMIFS(Inventory_Ledger!$E$2:$E$2001,Inventory_Ledger!$H$2:$H$2001,$A8,Inventory_Ledger!$C$2:$C$2001,"Receipt",Inventory_Ledger!$D$2:$D$2001,$C8)) -> 0 | N8: =IF($A8="","",IF(IFERROR(INDEX(Config!$D$15:$D$34,MATCH($H8,Config!$C$15:$C$34,0)),"No")="Yes",MAX(0,IF(ISNUMBER($D8),$D8,0)-$M8),0)) -> 0 | O8: =IF($A8="","",IF($N8>0,1,0)) -> 0 | P8: =IF($A8="","",IF(AND($O8=1,ISNUMBER($G8)),IF($G8<Config!$B$4,1,0),0)) -> 0 | Q8: =IF($A8="","",IF($P8=1,Config!$B$4-$G8,0)) -> 0 | R8: =IF($A8="","",IF(AND(ISNUMBER($D8),ISNUMBER($E8)),$D8*$E8,"")) -> 9660 | S8: =IF(COUNTA($A8:$J8)=0,"",IF($A8="","Missing: PO ID",IF(COUNTIF($A$2:$A$301,$A8)>1,"Duplicate PO ID",IF($B8="","Missing: supplier",IF($C8="","Missing: SKU",IF(NOT(ISNUMBER($D8)),"Missing: qty",IF(NOT(ISNUMBER($F8)),"Missing: order date",IF(NOT(ISNUMBER($G8)),"Missing: expected date",IF($H8="","Missing: status",IF($I8="","Missing: source link",IF(COUNTIF(Suppliers!$A$2:$A$51,$B8)=0,"Unknown supplier",IF(COUNTIF(Products!$A$2:$A$101,$C8)=0,"Unknown SKU",IF(COUNTIF(Config!$C$15:$C$34,$H8)=0,"Unsupported status",IF($D8<=0,"Qty must be above 0",IF($G8<$F8,"Expected date before order date",IF($M8>$D8,"Received more than ordered",IF(AND($H8="Received",$M8<$D8),"Status Received but not fully received",IF(AND(IFERROR(INDEX(Config!$D$15:$D$34,MATCH($H8,Config!$C$15:$C$34,0)),"No")="Yes",$M8>=$D8),"Fully received: update status","OK")))))))))))))))))) -> OK | T8: =IF($O8=1,IFERROR(COUNTIFS($O$2:$O$301,1,$G$2:$G$301,"<"&$G8)+COUNTIFS($O$2:$O8,1,$G$2:$G8,$G8),""),"")
A9: PO-2026-029 | B9: SUP-03 | C9: PLT-VAN-2LB | D9: 500 | E9: 16.1 | F9: 46266 | G9: 46301 | H9: Confirmed | I9: https://example.com/purchasing/PO-2026-029 | J9: Supplier confirmed 2026-09-03 | K9: =IF($A9="","",IFERROR(INDEX(Suppliers!$B$2:$B$51,MATCH($B9,Suppliers!$A$2:$A$51,0))&"","(not found)")) -> Corliss Plant Proteins | L9: =IF($A9="","",IFERROR(INDEX(Products!$B$2:$B$101,MATCH($C9,Products!$A$2:$A$101,0))&"","(not found)")) -> Plant Protein, Vanilla, 2 lb | M9: =IF($A9="","",SUMIFS(Inventory_Ledger!$E$2:$E$2001,Inventory_Ledger!$H$2:$H$2001,$A9,Inventory_Ledger!$C$2:$C$2001,"Receipt",Inventory_Ledger!$D$2:$D$2001,$C9)) -> 0 | N9: =IF($A9="","",IF(IFERROR(INDEX(Config!$D$15:$D$34,MATCH($H9,Config!$C$15:$C$34,0)),"No")="Yes",MAX(0,IF(ISNUMBER($D9),$D9,0)-$M9),0)) -> 500 | O9: =IF($A9="","",IF($N9>0,1,0)) -> 1 | P9: =IF($A9="","",IF(AND($O9=1,ISNUMBER($G9)),IF($G9<Config!$B$4,1,0),0)) -> 1 | Q9: =IF($A9="","",IF($P9=1,Config!$B$4-$G9,0)) -> 9 | R9: =IF($A9="","",IF(AND(ISNUMBER($D9),ISNUMBER($E9)),$D9*$E9,"")) -> 8050 | S9: =IF(COUNTA($A9:$J9)=0,"",IF($A9="","Missing: PO ID",IF(COUNTIF($A$2:$A$301,$A9)>1,"Duplicate PO ID",IF($B9="","Missing: supplier",IF($C9="","Missing: SKU",IF(NOT(ISNUMBER($D9)),"Missing: qty",IF(NOT(ISNUMBER($F9)),"Missing: order date",IF(NOT(ISNUMBER($G9)),"Missing: expected date",IF($H9="","Missing: status",IF($I9="","Missing: source link",IF(COUNTIF(Suppliers!$A$2:$A$51,$B9)=0,"Unknown supplier",IF(COUNTIF(Products!$A$2:$A$101,$C9)=0,"Unknown SKU",IF(COUNTIF(Config!$C$15:$C$34,$H9)=0,"Unsupported status",IF($D9<=0,"Qty must be above 0",IF($G9<$F9,"Expected date before order date",IF($M9>$D9,"Received more than ordered",IF(AND($H9="Received",$M9<$D9),"Status Received but not fully received",IF(AND(IFERROR(INDEX(Config!$D$15:$D$34,MATCH($H9,Config!$C$15:$C$34,0)),"No")="Yes",$M9>=$D9),"Fully received: update status","OK")))))))))))))))))) -> OK | T9: =IF($O9=1,IFERROR(COUNTIFS($O$2:$O$301,1,$G$2:$G$301,"<"&$G9)+COUNTIFS($O$2:$O9,1,$G$2:$G9,$G9),""),"") -> 1
A10: PO-2026-030 | B10: SUP-01 | C10: WPI-CHO-2LB | D10: 1500 | E10: 18.4 | F10: 46280 | G10: 46315 | H10: In transit | I10: https://example.com/purchasing/PO-2026-030 | J10: Carrier booked 2026-10-13 | K10: =IF($A10="","",IFERROR(INDEX(Suppliers!$B$2:$B$51,MATCH($B10,Suppliers!$A$2:$A$51,0))&"","(not found)")) -> Alder Creek Dairy Proteins | L10: =IF($A10="","",IFERROR(INDEX(Products!$B$2:$B$101,MATCH($C10,Products!$A$2:$A$101,0))&"","(not found)")) -> Whey Protein Isolate, Chocolate, 2 lb | M10: =IF($A10="","",SUMIFS(Inventory_Ledger!$E$2:$E$2001,Inventory_Ledger!$H$2:$H$2001,$A10,Inventory_Ledger!$C$2:$C$2001,"Receipt",Inventory_Ledger!$D$2:$D$2001,$C10)) -> 0 | N10: =IF($A10="","",IF(IFERROR(INDEX(Config!$D$15:$D$34,MATCH($H10,Config!$C$15:$C$34,0)),"No")="Yes",MAX(0,IF(ISNUMBER($D10),$D10,0)-$M10),0)) -> 1500 | O10: =IF($A10="","",IF($N10>0,1,0)) -> 1 | P10: =IF($A10="","",IF(AND($O10=1,ISNUMBER($G10)),IF($G10<Config!$B$4,1,0),0)) -> 0 | Q10: =IF($A10="","",IF($P10=1,Config!$B$4-$G10,0)) -> 0 | R10: =IF($A10="","",IF(AND(ISNUMBER($D10),ISNUMBER($E10)),$D10*$E10,"")) -> 27600 | S10: =IF(COUNTA($A10:$J10)=0,"",IF($A10="","Missing: PO ID",IF(COUNTIF($A$2:$A$301,$A10)>1,"Duplicate PO ID",IF($B10="","Missing: supplier",IF($C10="","Missing: SKU",IF(NOT(ISNUMBER($D10)),"Missing: qty",IF(NOT(ISNUMBER($F10)),"Missing: order date",IF(NOT(ISNUMBER($G10)),"Missing: expected date",IF($H10="","Missing: status",IF($I10="","Missing: source link",IF(COUNTIF(Suppliers!$A$2:$A$51,$B10)=0,"Unknown supplier",IF(COUNTIF(Products!$A$2:$A$101,$C10)=0,"Unknown SKU",IF(COUNTIF(Config!$C$15:$C$34,$H10)=0,"Unsupported status",IF($D10<=0,"Qty must be above 0",IF($G10<$F10,"Expected date before order date",IF($M10>$D10,"Received more than ordered",IF(AND($H10="Received",$M10<$D10),"Status Received but not fully received",IF(AND(IFERROR(INDEX(Config!$D$15:$D$34,MATCH($H10,Config!$C$15:$C$34,0)),"No")="Yes",$M10>=$D10),"Fully received: update status","OK")))))))))))))))))) -> OK | T10: =IF($O10=1,IFERROR(COUNTIFS($O$2:$O$301,1,$G$2:$G$301,"<"&$G10)+COUNTIFS($O$2:$O10,1,$G$2:$G10,$G10),""),"") -> 3
A11: PO-2026-031 | B11: SUP-04 | C11: PRE-WTM-30 | D11: 600 | E11: 9.6 | F11: 46269 | G11: 46305 | H11: In transit | I11: https://example.com/purchasing/PO-2026-031 | J11: Carrier delay reported | K11: =IF($A11="","",IFERROR(INDEX(Suppliers!$B$2:$B$51,MATCH($B11,Suppliers!$A$2:$A$51,0))&"","(not found)")) -> Dunmore Powder Labs | L11: =IF($A11="","",IFERROR(INDEX(Products!$B$2:$B$101,MATCH($C11,Products!$A$2:$A$101,0))&"","(not found)")) -> Pre-Workout, Watermelon, 30 servings | M11: =IF($A11="","",SUMIFS(Inventory_Ledger!$E$2:$E$2001,Inventory_Ledger!$H$2:$H$2001,$A11,Inventory_Ledger!$C$2:$C$2001,"Receipt",Inventory_Ledger!$D$2:$D$2001,$C11)) -> 0 | N11: =IF($A11="","",IF(IFERROR(INDEX(Config!$D$15:$D$34,MATCH($H11,Config!$C$15:$C$34,0)),"No")="Yes",MAX(0,IF(ISNUMBER($D11),$D11,0)-$M11),0)) -> 600 | O11: =IF($A11="","",IF($N11>0,1,0)) -> 1 | P11: =IF($A11="","",IF(AND($O11=1,ISNUMBER($G11)),IF($G11<Config!$B$4,1,0),0)) -> 1 | Q11: =IF($A11="","",IF($P11=1,Config!$B$4-$G11,0)) -> 5 | R11: =IF($A11="","",IF(AND(ISNUMBER($D11),ISNUMBER($E11)),$D11*$E11,"")) -> 5760 | S11: =IF(COUNTA($A11:$J11)=0,"",IF($A11="","Missing: PO ID",IF(COUNTIF($A$2:$A$301,$A11)>1,"Duplicate PO ID",IF($B11="","Missing: supplier",IF($C11="","Missing: SKU",IF(NOT(ISNUMBER($D11)),"Missing: qty",IF(NOT(ISNUMBER($F11)),"Missing: order date",IF(NOT(ISNUMBER($G11)),"Missing: expected date",IF($H11="","Missing: status",IF($I11="","Missing: source link",IF(COUNTIF(Suppliers!$A$2:$A$51,$B11)=0,"Unknown supplier",IF(COUNTIF(Products!$A$2:$A$101,$C11)=0,"Unknown SKU",IF(COUNTIF(Config!$C$15:$C$34,$H11)=0,"Unsupported status",IF($D11<=0,"Qty must be above 0",IF($G11<$F11,"Expected date before order date",IF($M11>$D11,"Received more than ordered",IF(AND($H11="Received",$M11<$D11),"Status Received but not fully received",IF(AND(IFERROR(INDEX(Config!$D$15:$D$34,MATCH($H11,Config!$C$15:$C$34,0)),"No")="Yes",$M11>=$D11),"Fully received: update status","OK")))))))))))))))))) -> OK | T11: =IF($O11=1,IFERROR(COUNTIFS($O$2:$O$301,1,$G$2:$G$301,"<"&$G11)+COUNTIFS($O$2:$O11,1,$G$2:$G11,$G11),""),"") -> 2
A12: PO-2026-032 | B12: SUP-05 | C12: CAS-CHO-2LB | D12: 360 | E12: 19.7 | F12: 46300 | G12: 46345 | H12: Ordered | I12: https://example.com/purchasing/PO-2026-032 | K12: =IF($A12="","",IFERROR(INDEX(Suppliers!$B$2:$B$51,MATCH($B12,Suppliers!$A$2:$A$51,0))&"","(not found)")) -> Elmstead Co-Packing | L12: =IF($A12="","",IFERROR(INDEX(Products!$B$2:$B$101,MATCH($C12,Products!$A$2:$A$101,0))&"","(not found)")) -> Micellar Casein, Chocolate, 2 lb | M12: =IF($A12="","",SUMIFS(Inventory_Ledger!$E$2:$E$2001,Inventory_Ledger!$H$2:$H$2001,$A12,Inventory_Ledger!$C$2:$C$2001,"Receipt",Inventory_Ledger!$D$2:$D$2001,$C12)) -> 0 | N12: =IF($A12="","",IF(IFERROR(INDEX(Config!$D$15:$D$34,MATCH($H12,Config!$C$15:$C$34,0)),"No")="Yes",MAX(0,IF(ISNUMBER($D12),$D12,0)-$M12),0)) -> 360 | O12: =IF($A12="","",IF($N12>0,1,0)) -> 1 | P12: =IF($A12="","",IF(AND($O12=1,ISNUMBER($G12)),IF($G12<Config!$B$4,1,0),0)) -> 0 | Q12: =IF($A12="","",IF($P12=1,Config!$B$4-$G12,0)) -> 0 | R12: =IF($A12="","",IF(AND(ISNUMBER($D12),ISNUMBER($E12)),$D12*$E12,"")) -> 7092 | S12: =IF(COUNTA($A12:$J12)=0,"",IF($A12="","Missing: PO ID",IF(COUNTIF($A$2:$A$301,$A12)>1,"Duplicate PO ID",IF($B12="","Missing: supplier",IF($C12="","Missing: SKU",IF(NOT(ISNUMBER($D12)),"Missing: qty",IF(NOT(ISNUMBER($F12)),"Missing: order date",IF(NOT(ISNUMBER($G12)),"Missing: expected date",IF($H12="","Missing: status",IF($I12="","Missing: source link",IF(COUNTIF(Suppliers!$A$2:$A$51,$B12)=0,"Unknown supplier",IF(COUNTIF(Products!$A$2:$A$101,$C12)=0,"Unknown SKU",IF(COUNTIF(Config!$C$15:$C$34,$H12)=0,"Unsupported status",IF($D12<=0,"Qty must be above 0",IF($G12<$F12,"Expected date before order date",IF($M12>$D12,"Received more than ordered",IF(AND($H12="Received",$M12<$D12),"Status Received but not fully received",IF(AND(IFERROR(INDEX(Config!$D$15:$D$34,MATCH($H12,Config!$C$15:$C$34,0)),"No")="Yes",$M12>=$D12),"Fully received: update status","OK")))))))))))))))))) -> OK | T12: =IF($O12=1,IFERROR(COUNTIFS($O$2:$O$301,1,$G$2:$G$301,"<"&$G12)+COUNTIFS($O$2:$O12,1,$G$2:$G12,$G12),""),"") -> 5
A13: PO-2026-034 | B13: SUP-04 | C13: CRE-UNF-500G | D13: 700 | E13: 10.3 | F13: 46309 | G13: 46351 | H13: Draft | I13: https://example.com/purchasing/PO-2026-034 | J13: Waiting for sign-off | K13: =IF($A13="","",IFERROR(INDEX(Suppliers!$B$2:$B$51,MATCH($B13,Suppliers!$A$2:$A$51,0))&"","(not found)")) -> Dunmore Powder Labs | L13: =IF($A13="","",IFERROR(INDEX(Products!$B$2:$B$101,MATCH($C13,Products!$A$2:$A$101,0))&"","(not found)")) -> Creatine Monohydrate, Unflavoured, 500 g | M13: =IF($A13="","",SUMIFS(Inventory_Ledger!$E$2:$E$2001,Inventory_Ledger!$H$2:$H$2001,$A13,Inventory_Ledger!$C$2:$C$2001,"Receipt",Inventory_Ledger!$D$2:$D$2001,$C13)) -> 0 | N13: =IF($A13="","",IF(IFERROR(INDEX(Config!$D$15:$D$34,MATCH($H13,Config!$C$15:$C$34,0)),"No")="Yes",MAX(0,IF(ISNUMBER($D13),$D13,0)-$M13),0)) -> 0 | O13: =IF($A13="","",IF($N13>0,1,0)) -> 0 | P13: =IF($A13="","",IF(AND($O13=1,ISNUMBER($G13)),IF($G13<Config!$B$4,1,0),0)) -> 0 | Q13: =IF($A13="","",IF($P13=1,Config!$B$4-$G13,0)) -> 0 | R13: =IF($A13="","",IF(AND(ISNUMBER($D13),ISNUMBER($E13)),$D13*$E13,"")) -> 7210 | S13: =IF(COUNTA($A13:$J13)=0,"",IF($A13="","Missing: PO ID",IF(COUNTIF($A$2:$A$301,$A13)>1,"Duplicate PO ID",IF($B13="","Missing: supplier",IF($C13="","Missing: SKU",IF(NOT(ISNUMBER($D13)),"Missing: qty",IF(NOT(ISNUMBER($F13)),"Missing: order date",IF(NOT(ISNUMBER($G13)),"Missing: expected date",IF($H13="","Missing: status",IF($I13="","Missing: source link",IF(COUNTIF(Suppliers!$A$2:$A$51,$B13)=0,"Unknown supplier",IF(COUNTIF(Products!$A$2:$A$101,$C13)=0,"Unknown SKU",IF(COUNTIF(Config!$C$15:$C$34,$H13)=0,"Unsupported status",IF($D13<=0,"Qty must be above 0",IF($G13<$F13,"Expected date before order date",IF($M13>$D13,"Received more than ordered",IF(AND($H13="Received",$M13<$D13),"Status Received but not fully received",IF(AND(IFERROR(INDEX(Config!$D$15:$D$34,MATCH($H13,Config!$C$15:$C$34,0)),"No")="Yes",$M13>=$D13),"Fully received: update status","OK")))))))))))))))))) -> OK | T13: =IF($O13=1,IFERROR(COUNTIFS($O$2:$O$301,1,$G$2:$G$301,"<"&$G13)+COUNTIFS($O$2:$O13,1,$G$2:$G13,$G13),""),"")
K14: =IF($A14="","",IFERROR(INDEX(Suppliers!$B$2:$B$51,MATCH($B14,Suppliers!$A$2:$A$51,0))&"","(not found)")) | L14: =IF($A14="","",IFERROR(INDEX(Products!$B$2:$B$101,MATCH($C14,Products!$A$2:$A$101,0))&"","(not found)")) | M14: =IF($A14="","",SUMIFS(Inventory_Ledger!$E$2:$E$2001,Inventory_Ledger!$H$2:$H$2001,$A14,Inventory_Ledger!$C$2:$C$2001,"Receipt",Inventory_Ledger!$D$2:$D$2001,$C14)) | N14: =IF($A14="","",IF(IFERROR(INDEX(Config!$D$15:$D$34,MATCH($H14,Config!$C$15:$C$34,0)),"No")="Yes",MAX(0,IF(ISNUMBER($D14),$D14,0)-$M14),0)) | O14: =IF($A14="","",IF($N14>0,1,0)) | P14: =IF($A14="","",IF(AND($O14=1,ISNUMBER($G14)),IF($G14<Config!$B$4,1,0),0)) | Q14: =IF($A14="","",IF($P14=1,Config!$B$4-$G14,0)) | R14: =IF($A14="","",IF(AND(ISNUMBER($D14),ISNUMBER($E14)),$D14*$E14,"")) | S14: =IF(COUNTA($A14:$J14)=0,"",IF($A14="","Missing: PO ID",IF(COUNTIF($A$2:$A$301,$A14)>1,"Duplicate PO ID",IF($B14="","Missing: supplier",IF($C14="","Missing: SKU",IF(NOT(ISNUMBER($D14)),"Missing: qty",IF(NOT(ISNUMBER($F14)),"Missing: order date",IF(NOT(ISNUMBER($G14)),"Missing: expected date",IF($H14="","Missing: status",IF($I14="","Missing: source link",IF(COUNTIF(Suppliers!$A$2:$A$51,$B14)=0,"Unknown supplier",IF(COUNTIF(Products!$A$2:$A$101,$C14)=0,"Unknown SKU",IF(COUNTIF(Config!$C$15:$C$34,$H14)=0,"Unsupported status",IF($D14<=0,"Qty must be above 0",IF($G14<$F14,"Expected date before order date",IF($M14>$D14,"Received more than ordered",IF(AND($H14="Received",$M14<$D14),"Status Received but not fully received",IF(AND(IFERROR(INDEX(Config!$D$15:$D$34,MATCH($H14,Config!$C$15:$C$34,0)),"No")="Yes",$M14>=$D14),"Fully received: update status","OK")))))))))))))))))) | T14: =IF($O14=1,IFERROR(COUNTIFS($O$2:$O$301,1,$G$2:$G$301,"<"&$G14)+COUNTIFS($O$2:$O14,1,$G$2:$G14,$G14),""),"")
K15: =IF($A15="","",IFERROR(INDEX(Suppliers!$B$2:$B$51,MATCH($B15,Suppliers!$A$2:$A$51,0))&"","(not found)")) | L15: =IF($A15="","",IFERROR(INDEX(Products!$B$2:$B$101,MATCH($C15,Products!$A$2:$A$101,0))&"","(not found)")) | M15: =IF($A15="","",SUMIFS(Inventory_Ledger!$E$2:$E$2001,Inventory_Ledger!$H$2:$H$2001,$A15,Inventory_Ledger!$C$2:$C$2001,"Receipt",Inventory_Ledger!$D$2:$D$2001,$C15)) | N15: =IF($A15="","",IF(IFERROR(INDEX(Config!$D$15:$D$34,MATCH($H15,Config!$C$15:$C$34,0)),"No")="Yes",MAX(0,IF(ISNUMBER($D15),$D15,0)-$M15),0)) | O15: =IF($A15="","",IF($N15>0,1,0)) | P15: =IF($A15="","",IF(AND($O15=1,ISNUMBER($G15)),IF($G15<Config!$B$4,1,0),0)) | Q15: =IF($A15="","",IF($P15=1,Config!$B$4-$G15,0)) | R15: =IF($A15="","",IF(AND(ISNUMBER($D15),ISNUMBER($E15)),$D15*$E15,"")) | S15: =IF(COUNTA($A15:$J15)=0,"",IF($A15="","Missing: PO ID",IF(COUNTIF($A$2:$A$301,$A15)>1,"Duplicate PO ID",IF($B15="","Missing: supplier",IF($C15="","Missing: SKU",IF(NOT(ISNUMBER($D15)),"Missing: qty",IF(NOT(ISNUMBER($F15)),"Missing: order date",IF(NOT(ISNUMBER($G15)),"Missing: expected date",IF($H15="","Missing: status",IF($I15="","Missing: source link",IF(COUNTIF(Suppliers!$A$2:$A$51,$B15)=0,"Unknown supplier",IF(COUNTIF(Products!$A$2:$A$101,$C15)=0,"Unknown SKU",IF(COUNTIF(Config!$C$15:$C$34,$H15)=0,"Unsupported status",IF($D15<=0,"Qty must be above 0",IF($G15<$F15,"Expected date before order date",IF($M15>$D15,"Received more than ordered",IF(AND($H15="Received",$M15<$D15),"Status Received but not fully received",IF(AND(IFERROR(INDEX(Config!$D$15:$D$34,MATCH($H15,Config!$C$15:$C$34,0)),"No")="Yes",$M15>=$D15),"Fully received: update status","OK")))))))))))))))))) | T15: =IF($O15=1,IFERROR(COUNTIFS($O$2:$O$301,1,$G$2:$G$301,"<"&$G15)+COUNTIFS($O$2:$O15,1,$G$2:$G15,$G15),""),"")
K16: =IF($A16="","",IFERROR(INDEX(Suppliers!$B$2:$B$51,MATCH($B16,Suppliers!$A$2:$A$51,0))&"","(not found)")) | L16: =IF($A16="","",IFERROR(INDEX(Products!$B$2:$B$101,MATCH($C16,Products!$A$2:$A$101,0))&"","(not found)")) | M16: =IF($A16="","",SUMIFS(Inventory_Ledger!$E$2:$E$2001,Inventory_Ledger!$H$2:$H$2001,$A16,Inventory_Ledger!$C$2:$C$2001,"Receipt",Inventory_Ledger!$D$2:$D$2001,$C16)) | N16: =IF($A16="","",IF(IFERROR(INDEX(Config!$D$15:$D$34,MATCH($H16,Config!$C$15:$C$34,0)),"No")="Yes",MAX(0,IF(ISNUMBER($D16),$D16,0)-$M16),0)) | O16: =IF($A16="","",IF($N16>0,1,0)) | P16: =IF($A16="","",IF(AND($O16=1,ISNUMBER($G16)),IF($G16<Config!$B$4,1,0),0)) | Q16: =IF($A16="","",IF($P16=1,Config!$B$4-$G16,0)) | R16: =IF($A16="","",IF(AND(ISNUMBER($D16),ISNUMBER($E16)),$D16*$E16,"")) | S16: =IF(COUNTA($A16:$J16)=0,"",IF($A16="","Missing: PO ID",IF(COUNTIF($A$2:$A$301,$A16)>1,"Duplicate PO ID",IF($B16="","Missing: supplier",IF($C16="","Missing: SKU",IF(NOT(ISNUMBER($D16)),"Missing: qty",IF(NOT(ISNUMBER($F16)),"Missing: order date",IF(NOT(ISNUMBER($G16)),"Missing: expected date",IF($H16="","Missing: status",IF($I16="","Missing: source link",IF(COUNTIF(Suppliers!$A$2:$A$51,$B16)=0,"Unknown supplier",IF(COUNTIF(Products!$A$2:$A$101,$C16)=0,"Unknown SKU",IF(COUNTIF(Config!$C$15:$C$34,$H16)=0,"Unsupported status",IF($D16<=0,"Qty must be above 0",IF($G16<$F16,"Expected date before order date",IF($M16>$D16,"Received more than ordered",IF(AND($H16="Received",$M16<$D16),"Status Received but not fully received",IF(AND(IFERROR(INDEX(Config!$D$15:$D$34,MATCH($H16,Config!$C$15:$C$34,0)),"No")="Yes",$M16>=$D16),"Fully received: update status","OK")))))))))))))))))) | T16: =IF($O16=1,IFERROR(COUNTIFS($O$2:$O$301,1,$G$2:$G$301,"<"&$G16)+COUNTIFS($O$2:$O16,1,$G$2:$G16,$G16),""),"")
K17: =IF($A17="","",IFERROR(INDEX(Suppliers!$B$2:$B$51,MATCH($B17,Suppliers!$A$2:$A$51,0))&"","(not found)")) | L17: =IF($A17="","",IFERROR(INDEX(Products!$B$2:$B$101,MATCH($C17,Products!$A$2:$A$101,0))&"","(not found)")) | M17: =IF($A17="","",SUMIFS(Inventory_Ledger!$E$2:$E$2001,Inventory_Ledger!$H$2:$H$2001,$A17,Inventory_Ledger!$C$2:$C$2001,"Receipt",Inventory_Ledger!$D$2:$D$2001,$C17)) | N17: =IF($A17="","",IF(IFERROR(INDEX(Config!$D$15:$D$34,MATCH($H17,Config!$C$15:$C$34,0)),"No")="Yes",MAX(0,IF(ISNUMBER($D17),$D17,0)-$M17),0)) | O17: =IF($A17="","",IF($N17>0,1,0)) | P17: =IF($A17="","",IF(AND($O17=1,ISNUMBER($G17)),IF($G17<Config!$B$4,1,0),0)) | Q17: =IF($A17="","",IF($P17=1,Config!$B$4-$G17,0)) | R17: =IF($A17="","",IF(AND(ISNUMBER($D17),ISNUMBER($E17)),$D17*$E17,"")) | S17: =IF(COUNTA($A17:$J17)=0,"",IF($A17="","Missing: PO ID",IF(COUNTIF($A$2:$A$301,$A17)>1,"Duplicate PO ID",IF($B17="","Missing: supplier",IF($C17="","Missing: SKU",IF(NOT(ISNUMBER($D17)),"Missing: qty",IF(NOT(ISNUMBER($F17)),"Missing: order date",IF(NOT(ISNUMBER($G17)),"Missing: expected date",IF($H17="","Missing: status",IF($I17="","Missing: source link",IF(COUNTIF(Suppliers!$A$2:$A$51,$B17)=0,"Unknown supplier",IF(COUNTIF(Products!$A$2:$A$101,$C17)=0,"Unknown SKU",IF(COUNTIF(Config!$C$15:$C$34,$H17)=0,"Unsupported status",IF($D17<=0,"Qty must be above 0",IF($G17<$F17,"Expected date before order date",IF($M17>$D17,"Received more than ordered",IF(AND($H17="Received",$M17<$D17),"Status Received but not fully received",IF(AND(IFERROR(INDEX(Config!$D$15:$D$34,MATCH($H17,Config!$C$15:$C$34,0)),"No")="Yes",$M17>=$D17),"Fully received: update status","OK")))))))))))))))))) | T17: =IF($O17=1,IFERROR(COUNTIFS($O$2:$O$301,1,$G$2:$G$301,"<"&$G17)+COUNTIFS($O$2:$O17,1,$G$2:$G17,$G17),""),"")
K18: =IF($A18="","",IFERROR(INDEX(Suppliers!$B$2:$B$51,MATCH($B18,Suppliers!$A$2:$A$51,0))&"","(not found)")) | L18: =IF($A18="","",IFERROR(INDEX(Products!$B$2:$B$101,MATCH($C18,Products!$A$2:$A$101,0))&"","(not found)")) | M18: =IF($A18="","",SUMIFS(Inventory_Ledger!$E$2:$E$2001,Inventory_Ledger!$H$2:$H$2001,$A18,Inventory_Ledger!$C$2:$C$2001,"Receipt",Inventory_Ledger!$D$2:$D$2001,$C18)) | N18: =IF($A18="","",IF(IFERROR(INDEX(Config!$D$15:$D$34,MATCH($H18,Config!$C$15:$C$34,0)),"No")="Yes",MAX(0,IF(ISNUMBER($D18),$D18,0)-$M18),0)) | O18: =IF($A18="","",IF($N18>0,1,0)) | P18: =IF($A18="","",IF(AND($O18=1,ISNUMBER($G18)),IF($G18<Config!$B$4,1,0),0)) | Q18: =IF($A18="","",IF($P18=1,Config!$B$4-$G18,0)) | R18: =IF($A18="","",IF(AND(ISNUMBER($D18),ISNUMBER($E18)),$D18*$E18,"")) | S18: =IF(COUNTA($A18:$J18)=0,"",IF($A18="","Missing: PO ID",IF(COUNTIF($A$2:$A$301,$A18)>1,"Duplicate PO ID",IF($B18="","Missing: supplier",IF($C18="","Missing: SKU",IF(NOT(ISNUMBER($D18)),"Missing: qty",IF(NOT(ISNUMBER($F18)),"Missing: order date",IF(NOT(ISNUMBER($G18)),"Missing: expected date",IF($H18="","Missing: status",IF($I18="","Missing: source link",IF(COUNTIF(Suppliers!$A$2:$A$51,$B18)=0,"Unknown supplier",IF(COUNTIF(Products!$A$2:$A$101,$C18)=0,"Unknown SKU",IF(COUNTIF(Config!$C$15:$C$34,$H18)=0,"Unsupported status",IF($D18<=0,"Qty must be above 0",IF($G18<$F18,"Expected date before order date",IF($M18>$D18,"Received more than ordered",IF(AND($H18="Received",$M18<$D18),"Status Received but not fully received",IF(AND(IFERROR(INDEX(Config!$D$15:$D$34,MATCH($H18,Config!$C$15:$C$34,0)),"No")="Yes",$M18>=$D18),"Fully received: update status","OK")))))))))))))))))) | T18: =IF($O18=1,IFERROR(COUNTIFS($O$2:$O$301,1,$G$2:$G$301,"<"&$G18)+COUNTIFS($O$2:$O18,1,$G$2:$G18,$G18),""),"")
K19: =IF($A19="","",IFERROR(INDEX(Suppliers!$B$2:$B$51,MATCH($B19,Suppliers!$A$2:$A$51,0))&"","(not found)")) | L19: =IF($A19="","",IFERROR(INDEX(Products!$B$2:$B$101,MATCH($C19,Products!$A$2:$A$101,0))&"","(not found)")) | M19: =IF($A19="","",SUMIFS(Inventory_Ledger!$E$2:$E$2001,Inventory_Ledger!$H$2:$H$2001,$A19,Inventory_Ledger!$C$2:$C$2001,"Receipt",Inventory_Ledger!$D$2:$D$2001,$C19)) | N19: =IF($A19="","",IF(IFERROR(INDEX(Config!$D$15:$D$34,MATCH($H19,Config!$C$15:$C$34,0)),"No")="Yes",MAX(0,IF(ISNUMBER($D19),$D19,0)-$M19),0)) | O19: =IF($A19="","",IF($N19>0,1,0)) | P19: =IF($A19="","",IF(AND($O19=1,ISNUMBER($G19)),IF($G19<Config!$B$4,1,0),0)) | Q19: =IF($A19="","",IF($P19=1,Config!$B$4-$G19,0)) | R19: =IF($A19="","",IF(AND(ISNUMBER($D19),ISNUMBER($E19)),$D19*$E19,"")) | S19: =IF(COUNTA($A19:$J19)=0,"",IF($A19="","Missing: PO ID",IF(COUNTIF($A$2:$A$301,$A19)>1,"Duplicate PO ID",IF($B19="","Missing: supplier",IF($C19="","Missing: SKU",IF(NOT(ISNUMBER($D19)),"Missing: qty",IF(NOT(ISNUMBER($F19)),"Missing: order date",IF(NOT(ISNUMBER($G19)),"Missing: expected date",IF($H19="","Missing: status",IF($I19="","Missing: source link",IF(COUNTIF(Suppliers!$A$2:$A$51,$B19)=0,"Unknown supplier",IF(COUNTIF(Products!$A$2:$A$101,$C19)=0,"Unknown SKU",IF(COUNTIF(Config!$C$15:$C$34,$H19)=0,"Unsupported status",IF($D19<=0,"Qty must be above 0",IF($G19<$F19,"Expected date before order date",IF($M19>$D19,"Received more than ordered",IF(AND($H19="Received",$M19<$D19),"Status Received but not fully received",IF(AND(IFERROR(INDEX(Config!$D$15:$D$34,MATCH($H19,Config!$C$15:$C$34,0)),"No")="Yes",$M19>=$D19),"Fully received: update status","OK")))))))))))))))))) | T19: =IF($O19=1,IFERROR(COUNTIFS($O$2:$O$301,1,$G$2:$G$301,"<"&$G19)+COUNTIFS($O$2:$O19,1,$G$2:$G19,$G19),""),"")
K20: =IF($A20="","",IFERROR(INDEX(Suppliers!$B$2:$B$51,MATCH($B20,Suppliers!$A$2:$A$51,0))&"","(not found)")) | L20: =IF($A20="","",IFERROR(INDEX(Products!$B$2:$B$101,MATCH($C20,Products!$A$2:$A$101,0))&"","(not found)")) | M20: =IF($A20="","",SUMIFS(Inventory_Ledger!$E$2:$E$2001,Inventory_Ledger!$H$2:$H$2001,$A20,Inventory_Ledger!$C$2:$C$2001,"Receipt",Inventory_Ledger!$D$2:$D$2001,$C20)) | N20: =IF($A20="","",IF(IFERROR(INDEX(Config!$D$15:$D$34,MATCH($H20,Config!$C$15:$C$34,0)),"No")="Yes",MAX(0,IF(ISNUMBER($D20),$D20,0)-$M20),0)) | O20: =IF($A20="","",IF($N20>0,1,0)) | P20: =IF($A20="","",IF(AND($O20=1,ISNUMBER($G20)),IF($G20<Config!$B$4,1,0),0)) | Q20: =IF($A20="","",IF($P20=1,Config!$B$4-$G20,0)) | R20: =IF($A20="","",IF(AND(ISNUMBER($D20),ISNUMBER($E20)),$D20*$E20,"")) | S20: =IF(COUNTA($A20:$J20)=0,"",IF($A20="","Missing: PO ID",IF(COUNTIF($A$2:$A$301,$A20)>1,"Duplicate PO ID",IF($B20="","Missing: supplier",IF($C20="","Missing: SKU",IF(NOT(ISNUMBER($D20)),"Missing: qty",IF(NOT(ISNUMBER($F20)),"Missing: order date",IF(NOT(ISNUMBER($G20)),"Missing: expected date",IF($H20="","Missing: status",IF($I20="","Missing: source link",IF(COUNTIF(Suppliers!$A$2:$A$51,$B20)=0,"Unknown supplier",IF(COUNTIF(Products!$A$2:$A$101,$C20)=0,"Unknown SKU",IF(COUNTIF(Config!$C$15:$C$34,$H20)=0,"Unsupported status",IF($D20<=0,"Qty must be above 0",IF($G20<$F20,"Expected date before order date",IF($M20>$D20,"Received more than ordered",IF(AND($H20="Received",$M20<$D20),"Status Received but not fully received",IF(AND(IFERROR(INDEX(Config!$D$15:$D$34,MATCH($H20,Config!$C$15:$C$34,0)),"No")="Yes",$M20>=$D20),"Fully received: update status","OK")))))))))))))))))) | T20: =IF($O20=1,IFERROR(COUNTIFS($O$2:$O$301,1,$G$2:$G$301,"<"&$G20)+COUNTIFS($O$2:$O20,1,$G$2:$G20,$G20),""),"")
K21: =IF($A21="","",IFERROR(INDEX(Suppliers!$B$2:$B$51,MATCH($B21,Suppliers!$A$2:$A$51,0))&"","(not found)")) | L21: =IF($A21="","",IFERROR(INDEX(Products!$B$2:$B$101,MATCH($C21,Products!$A$2:$A$101,0))&"","(not found)")) | M21: =IF($A21="","",SUMIFS(Inventory_Ledger!$E$2:$E$2001,Inventory_Ledger!$H$2:$H$2001,$A21,Inventory_Ledger!$C$2:$C$2001,"Receipt",Inventory_Ledger!$D$2:$D$2001,$C21)) | N21: =IF($A21="","",IF(IFERROR(INDEX(Config!$D$15:$D$34,MATCH($H21,Config!$C$15:$C$34,0)),"No")="Yes",MAX(0,IF(ISNUMBER($D21),$D21,0)-$M21),0)) | O21: =IF($A21="","",IF($N21>0,1,0)) | P21: =IF($A21="","",IF(AND($O21=1,ISNUMBER($G21)),IF($G21<Config!$B$4,1,0),0)) | Q21: =IF($A21="","",IF($P21=1,Config!$B$4-$G21,0)) | R21: =IF($A21="","",IF(AND(ISNUMBER($D21),ISNUMBER($E21)),$D21*$E21,"")) | S21: =IF(COUNTA($A21:$J21)=0,"",IF($A21="","Missing: PO ID",IF(COUNTIF($A$2:$A$301,$A21)>1,"Duplicate PO ID",IF($B21="","Missing: supplier",IF($C21="","Missing: SKU",IF(NOT(ISNUMBER($D21)),"Missing: qty",IF(NOT(ISNUMBER($F21)),"Missing: order date",IF(NOT(ISNUMBER($G21)),"Missing: expected date",IF($H21="","Missing: status",IF($I21="","Missing: source link",IF(COUNTIF(Suppliers!$A$2:$A$51,$B21)=0,"Unknown supplier",IF(COUNTIF(Products!$A$2:$A$101,$C21)=0,"Unknown SKU",IF(COUNTIF(Config!$C$15:$C$34,$H21)=0,"Unsupported status",IF($D21<=0,"Qty must be above 0",IF($G21<$F21,"Expected date before order date",IF($M21>$D21,"Received more than ordered",IF(AND($H21="Received",$M21<$D21),"Status Received but not fully received",IF(AND(IFERROR(INDEX(Config!$D$15:$D$34,MATCH($H21,Config!$C$15:$C$34,0)),"No")="Yes",$M21>=$D21),"Fully received: update status","OK")))))))))))))))))) | T21: =IF($O21=1,IFERROR(COUNTIFS($O$2:$O$301,1,$G$2:$G$301,"<"&$G21)+COUNTIFS($O$2:$O21,1,$G$2:$G21,$G21),""),"")
K22: =IF($A22="","",IFERROR(INDEX(Suppliers!$B$2:$B$51,MATCH($B22,Suppliers!$A$2:$A$51,0))&"","(not found)")) | L22: =IF($A22="","",IFERROR(INDEX(Products!$B$2:$B$101,MATCH($C22,Products!$A$2:$A$101,0))&"","(not found)")) | M22: =IF($A22="","",SUMIFS(Inventory_Ledger!$E$2:$E$2001,Inventory_Ledger!$H$2:$H$2001,$A22,Inventory_Ledger!$C$2:$C$2001,"Receipt",Inventory_Ledger!$D$2:$D$2001,$C22)) | N22: =IF($A22="","",IF(IFERROR(INDEX(Config!$D$15:$D$34,MATCH($H22,Config!$C$15:$C$34,0)),"No")="Yes",MAX(0,IF(ISNUMBER($D22),$D22,0)-$M22),0)) | O22: =IF($A22="","",IF($N22>0,1,0)) | P22: =IF($A22="","",IF(AND($O22=1,ISNUMBER($G22)),IF($G22<Config!$B$4,1,0),0)) | Q22: =IF($A22="","",IF($P22=1,Config!$B$4-$G22,0)) | R22: =IF($A22="","",IF(AND(ISNUMBER($D22),ISNUMBER($E22)),$D22*$E22,"")) | S22: =IF(COUNTA($A22:$J22)=0,"",IF($A22="","Missing: PO ID",IF(COUNTIF($A$2:$A$301,$A22)>1,"Duplicate PO ID",IF($B22="","Missing: supplier",IF($C22="","Missing: SKU",IF(NOT(ISNUMBER($D22)),"Missing: qty",IF(NOT(ISNUMBER($F22)),"Missing: order date",IF(NOT(ISNUMBER($G22)),"Missing: expected date",IF($H22="","Missing: status",IF($I22="","Missing: source link",IF(COUNTIF(Suppliers!$A$2:$A$51,$B22)=0,"Unknown supplier",IF(COUNTIF(Products!$A$2:$A$101,$C22)=0,"Unknown SKU",IF(COUNTIF(Config!$C$15:$C$34,$H22)=0,"Unsupported status",IF($D22<=0,"Qty must be above 0",IF($G22<$F22,"Expected date before order date",IF($M22>$D22,"Received more than ordered",IF(AND($H22="Received",$M22<$D22),"Status Received but not fully received",IF(AND(IFERROR(INDEX(Config!$D$15:$D$34,MATCH($H22,Config!$C$15:$C$34,0)),"No")="Yes",$M22>=$D22),"Fully received: update status","OK")))))))))))))))))) | T22: =IF($O22=1,IFERROR(COUNTIFS($O$2:$O$301,1,$G$2:$G$301,"<"&$G22)+COUNTIFS($O$2:$O22,1,$G$2:$G22,$G22),""),"")
K23: =IF($A23="","",IFERROR(INDEX(Suppliers!$B$2:$B$51,MATCH($B23,Suppliers!$A$2:$A$51,0))&"","(not found)")) | L23: =IF($A23="","",IFERROR(INDEX(Products!$B$2:$B$101,MATCH($C23,Products!$A$2:$A$101,0))&"","(not found)")) | M23: =IF($A23="","",SUMIFS(Inventory_Ledger!$E$2:$E$2001,Inventory_Ledger!$H$2:$H$2001,$A23,Inventory_Ledger!$C$2:$C$2001,"Receipt",Inventory_Ledger!$D$2:$D$2001,$C23)) | N23: =IF($A23="","",IF(IFERROR(INDEX(Config!$D$15:$D$34,MATCH($H23,Config!$C$15:$C$34,0)),"No")="Yes",MAX(0,IF(ISNUMBER($D23),$D23,0)-$M23),0)) | O23: =IF($A23="","",IF($N23>0,1,0)) | P23: =IF($A23="","",IF(AND($O23=1,ISNUMBER($G23)),IF($G23<Config!$B$4,1,0),0)) | Q23: =IF($A23="","",IF($P23=1,Config!$B$4-$G23,0)) | R23: =IF($A23="","",IF(AND(ISNUMBER($D23),ISNUMBER($E23)),$D23*$E23,"")) | S23: =IF(COUNTA($A23:$J23)=0,"",IF($A23="","Missing: PO ID",IF(COUNTIF($A$2:$A$301,$A23)>1,"Duplicate PO ID",IF($B23="","Missing: supplier",IF($C23="","Missing: SKU",IF(NOT(ISNUMBER($D23)),"Missing: qty",IF(NOT(ISNUMBER($F23)),"Missing: order date",IF(NOT(ISNUMBER($G23)),"Missing: expected date",IF($H23="","Missing: status",IF($I23="","Missing: source link",IF(COUNTIF(Suppliers!$A$2:$A$51,$B23)=0,"Unknown supplier",IF(COUNTIF(Products!$A$2:$A$101,$C23)=0,"Unknown SKU",IF(COUNTIF(Config!$C$15:$C$34,$H23)=0,"Unsupported status",IF($D23<=0,"Qty must be above 0",IF($G23<$F23,"Expected date before order date",IF($M23>$D23,"Received more than ordered",IF(AND($H23="Received",$M23<$D23),"Status Received but not fully received",IF(AND(IFERROR(INDEX(Config!$D$15:$D$34,MATCH($H23,Config!$C$15:$C$34,0)),"No")="Yes",$M23>=$D23),"Fully received: update status","OK")))))))))))))))))) | T23: =IF($O23=1,IFERROR(COUNTIFS($O$2:$O$301,1,$G$2:$G$301,"<"&$G23)+COUNTIFS($O$2:$O23,1,$G$2:$G23,$G23),""),"")
K24: =IF($A24="","",IFERROR(INDEX(Suppliers!$B$2:$B$51,MATCH($B24,Suppliers!$A$2:$A$51,0))&"","(not found)")) | L24: =IF($A24="","",IFERROR(INDEX(Products!$B$2:$B$101,MATCH($C24,Products!$A$2:$A$101,0))&"","(not found)")) | M24: =IF($A24="","",SUMIFS(Inventory_Ledger!$E$2:$E$2001,Inventory_Ledger!$H$2:$H$2001,$A24,Inventory_Ledger!$C$2:$C$2001,"Receipt",Inventory_Ledger!$D$2:$D$2001,$C24)) | N24: =IF($A24="","",IF(IFERROR(INDEX(Config!$D$15:$D$34,MATCH($H24,Config!$C$15:$C$34,0)),"No")="Yes",MAX(0,IF(ISNUMBER($D24),$D24,0)-$M24),0)) | O24: =IF($A24="","",IF($N24>0,1,0)) | P24: =IF($A24="","",IF(AND($O24=1,ISNUMBER($G24)),IF($G24<Config!$B$4,1,0),0)) | Q24: =IF($A24="","",IF($P24=1,Config!$B$4-$G24,0)) | R24: =IF($A24="","",IF(AND(ISNUMBER($D24),ISNUMBER($E24)),$D24*$E24,"")) | S24: =IF(COUNTA($A24:$J24)=0,"",IF($A24="","Missing: PO ID",IF(COUNTIF($A$2:$A$301,$A24)>1,"Duplicate PO ID",IF($B24="","Missing: supplier",IF($C24="","Missing: SKU",IF(NOT(ISNUMBER($D24)),"Missing: qty",IF(NOT(ISNUMBER($F24)),"Missing: order date",IF(NOT(ISNUMBER($G24)),"Missing: expected date",IF($H24="","Missing: status",IF($I24="","Missing: source link",IF(COUNTIF(Suppliers!$A$2:$A$51,$B24)=0,"Unknown supplier",IF(COUNTIF(Products!$A$2:$A$101,$C24)=0,"Unknown SKU",IF(COUNTIF(Config!$C$15:$C$34,$H24)=0,"Unsupported status",IF($D24<=0,"Qty must be above 0",IF($G24<$F24,"Expected date before order date",IF($M24>$D24,"Received more than ordered",IF(AND($H24="Received",$M24<$D24),"Status Received but not fully received",IF(AND(IFERROR(INDEX(Config!$D$15:$D$34,MATCH($H24,Config!$C$15:$C$34,0)),"No")="Yes",$M24>=$D24),"Fully received: update status","OK")))))))))))))))))) | T24: =IF($O24=1,IFERROR(COUNTIFS($O$2:$O$301,1,$G$2:$G$301,"<"&$G24)+COUNTIFS($O$2:$O24,1,$G$2:$G24,$G24),""),"")
K25: =IF($A25="","",IFERROR(INDEX(Suppliers!$B$2:$B$51,MATCH($B25,Suppliers!$A$2:$A$51,0))&"","(not found)")) | L25: =IF($A25="","",IFERROR(INDEX(Products!$B$2:$B$101,MATCH($C25,Products!$A$2:$A$101,0))&"","(not found)")) | M25: =IF($A25="","",SUMIFS(Inventory_Ledger!$E$2:$E$2001,Inventory_Ledger!$H$2:$H$2001,$A25,Inventory_Ledger!$C$2:$C$2001,"Receipt",Inventory_Ledger!$D$2:$D$2001,$C25)) | N25: =IF($A25="","",IF(IFERROR(INDEX(Config!$D$15:$D$34,MATCH($H25,Config!$C$15:$C$34,0)),"No")="Yes",MAX(0,IF(ISNUMBER($D25),$D25,0)-$M25),0)) | O25: =IF($A25="","",IF($N25>0,1,0)) | P25: =IF($A25="","",IF(AND($O25=1,ISNUMBER($G25)),IF($G25<Config!$B$4,1,0),0)) | Q25: =IF($A25="","",IF($P25=1,Config!$B$4-$G25,0)) | R25: =IF($A25="","",IF(AND(ISNUMBER($D25),ISNUMBER($E25)),$D25*$E25,"")) | S25: =IF(COUNTA($A25:$J25)=0,"",IF($A25="","Missing: PO ID",IF(COUNTIF($A$2:$A$301,$A25)>1,"Duplicate PO ID",IF($B25="","Missing: supplier",IF($C25="","Missing: SKU",IF(NOT(ISNUMBER($D25)),"Missing: qty",IF(NOT(ISNUMBER($F25)),"Missing: order date",IF(NOT(ISNUMBER($G25)),"Missing: expected date",IF($H25="","Missing: status",IF($I25="","Missing: source link",IF(COUNTIF(Suppliers!$A$2:$A$51,$B25)=0,"Unknown supplier",IF(COUNTIF(Products!$A$2:$A$101,$C25)=0,"Unknown SKU",IF(COUNTIF(Config!$C$15:$C$34,$H25)=0,"Unsupported status",IF($D25<=0,"Qty must be above 0",IF($G25<$F25,"Expected date before order date",IF($M25>$D25,"Received more than ordered",IF(AND($H25="Received",$M25<$D25),"Status Received but not fully received",IF(AND(IFERROR(INDEX(Config!$D$15:$D$34,MATCH($H25,Config!$C$15:$C$34,0)),"No")="Yes",$M25>=$D25),"Fully received: update status","OK")))))))))))))))))) | T25: =IF($O25=1,IFERROR(COUNTIFS($O$2:$O$301,1,$G$2:$G$301,"<"&$G25)+COUNTIFS($O$2:$O25,1,$G$2:$G25,$G25),""),"")
... K301: =IF($A301="","",IFERROR(INDEX(Suppliers!$B$2:$B$51,MATCH($B301,Suppliers!$A$2:$A$51,0))&"","(not found)")) | L301: =IF($A301="","",IFERROR(INDEX(Products!$B$2:$B$101,MATCH($C301,Products!$A$2:$A$101,0))&"","(not found)")) | M301: =IF($A301="","",SUMIFS(Inventory_Ledger!$E$2:$E$2001,Inventory_Ledger!$H$2:$H$2001,$A301,Inventory_Ledger!$C$2:$C$2001,"Receipt",Inventory_Ledger!$D$2:$D$2001,$C301)) | N301: =IF($A301="","",IF(IFERROR(INDEX(Config!$D$15:$D$34,MATCH($H301,Config!$C$15:$C$34,0)),"No")="Yes",MAX(0,IF(ISNUMBER($D301),$D301,0)-$M301),0)) | O301: =IF($A301="","",IF($N301>0,1,0)) | P301: =IF($A301="","",IF(AND($O301=1,ISNUMBER($G301)),IF($G301<Config!$B$4,1,0),0)) | Q301: =IF($A301="","",IF($P301=1,Config!$B$4-$G301,0)) | R301: =IF($A301="","",IF(AND(ISNUMBER($D301),ISNUMBER($E301)),$D301*$E301,"")) | S301: =IF(COUNTA($A301:$J301)=0,"",IF($A301="","Missing: PO ID",IF(COUNTIF($A$2:$A$301,$A301)>1,"Duplicate PO ID",IF($B301="","Missing: supplier",IF($C301="","Missing: SKU",IF(NOT(ISNUMBER($D301)),"Missing: qty",IF(NOT(ISNUMBER($F301)),"Missing: order date",IF(NOT(ISNUMBER($G301)),"Missing: expected date",IF($H301="","Missing: status",IF($I301="","Missing: source link",IF(COUNTIF(Suppliers!$A$2:$A$51,$B301)=0,"Unknown supplier",IF(COUNTIF(Products!$A$2:$A$101,$C301)=0,"Unknown SKU",IF(COUNTIF(Config!$C$15:$C$34,$H301)=0,"Unsupported status",IF($D301<=0,"Qty must be above 0",IF($G301<$F301,"Expected date before order date",IF($M301>$D301,"Received more than ordered",IF(AND($H301="Received",$M301<$D301),"Status Received but not fully received",IF(AND(IFERROR(INDEX(Config!$D$15:$D$34,MATCH($H301,Config!$C$15:$C$34,0)),"No")="Yes",$M301>=$D301),"Fully received: update status","OK")))))))))))))))))) | T301: =IF($O301=1,IFERROR(COUNTIFS($O$2:$O$301,1,$G$2:$G$301,"<"&$G301)+COUNTIFS($O$2:$O301,1,$G$2:$G301,$G301),""),"")

Sheet Inventory_Ledger
A1: Entry ID * | B1: Date * | C1: Type * | D1: SKU * | E1: Qty * | F1: Lot * | G1: Reason (adjustments) | H1: Reference | I1: Source link * | J1: Entered by | K1: Import batch | L1: Notes | M1: Signed qty | N1: Product name | O1: Lot belongs to | P1: Record check
A2: ADJ-2607-001 | B2: 46221 | C2: Adjustment | D2: WPI-CHO-2LB | E2: -6 | F2: WCH2502A | G2: Damaged in warehouse | H2: CC-0718 | I2: https://example.com/ops/adjustments/ADJ-2607-001 | J2: Ben Okafor | L2: Six tubs crushed on a pallet | M2: =IF(NOT(ISNUMBER($E2)),"",IF($C2="Receipt",$E2,IF($C2="Shipment",-$E2,IF($C2="Adjustment",$E2,0)))) -> -6 | N2: =IF($D2="","",IFERROR(INDEX(Products!$B$2:$B$101,MATCH($D2,Products!$A$2:$A$101,0))&"","(not found)")) -> Whey Protein Isolate, Chocolate, 2 lb | O2: =IF($F2="","",IFERROR(INDEX(Batches!$B$2:$B$301,MATCH($F2,Batches!$A$2:$A$301,0))&"","(not found)")) -> WPI-CHO-2LB | P2: =IF(COUNTA($A2:$L2)=0,"",IF($A2="","Missing: entry ID",IF(COUNTIF($A$2:$A$2001,$A2)>1,"Duplicate entry ID",IF(NOT(ISNUMBER($B2)),"Missing or invalid: date",IF($C2="","Missing: type",IF($D2="","Missing: SKU",IF(NOT(ISNUMBER($E2)),"Missing: qty",IF($F2="","Missing: lot",IF($I2="","Missing: source link",IF(COUNTIF(Config!$A$15:$A$34,$C2)=0,"Unsupported type",IF(COUNTIF(Products!$A$2:$A$101,$D2)=0,"Unknown SKU",IF(COUNTIFS(Batches!$A$2:$A$301,$F2,Batches!$B$2:$B$301,$D2)=0,"Unknown lot for this SKU",IF(AND($C2="Adjustment",$G2=""),"Missing: reason",IF(AND($G2<>"",COUNTIF(Config!$B$15:$B$34,$G2)=0),"Unsupported reason",IF(OR(INT($E2)<>$E2,AND(OR($C2="Receipt",$C2="Shipment"),$E2<=0),AND($C2="Adjustment",$E2=0)),"Invalid qty",IF($B2>Config!$B$4,"Date after the as-of date",IF($B2<Config!$B$5,"Date before the opening balance date","OK"))))))))))))))))) -> OK
A3: MV-2607-001 | B3: 46227 | C3: Receipt | D3: WPI-CHO-2LB | E3: 1500 | F3: WCH2607A | H3: PO-2026-018 | I3: https://example.com/3pl/receiving/PO-2026-018 | J3: 3PL import | K3: warehouse-movements-2026-07.csv | L3: Received against PO-2026-018 | M3: =IF(NOT(ISNUMBER($E3)),"",IF($C3="Receipt",$E3,IF($C3="Shipment",-$E3,IF($C3="Adjustment",$E3,0)))) -> 1500 | N3: =IF($D3="","",IFERROR(INDEX(Products!$B$2:$B$101,MATCH($D3,Products!$A$2:$A$101,0))&"","(not found)")) -> Whey Protein Isolate, Chocolate, 2 lb | O3: =IF($F3="","",IFERROR(INDEX(Batches!$B$2:$B$301,MATCH($F3,Batches!$A$2:$A$301,0))&"","(not found)")) -> WPI-CHO-2LB | P3: =IF(COUNTA($A3:$L3)=0,"",IF($A3="","Missing: entry ID",IF(COUNTIF($A$2:$A$2001,$A3)>1,"Duplicate entry ID",IF(NOT(ISNUMBER($B3)),"Missing or invalid: date",IF($C3="","Missing: type",IF($D3="","Missing: SKU",IF(NOT(ISNUMBER($E3)),"Missing: qty",IF($F3="","Missing: lot",IF($I3="","Missing: source link",IF(COUNTIF(Config!$A$15:$A$34,$C3)=0,"Unsupported type",IF(COUNTIF(Products!$A$2:$A$101,$D3)=0,"Unknown SKU",IF(COUNTIFS(Batches!$A$2:$A$301,$F3,Batches!$B$2:$B$301,$D3)=0,"Unknown lot for this SKU",IF(AND($C3="Adjustment",$G3=""),"Missing: reason",IF(AND($G3<>"",COUNTIF(Config!$B$15:$B$34,$G3)=0),"Unsupported reason",IF(OR(INT($E3)<>$E3,AND(OR($C3="Receipt",$C3="Shipment"),$E3<=0),AND($C3="Adjustment",$E3=0)),"Invalid qty",IF($B3>Config!$B$4,"Date after the as-of date",IF($B3<Config!$B$5,"Date before the opening balance date","OK"))))))))))))))))) -> OK
A4: MV-2607-002 | B4: 46234 | C4: Shipment | D4: WPI-CHO-2LB | E4: 534 | F4: WCH2502A | H4: OB-2607 | I4: https://example.com/3pl/outbound/2026-07 | J4: 3PL import | K4: warehouse-movements-2026-07.csv | L4: July outbound summary (FEFO) | M4: =IF(NOT(ISNUMBER($E4)),"",IF($C4="Receipt",$E4,IF($C4="Shipment",-$E4,IF($C4="Adjustment",$E4,0)))) -> -534 | N4: =IF($D4="","",IFERROR(INDEX(Products!$B$2:$B$101,MATCH($D4,Products!$A$2:$A$101,0))&"","(not found)")) -> Whey Protein Isolate, Chocolate, 2 lb | O4: =IF($F4="","",IFERROR(INDEX(Batches!$B$2:$B$301,MATCH($F4,Batches!$A$2:$A$301,0))&"","(not found)")) -> WPI-CHO-2LB | P4: =IF(COUNTA($A4:$L4)=0,"",IF($A4="","Missing: entry ID",IF(COUNTIF($A$2:$A$2001,$A4)>1,"Duplicate entry ID",IF(NOT(ISNUMBER($B4)),"Missing or invalid: date",IF($C4="","Missing: type",IF($D4="","Missing: SKU",IF(NOT(ISNUMBER($E4)),"Missing: qty",IF($F4="","Missing: lot",IF($I4="","Missing: source link",IF(COUNTIF(Config!$A$15:$A$34,$C4)=0,"Unsupported type",IF(COUNTIF(Products!$A$2:$A$101,$D4)=0,"Unknown SKU",IF(COUNTIFS(Batches!$A$2:$A$301,$F4,Batches!$B$2:$B$301,$D4)=0,"Unknown lot for this SKU",IF(AND($C4="Adjustment",$G4=""),"Missing: reason",IF(AND($G4<>"",COUNTIF(Config!$B$15:$B$34,$G4)=0),"Unsupported reason",IF(OR(INT($E4)<>$E4,AND(OR($C4="Receipt",$C4="Shipment"),$E4<=0),AND($C4="Adjustment",$E4=0)),"Invalid qty",IF($B4>Config!$B$4,"Date after the as-of date",IF($B4<Config!$B$5,"Date before the opening balance date","OK"))))))))))))))))) -> OK
A5: MV-2607-003 | B5: 46234 | C5: Shipment | D5: WPI-CHO-2LB | E5: 224 | F5: WCH2504A | H5: OB-2607 | I5: https://example.com/3pl/outbound/2026-07 | J5: 3PL import | K5: warehouse-movements-2026-07.csv | L5: July outbound summary (FEFO) | M5: =IF(NOT(ISNUMBER($E5)),"",IF($C5="Receipt",$E5,IF($C5="Shipment",-$E5,IF($C5="Adjustment",$E5,0)))) -> -224 | N5: =IF($D5="","",IFERROR(INDEX(Products!$B$2:$B$101,MATCH($D5,Products!$A$2:$A$101,0))&"","(not found)")) -> Whey Protein Isolate, Chocolate, 2 lb | O5: =IF($F5="","",IFERROR(INDEX(Batches!$B$2:$B$301,MATCH($F5,Batches!$A$2:$A$301,0))&"","(not found)")) -> WPI-CHO-2LB | P5: =IF(COUNTA($A5:$L5)=0,"",IF($A5="","Missing: entry ID",IF(COUNTIF($A$2:$A$2001,$A5)>1,"Duplicate entry ID",IF(NOT(ISNUMBER($B5)),"Missing or invalid: date",IF($C5="","Missing: type",IF($D5="","Missing: SKU",IF(NOT(ISNUMBER($E5)),"Missing: qty",IF($F5="","Missing: lot",IF($I5="","Missing: source link",IF(COUNTIF(Config!$A$15:$A$34,$C5)=0,"Unsupported type",IF(COUNTIF(Products!$A$2:$A$101,$D5)=0,"Unknown SKU",IF(COUNTIFS(Batches!$A$2:$A$301,$F5,Batches!$B$2:$B$301,$D5)=0,"Unknown lot for this SKU",IF(AND($C5="Adjustment",$G5=""),"Missing: reason",IF(AND($G5<>"",COUNTIF(Config!$B$15:$B$34,$G5)=0),"Unsupported reason",IF(OR(INT($E5)<>$E5,AND(OR($C5="Receipt",$C5="Shipment"),$E5<=0),AND($C5="Adjustment",$E5=0)),"Invalid qty",IF($B5>Config!$B$4,"Date after the as-of date",IF($B5<Config!$B$5,"Date before the opening balance date","OK"))))))))))))))))) -> OK
A6: MV-2607-004 | B6: 46234 | C6: Shipment | D6: WPI-VAN-2LB | E6: 182 | F6: WVA2411A | H6: OB-2607 | I6: https://example.com/3pl/outbound/2026-07 | J6: 3PL import | K6: warehouse-movements-2026-07.csv | L6: July outbound summary (FEFO) | M6: =IF(NOT(ISNUMBER($E6)),"",IF($C6="Receipt",$E6,IF($C6="Shipment",-$E6,IF($C6="Adjustment",$E6,0)))) -> -182 | N6: =IF($D6="","",IFERROR(INDEX(Products!$B$2:$B$101,MATCH($D6,Products!$A$2:$A$101,0))&"","(not found)")) -> Whey Protein Isolate, Vanilla, 2 lb | O6: =IF($F6="","",IFERROR(INDEX(Batches!$B$2:$B$301,MATCH($F6,Batches!$A$2:$A$301,0))&"","(not found)")) -> WPI-VAN-2LB | P6: =IF(COUNTA($A6:$L6)=0,"",IF($A6="","Missing: entry ID",IF(COUNTIF($A$2:$A$2001,$A6)>1,"Duplicate entry ID",IF(NOT(ISNUMBER($B6)),"Missing or invalid: date",IF($C6="","Missing: type",IF($D6="","Missing: SKU",IF(NOT(ISNUMBER($E6)),"Missing: qty",IF($F6="","Missing: lot",IF($I6="","Missing: source link",IF(COUNTIF(Config!$A$15:$A$34,$C6)=0,"Unsupported type",IF(COUNTIF(Products!$A$2:$A$101,$D6)=0,"Unknown SKU",IF(COUNTIFS(Batches!$A$2:$A$301,$F6,Batches!$B$2:$B$301,$D6)=0,"Unknown lot for this SKU",IF(AND($C6="Adjustment",$G6=""),"Missing: reason",IF(AND($G6<>"",COUNTIF(Config!$B$15:$B$34,$G6)=0),"Unsupported reason",IF(OR(INT($E6)<>$E6,AND(OR($C6="Receipt",$C6="Shipment"),$E6<=0),AND($C6="Adjustment",$E6=0)),"Invalid qty",IF($B6>Config!$B$4,"Date after the as-of date",IF($B6<Config!$B$5,"Date before the opening balance date","OK"))))))))))))))))) -> OK
A7: MV-2607-005 | B7: 46234 | C7: Shipment | D7: WPI-CHO-5LB | E7: 59 | F7: W5C2501A | H7: OB-2607 | I7: https://example.com/3pl/outbound/2026-07 | J7: 3PL import | K7: warehouse-movements-2026-07.csv | L7: July outbound summary (FEFO) | M7: =IF(NOT(ISNUMBER($E7)),"",IF($C7="Receipt",$E7,IF($C7="Shipment",-$E7,IF($C7="Adjustment",$E7,0)))) -> -59 | N7: =IF($D7="","",IFERROR(INDEX(Products!$B$2:$B$101,MATCH($D7,Products!$A$2:$A$101,0))&"","(not found)")) -> Whey Protein Isolate, Chocolate, 5 lb | O7: =IF($F7="","",IFERROR(INDEX(Batches!$B$2:$B$301,MATCH($F7,Batches!$A$2:$A$301,0))&"","(not found)")) -> WPI-CHO-5LB | P7: =IF(COUNTA($A7:$L7)=0,"",IF($A7="","Missing: entry ID",IF(COUNTIF($A$2:$A$2001,$A7)>1,"Duplicate entry ID",IF(NOT(ISNUMBER($B7)),"Missing or invalid: date",IF($C7="","Missing: type",IF($D7="","Missing: SKU",IF(NOT(ISNUMBER($E7)),"Missing: qty",IF($F7="","Missing: lot",IF($I7="","Missing: source link",IF(COUNTIF(Config!$A$15:$A$34,$C7)=0,"Unsupported type",IF(COUNTIF(Products!$A$2:$A$101,$D7)=0,"Unknown SKU",IF(COUNTIFS(Batches!$A$2:$A$301,$F7,Batches!$B$2:$B$301,$D7)=0,"Unknown lot for this SKU",IF(AND($C7="Adjustment",$G7=""),"Missing: reason",IF(AND($G7<>"",COUNTIF(Config!$B$15:$B$34,$G7)=0),"Unsupported reason",IF(OR(INT($E7)<>$E7,AND(OR($C7="Receipt",$C7="Shipment"),$E7<=0),AND($C7="Adjustment",$E7=0)),"Invalid qty",IF($B7>Config!$B$4,"Date after the as-of date",IF($B7<Config!$B$5,"Date before the opening balance date","OK"))))))))))))))))) -> OK
A8: MV-2607-006 | B8: 46234 | C8: Shipment | D8: PLT-CHO-2LB | E8: 134 | F8: PCH2412A | H8: OB-2607 | I8: https://example.com/3pl/outbound/2026-07 | J8: 3PL import | K8: warehouse-movements-2026-07.csv | L8: July outbound summary (FEFO) | M8: =IF(NOT(ISNUMBER($E8)),"",IF($C8="Receipt",$E8,IF($C8="Shipment",-$E8,IF($C8="Adjustment",$E8,0)))) -> -134 | N8: =IF($D8="","",IFERROR(INDEX(Products!$B$2:$B$101,MATCH($D8,Products!$A$2:$A$101,0))&"","(not found)")) -> Plant Protein, Chocolate, 2 lb | O8: =IF($F8="","",IFERROR(INDEX(Batches!$B$2:$B$301,MATCH($F8,Batches!$A$2:$A$301,0))&"","(not found)")) -> PLT-CHO-2LB | P8: =IF(COUNTA($A8:$L8)=0,"",IF($A8="","Missing: entry ID",IF(COUNTIF($A$2:$A$2001,$A8)>1,"Duplicate entry ID",IF(NOT(ISNUMBER($B8)),"Missing or invalid: date",IF($C8="","Missing: type",IF($D8="","Missing: SKU",IF(NOT(ISNUMBER($E8)),"Missing: qty",IF($F8="","Missing: lot",IF($I8="","Missing: source link",IF(COUNTIF(Config!$A$15:$A$34,$C8)=0,"Unsupported type",IF(COUNTIF(Products!$A$2:$A$101,$D8)=0,"Unknown SKU",IF(COUNTIFS(Batches!$A$2:$A$301,$F8,Batches!$B$2:$B$301,$D8)=0,"Unknown lot for this SKU",IF(AND($C8="Adjustment",$G8=""),"Missing: reason",IF(AND($G8<>"",COUNTIF(Config!$B$15:$B$34,$G8)=0),"Unsupported reason",IF(OR(INT($E8)<>$E8,AND(OR($C8="Receipt",$C8="Shipment"),$E8<=0),AND($C8="Adjustment",$E8=0)),"Invalid qty",IF($B8>Config!$B$4,"Date after the as-of date",IF($B8<Config!$B$5,"Date before the opening balance date","OK"))))))))))))))))) -> OK
A9: MV-2607-007 | B9: 46234 | C9: Shipment | D9: PLT-VAN-2LB | E9: 85 | F9: PVA2411A | H9: OB-2607 | I9: https://example.com/3pl/outbound/2026-07 | J9: 3PL import | K9: warehouse-movements-2026-07.csv | L9: July outbound summary (FEFO) | M9: =IF(NOT(ISNUMBER($E9)),"",IF($C9="Receipt",$E9,IF($C9="Shipment",-$E9,IF($C9="Adjustment",$E9,0)))) -> -85 | N9: =IF($D9="","",IFERROR(INDEX(Products!$B$2:$B$101,MATCH($D9,Products!$A$2:$A$101,0))&"","(not found)")) -> Plant Protein, Vanilla, 2 lb | O9: =IF($F9="","",IFERROR(INDEX(Batches!$B$2:$B$301,MATCH($F9,Batches!$A$2:$A$301,0))&"","(not found)")) -> PLT-VAN-2LB | P9: =IF(COUNTA($A9:$L9)=0,"",IF($A9="","Missing: entry ID",IF(COUNTIF($A$2:$A$2001,$A9)>1,"Duplicate entry ID",IF(NOT(ISNUMBER($B9)),"Missing or invalid: date",IF($C9="","Missing: type",IF($D9="","Missing: SKU",IF(NOT(ISNUMBER($E9)),"Missing: qty",IF($F9="","Missing: lot",IF($I9="","Missing: source link",IF(COUNTIF(Config!$A$15:$A$34,$C9)=0,"Unsupported type",IF(COUNTIF(Products!$A$2:$A$101,$D9)=0,"Unknown SKU",IF(COUNTIFS(Batches!$A$2:$A$301,$F9,Batches!$B$2:$B$301,$D9)=0,"Unknown lot for this SKU",IF(AND($C9="Adjustment",$G9=""),"Missing: reason",IF(AND($G9<>"",COUNTIF(Config!$B$15:$B$34,$G9)=0),"Unsupported reason",IF(OR(INT($E9)<>$E9,AND(OR($C9="Receipt",$C9="Shipment"),$E9<=0),AND($C9="Adjustment",$E9=0)),"Invalid qty",IF($B9>Config!$B$4,"Date after the as-of date",IF($B9<Config!$B$5,"Date before the opening balance date","OK"))))))))))))))))) -> OK
A10: MV-2607-008 | B10: 46234 | C10: Shipment | D10: BAR-PBC-12 | E10: 562 | F10: PBC2511A | H10: OB-2607 | I10: https://example.com/3pl/outbound/2026-07 | J10: 3PL import | K10: warehouse-movements-2026-07.csv | L10: July outbound summary (FEFO) | M10: =IF(NOT(ISNUMBER($E10)),"",IF($C10="Receipt",$E10,IF($C10="Shipment",-$E10,IF($C10="Adjustment",$E10,0)))) -> -562 | N10: =IF($D10="","",IFERROR(INDEX(Products!$B$2:$B$101,MATCH($D10,Products!$A$2:$A$101,0))&"","(not found)")) -> Protein Bar, Peanut Butter Chocolate, 12-pack | O10: =IF($F10="","",IFERROR(INDEX(Batches!$B$2:$B$301,MATCH($F10,Batches!$A$2:$A$301,0))&"","(not found)")) -> BAR-PBC-12 | P10: =IF(COUNTA($A10:$L10)=0,"",IF($A10="","Missing: entry ID",IF(COUNTIF($A$2:$A$2001,$A10)>1,"Duplicate entry ID",IF(NOT(ISNUMBER($B10)),"Missing or invalid: date",IF($C10="","Missing: type",IF($D10="","Missing: SKU",IF(NOT(ISNUMBER($E10)),"Missing: qty",IF($F10="","Missing: lot",IF($I10="","Missing: source link",IF(COUNTIF(Config!$A$15:$A$34,$C10)=0,"Unsupported type",IF(COUNTIF(Products!$A$2:$A$101,$D10)=0,"Unknown SKU",IF(COUNTIFS(Batches!$A$2:$A$301,$F10,Batches!$B$2:$B$301,$D10)=0,"Unknown lot for this SKU",IF(AND($C10="Adjustment",$G10=""),"Missing: reason",IF(AND($G10<>"",COUNTIF(Config!$B$15:$B$34,$G10)=0),"Unsupported reason",IF(OR(INT($E10)<>$E10,AND(OR($C10="Receipt",$C10="Shipment"),$E10<=0),AND($C10="Adjustment",$E10=0)),"Invalid qty",IF($B10>Config!$B$4,"Date after the as-of date",IF($B10<Config!$B$5,"Date before the opening balance date","OK"))))))))))))))))) -> OK
A11: MV-2607-009 | B11: 46234 | C11: Shipment | D11: BAR-CKD-12 | E11: 521 | F11: CKD2510A | H11: OB-2607 | I11: https://example.com/3pl/outbound/2026-07 | J11: 3PL import | K11: warehouse-movements-2026-07.csv | L11: July outbound summary (FEFO) | M11: =IF(NOT(ISNUMBER($E11)),"",IF($C11="Receipt",$E11,IF($C11="Shipment",-$E11,IF($C11="Adjustment",$E11,0)))) -> -521 | N11: =IF($D11="","",IFERROR(INDEX(Products!$B$2:$B$101,MATCH($D11,Products!$A$2:$A$101,0))&"","(not found)")) -> Protein Bar, Cookie Dough, 12-pack | O11: =IF($F11="","",IFERROR(INDEX(Batches!$B$2:$B$301,MATCH($F11,Batches!$A$2:$A$301,0))&"","(not found)")) -> BAR-CKD-12 | P11: =IF(COUNTA($A11:$L11)=0,"",IF($A11="","Missing: entry ID",IF(COUNTIF($A$2:$A$2001,$A11)>1,"Duplicate entry ID",IF(NOT(ISNUMBER($B11)),"Missing or invalid: date",IF($C11="","Missing: type",IF($D11="","Missing: SKU",IF(NOT(ISNUMBER($E11)),"Missing: qty",IF($F11="","Missing: lot",IF($I11="","Missing: source link",IF(COUNTIF(Config!$A$15:$A$34,$C11)=0,"Unsupported type",IF(COUNTIF(Products!$A$2:$A$101,$D11)=0,"Unknown SKU",IF(COUNTIFS(Batches!$A$2:$A$301,$F11,Batches!$B$2:$B$301,$D11)=0,"Unknown lot for this SKU",IF(AND($C11="Adjustment",$G11=""),"Missing: reason",IF(AND($G11<>"",COUNTIF(Config!$B$15:$B$34,$G11)=0),"Unsupported reason",IF(OR(INT($E11)<>$E11,AND(OR($C11="Receipt",$C11="Shipment"),$E11<=0),AND($C11="Adjustment",$E11=0)),"Invalid qty",IF($B11>Config!$B$4,"Date after the as-of date",IF($B11<Config!$B$5,"Date before the opening balance date","OK"))))))))))))))))) -> OK
A12: MV-2607-010 | B12: 46234 | C12: Shipment | D12: CRE-UNF-300G | E12: 236 | F12: CRT2502A | H12: OB-2607 | I12: https://example.com/3pl/outbound/2026-07 | J12: 3PL import | K12: warehouse-movements-2026-07.csv | L12: July outbound summary (FEFO) | M12: =IF(NOT(ISNUMBER($E12)),"",IF($C12="Receipt",$E12,IF($C12="Shipment",-$E12,IF($C12="Adjustment",$E12,0)))) -> -236 | N12: =IF($D12="","",IFERROR(INDEX(Products!$B$2:$B$101,MATCH($D12,Products!$A$2:$A$101,0))&"","(not found)")) -> Creatine Monohydrate, Unflavoured, 300 g | O12: =IF($F12="","",IFERROR(INDEX(Batches!$B$2:$B$301,MATCH($F12,Batches!$A$2:$A$301,0))&"","(not found)")) -> CRE-UNF-300G | P12: =IF(COUNTA($A12:$L12)=0,"",IF($A12="","Missing: entry ID",IF(COUNTIF($A$2:$A$2001,$A12)>1,"Duplicate entry ID",IF(NOT(ISNUMBER($B12)),"Missing or invalid: date",IF($C12="","Missing: type",IF($D12="","Missing: SKU",IF(NOT(ISNUMBER($E12)),"Missing: qty",IF($F12="","Missing: lot",IF($I12="","Missing: source link",IF(COUNTIF(Config!$A$15:$A$34,$C12)=0,"Unsupported type",IF(COUNTIF(Products!$A$2:$A$101,$D12)=0,"Unknown SKU",IF(COUNTIFS(Batches!$A$2:$A$301,$F12,Batches!$B$2:$B$301,$D12)=0,"Unknown lot for this SKU",IF(AND($C12="Adjustment",$G12=""),"Missing: reason",IF(AND($G12<>"",COUNTIF(Config!$B$15:$B$34,$G12)=0),"Unsupported reason",IF(OR(INT($E12)<>$E12,AND(OR($C12="Receipt",$C12="Shipment"),$E12<=0),AND($C12="Adjustment",$E12=0)),"Invalid qty",IF($B12>Config!$B$4,"Date after the as-of date",IF($B12<Config!$B$5,"Date before the opening balance date","OK"))))))))))))))))) -> OK
A13: MV-2607-011 | B13: 46234 | C13: Shipment | D13: CRE-UNF-500G | E13: 106 | F13: CRL2504A | H13: OB-2607 | I13: https://example.com/3pl/outbound/2026-07 | J13: 3PL import | K13: warehouse-movements-2026-07.csv | L13: July outbound summary (FEFO) | M13: =IF(NOT(ISNUMBER($E13)),"",IF($C13="Receipt",$E13,IF($C13="Shipment",-$E13,IF($C13="Adjustment",$E13,0)))) -> -106 | N13: =IF($D13="","",IFERROR(INDEX(Products!$B$2:$B$101,MATCH($D13,Products!$A$2:$A$101,0))&"","(not found)")) -> Creatine Monohydrate, Unflavoured, 500 g | O13: =IF($F13="","",IFERROR(INDEX(Batches!$B$2:$B$301,MATCH($F13,Batches!$A$2:$A$301,0))&"","(not found)")) -> CRE-UNF-500G | P13: =IF(COUNTA($A13:$L13)=0,"",IF($A13="","Missing: entry ID",IF(COUNTIF($A$2:$A$2001,$A13)>1,"Duplicate entry ID",IF(NOT(ISNUMBER($B13)),"Missing or invalid: date",IF($C13="","Missing: type",IF($D13="","Missing: SKU",IF(NOT(ISNUMBER($E13)),"Missing: qty",IF($F13="","Missing: lot",IF($I13="","Missing: source link",IF(COUNTIF(Config!$A$15:$A$34,$C13)=0,"Unsupported type",IF(COUNTIF(Products!$A$2:$A$101,$D13)=0,"Unknown SKU",IF(COUNTIFS(Batches!$A$2:$A$301,$F13,Batches!$B$2:$B$301,$D13)=0,"Unknown lot for this SKU",IF(AND($C13="Adjustment",$G13=""),"Missing: reason",IF(AND($G13<>"",COUNTIF(Config!$B$15:$B$34,$G13)=0),"Unsupported reason",IF(OR(INT($E13)<>$E13,AND(OR($C13="Receipt",$C13="Shipment"),$E13<=0),AND($C13="Adjustment",$E13=0)),"Invalid qty",IF($B13>Config!$B$4,"Date after the as-of date",IF($B13<Config!$B$5,"Date before the opening balance date","OK"))))))))))))))))) -> OK
A14: MV-2607-012 | B14: 46234 | C14: Shipment | D14: PRE-BRZ-30 | E14: 217 | F14: PBZ2501A | H14: OB-2607 | I14: https://example.com/3pl/outbound/2026-07 | J14: 3PL import | K14: warehouse-movements-2026-07.csv | L14: July outbound summary (FEFO) | M14: =IF(NOT(ISNUMBER($E14)),"",IF($C14="Receipt",$E14,IF($C14="Shipment",-$E14,IF($C14="Adjustment",$E14,0)))) -> -217 | N14: =IF($D14="","",IFERROR(INDEX(Products!$B$2:$B$101,MATCH($D14,Products!$A$2:$A$101,0))&"","(not found)")) -> Pre-Workout, Blue Raspberry, 30 servings | O14: =IF($F14="","",IFERROR(INDEX(Batches!$B$2:$B$301,MATCH($F14,Batches!$A$2:$A$301,0))&"","(not found)")) -> PRE-BRZ-30 | P14: =IF(COUNTA($A14:$L14)=0,"",IF($A14="","Missing: entry ID",IF(COUNTIF($A$2:$A$2001,$A14)>1,"Duplicate entry ID",IF(NOT(ISNUMBER($B14)),"Missing or invalid: date",IF($C14="","Missing: type",IF($D14="","Missing: SKU",IF(NOT(ISNUMBER($E14)),"Missing: qty",IF($F14="","Missing: lot",IF($I14="","Missing: source link",IF(COUNTIF(Config!$A$15:$A$34,$C14)=0,"Unsupported type",IF(COUNTIF(Products!$A$2:$A$101,$D14)=0,"Unknown SKU",IF(COUNTIFS(Batches!$A$2:$A$301,$F14,Batches!$B$2:$B$301,$D14)=0,"Unknown lot for this SKU",IF(AND($C14="Adjustment",$G14=""),"Missing: reason",IF(AND($G14<>"",COUNTIF(Config!$B$15:$B$34,$G14)=0),"Unsupported reason",IF(OR(INT($E14)<>$E14,AND(OR($C14="Receipt",$C14="Shipment"),$E14<=0),AND($C14="Adjustment",$E14=0)),"Invalid qty",IF($B14>Config!$B$4,"Date after the as-of date",IF($B14<Config!$B$5,"Date before the opening balance date","OK"))))))))))))))))) -> OK
